Workbook
Name EndingBalance: -FV(InterestRate/12,PaymentNumber,-MonthlyPayment,LoanAmount)
Name Fabricator: lists!$K$2:$L$2
Name Gym_Package: lists!$C$2:$C$5
Name Gym_Shape: lists!$B$2:$B$4
Name Gym_Type: lists!$A$2:$A$4
Name HeaderRow: ROW(#REF!)
Name InterestAmt: -IPMT(InterestRate/12,PaymentNumber,NumberOfPayments,LoanAmount)
Name InterestRate: #REF!
Name LastRow: MATCH(9.99E+307,#REF!)
Name LoanAmount: #REF!
Name LoanIsGood: IF(LoanAmount*InterestRate*LoanYears*LoanStartDate>0,1,0)
Name LoanIsNotPaid: IF(PaymentNumber<=NumberOfPayments,1,0)
Name LoanStartDate: #REF!
Name LoanValue: -FV(InterestRate/12,PaymentNumber-1,-MonthlyPayment,LoanAmount)
Name LoanYears: #REF!
Name MonthlyPayment: -PMT(InterestRate/12,NumberOfPayments,LoanAmount)
Name NumberOfPayments: #REF!
Name PaymentDate: DATE(YEAR(LoanStartDate),MONTH(LoanStartDate)+PaymentNumber,DAY(LoanStartDate))
Name PaymentNumber: ROW()-HeaderRow
Name Powder_Brand: #REF!
Name Principal: -PPMT(InterestRate/12,PaymentNumber,NumberOfPayments,LoanAmount)
Name Shields: lists!$D$2:$D$3
Name TotalLoanCost: #REF!

Sheet Discovery
A1: PROJECT DISCOVERY INPUT | E1: Project Template Revision Log
A2: Client Name: | B2: =ZAPIER!C5 -> Tyler Galiotto | E2: Revision | F2: Description of changes made | G2: Made by: | H2: Date:
A3: Organization Name: | B3: =ZAPIER!D5 -> Soar Autism Center - South Fort Collins | E3: 1 | F3: Added logo parts and updated pricing and quoting sheet | G3: Kmaurer | H3: 44784
A4: Organization Address: | B4: =ZAPIER!E5 -> 3801 Automation Way | E4: 2 | F4: Added Alternating hole parts | G4: Kmaurer | H4: 44901
A5: Organization City & State: | B5: =ZAPIER!F5&", "&ZAPIER!G5 -> Fort Collins, CO | E5: 3 | F5: Added Margin dollar amount and fixed a couple quote tab issues | G5: Kmaurer | H5: 44932
A6: Organization Zip Code: | B6: =ZAPIER!H5 -> 80525 | E6: 4 | F6: Updated quote tab headers and added low ceiling parts | G6: Kmaurer | H6: 44938
A7: Ship to Address: | B7: =B4 -> 3801 Automation Way | E7: 5 | F7: Added 3 quote options and organized the calcs tabs | G7: Kmaurer | H7: 44978
A8: Ship to City & State: | B8: =B5 -> Fort Collins, CO | E8: 6 | F8: Corrected 1/2" washer price from $11.00 to $0.28 | G8: Kmaurer | H8: 44992
A9: Ship to Zip Code: | B9: =B6 -> 80525 | E9: 7 | F9: Quoting tab; Moved Trolley steel parts into trolley portion | G9: Kmaurer | H9: 45001
A10: Country: | B10: =ZAPIER!I5 -> United States | E10: 8 | F10: Added weight calcs for each component | G10: Kmaurer
A11: Phone: | B11: =ZAPIER!J5 -> 5203895979 | E11: 9 | F11: Corrected 3/8" monkey bar bolt quantities | G11: Kmaurer | H11: 45079
A12: Email Address: | B12: =ZAPIER!K5 | E12: 10 | F12: Updated TRT 2001 from $96 to $106, quote creation time stamp & Goldberg Order Details | G12: Kmaurer | H12: 45098
A13: Project ID: | B13: =ZAPIER!B2 -> 12552093278 | E13: 11 | F13: Added Mail_Workbook macro and email worksheet button to order details tab | G13: Kmaurer | H13: 45101
A14: CUSTOMS & DUTES | B14: =SUM(B15:B16) -> 0 | E14: 12 | F14: Added $100 crating fee to shipping calculations | G14: BShepherd | H14: 45102
A15: Customs Fees | B15: 0 | E15: 13 | F15: Added discount logic to quote page | G15: BShepherd | H15: 45102
A16: Border Buddy Fees | B16: 0 | E16: 14 | F16: Added calculations to quote for accessory brackets, eyebolts, swivel bolt | G16: BShepherd | H16: 45102
A17: TRAVEL | B17: No | E17: 15 | F17: Updated formula on Calcs tab - If quantity is negative, the total will return a zero $ result | G17: BShepherd | H17: 45102
A18: Estimated Travel Expenses | B18: 0 | E18: 16 | F18: Added invoice tab & added payment calculation data for invoice tab | G18: BShepherd | H18: 45112
A19: Estimated Freight Cost-Goldberg | B19: TBD | C19: =IF(B19=0,"TBD",B19) -> TBD | E19: 17 | F19: Updated Goldberg pricing per part based on order details sent and updated 1/2 nuts qty per | G19: KMaurer | H19: 45114
A20: Estimated Freight - 3rd Party Orders | B20: 0 | C20: =IF(B20=0,"TBD",B20) -> TBD | E20: 18 | F20: Added trolley weights to total shipment weight on Goldberg Order Details tab | G20: Kmaurer | H20: 45117
A21: RESILITE INTEREST | B21: Yes | E21: 19 | F21: Add various calculations to Calcs tab - Will allow us to determine max discount rate while still obtaining a 100% mark up | G21: BShepherd | H21: 45120
A22: Estimated Resilite Product Cost | B22: =Calcs!N176 -> 0 | E22: 20 | F22: Add several accessory items to the calcs tab - Product numbers are associated Amazon ASIN # | G22: BShepherd | H22: 45126
B23: ENTER RESILITE RATE FROM WEBSITE
A24: Estimated Freight Cost | B24: 859.14 | C24: =IF(B24=0,"TBD",B24) -> 859.14 | E24: 21 | F24: Corrected 6820H-024 hardware calculation | G24: Kmaurer | H24: 45134
A25: Estimated State & Local Tax | B25: 294.07 | C25: =IF(B25="TBD","TBD",B25) -> 294.07 | E25: 22 | F25: Corrected 6820H-023 description to 5/16" bolt | G25: Kmaurer | H25: 45134
A26: Column Mats | B26: Yes | E26: 23 | F26: Added Calculations for single and double ladder leg sleeves, changed Zip Line kit, TRT-2001 price | G26: Kmaurer | H26: 45145
A27: Floor Mats | B27: Yes | E27: 24 | F27: Corrected calculation for 1/2"-13 X 4.5" Bolt | G27: KMaurer | H27: 45161
A28: Proposal Description Prefix Add-On | E28: 25 | F28: Corrected calculation for 3/8"-16 x 2.25" 6820H-013 | G28: KMaurer | H28: 45181
A29: Product Line: | B29: Summit Adventure Series | E29: 26 | F29: Fixed all the SaveAsPDF macros | G29: KMaurer | H29: 45189
A30: Gym Type: | B30: Clinic | E30: 27 | F30: Added 6820H-031 & 6820H-032 for the V-Ring and hardware. Need to update costs. | G30: KMaurer | H30: 45195
A31: Shape: | B31: Rectangle | E31: 28 | F31: Fixed 6820H-013 3/8"x2.25" bolt quantity calcs | G31: Kmaurer | H31: 45212
A32: Gym Package: | B32: Lien | E32: 29 | F32: Updated entire workbook to switch to <80" member sizes affecting 10' HRZ, Verticals & Corner Posts | G32: Kmaurer | H32: 45239
A33: Tax Exempt | B33: Yes | C33: =IF(B33="No",'Adventure Series Proposal (USA)'!H230-'Adventure Series Proposal (USA)'!H231,"") | E33: 30 | F33: Added Summit Slide and Summit Climb Color selection and udpated Goldberg Order Details | G33: Kmaurer | H33: 45300
A34: Combined Tax Rate | B34: =IF(B33="No",VLOOKUP(B6,#REF!,2,FALSE),0) -> 0 | C34: =IF(B33="No",(C19+C24+C33)*B34,"") | E34: 31 | F34: Added the additional Resilite mat options to the proposal | G34: BShepherd | H34: 45302
A35: Size LENGTH inches (LONG): | B35: 120 | C35: =B35/12 -> 10 | E35: 32 | F35: Transitioned all A-2016 mid saddle brackets to A-2225 | G35: Kmaurer | H35: 45313
A36: Size WIDTH inches (SHORT): | B36: 120 | C36: =B36/12 -> 10 | E36: 33 | F36: Updated P-2209 & P2219 to the <80 A-2409 & A-2419 | G36: Kmaurer | H36: 45329
A37: Size HEIGHT inches: | B37: 96 | C37: =B37/12 -> 8 | E37: 34 | F37: Updated our playground handle cost from $11.99 to $30 that Goldberg is charging us. | G37: Kmaurer | H37: 45362
A38: Number of Accessory Brackets: | B38: 4 | E38: 35 | F38: Updated the Handles from quantity per set of 2 to quantity per handle | G38: Kmaurer | H38: 45363
A39: Number of 3/8" Swivel Eyebolts for accessory saddle brackets | B39: 4 | C39: NOTE: $74.95/each | E39: 36 | F39: Moved Goldberg Order Details tab next to Calcs tab for convenience | G39: Kmaurer | H39: 45368
A40: Number of 3/8" non-swivel eyebolts for accessory saddle brackets | B40: =B38-B39 -> 0 | C40: NOTE: $5.07/each | E40: 37 | F40: Updated Goldberg Order Details tab to mark zipline wire rope and zipline trolley prices as $0 | G40: Kmaurer | H40: 45378
A41: Base Plate Shields | B41: Yes | E41: 38 | F41: Updated 1/4" handle bolt calcs | G41: Kmaurer | H41: 45443
A42: Number of 1/2" Forged Eyebolts | B42: 12 | C42: NOTE: Typically send 12 | E42: 39 | F42: Updated all Adventure series parts from G2 to G3 <80" | G42: Kmaurer | H42: 45462
A43: Number of V-Rings | B43: 20 | E43: 40 | F43: Updated wedge anchor quantity per from box of 25 to price per anchor | G43: Kmaurer | H43: 45502
A44: Powder Coat Brand | B44: Cardinal | C44: Prismatic is $250(our cost) custom color upcharge | E44: 41 | F44: Updated Threaded Rod Hanger price from $81 to $96.05 & updated Trolley PO shipping method | G44: Kmaurer | H44: 45526
A45: Prismatic-Other (Custom Color Cost) | B45: 800 | E45: 42 | F45: Updated all Hardware Pricing per emailed list from John | G45: Kmaurer | H45: 45527
E46: 43 | F46: Updated Resilite Column Wraps to the new SKU and pricing | G46: Kmaurer | H46: 45534
A47: Color Spec: A(Verticals/Base Shields) | B47: CHANGEME | C47: Include Color spec numbers | E47: 44 | F47: Fixed Trolley quantities and costs on Goldberg Order Details Tab | G47: Kmaurer | H47: 45597
A48: Color Spec: B(Horizontals/corner posts) | B48: CHANGEME | C48: Include Color spec numbers | E48: 45 | F48: Updated A-2210 slide platform to A-2216 latest tube rail slide platform | G48: Kmaurer | H48: 45639
A49: Color Spec: C(Monkey Bars/ladder verts/saddle brkts) | B49: CHANGEME | C49: Include Color spec numbers | E49: 46 | F49: Added product item "SP0810CLM" within Calcs tab & Adventure Proposal tab | G49: BShepherd | H49: 45646
A50: Color Spec: Summit Slide Platform | B50: CHANGEME | C50: Include Color spec numbers | E50: 47 | F50: Added product item "T11412" within Calcs tab & Adventure Proposal tab | G50: BShepherd | H50: 45664
A51: Color Spec: Summit Climb | B51: CHANGEME | C51: Include Color spec numbers | E51: 48 | F51: Added product item "T11412-Freight" within Calcs tab & Adventure Proposal Tab | G51: BShepherd | H51: 45664
E52: 49 | F52: Added freight cost line item for product item "T11412-Freight" within Discovery Tab - Freight costs for the adjustable climbing wall that we purchase from eSpecial Needs will appear on the Adventure Proposal tab | G52: BShepherd | H52: 45664
A53: Quote Creation Date: | B53: =TODAY() -> 46225 | E53: 50 | F53: Added calculations for Canadian customs and duties - If Canada is selected on the discovery tab, it will automatically add "Canadian Customs & Duties Fees" to Adventure Proposal template. The customs and duties fees should be entered on column A, under "customs fees" and "border buddy fees". The sum of these two numbers will then be added to the total cost on the adventure proposal tab within the proposal. | G53: BShepherd | H53: 45670
A54: Project Number: | B54: {=_xlfn.LET( _xlpm.d, B53, _xlpm.initials, UPPER(LEFT(B2,1) & RIGHT(B2,1)), _xlpm.n, COUNTIFS($B$2:B2, C2, $A$2:A2, A2), "PR-" & _xlpm.initials & "-" & TEXT(_xlpm.d, "yymmdd") & "-" & TEXT(_xlpm.n, "000") )} -> PR-TO-260722-000 | E54: 51 | F54: Additional product added to calc tab: 2 Hole Heavy Duty Aluminum Swing Hangers | G54: BShepherd | H54: 45698
A55: Customer #: | B55: =RANDBETWEEN(1000,24676)*3 -> 8283 | E55: 52 | F55: Cost for the Wheelchair Swing Platform - Adult was updated - Cost increased | G55: BShepherd | H55: 45699
E56: 53 | F56: : RSS2422 and RSS2433 | G56: BShepherd | H56: 45699
E57: 54 | F57: Updated cost of Trolley Threaded Rod Hanger TRH2005 from $96.05 to $113 | G57: Kmaurer
E58: 55 | F58: Added pricing for leather belts within Calc tab under UEU | G58: BShepherd | H58: 45713
E59: 56 | F59: Resilite floor padding costs have been modified for all sizes of mats | G59: BShepherd | H59: 45730
E60: 57 | F60: Product: UEU TheraBungee was added to the product offering under Calcs>Summit Soar | G60: BShepherd | H60: 45733
E61: 58 | F61: Updated single swivel eye bolt 6820H-LD to 6820H-LDD double swivel eye bolt and price from $71 to $78.38 | G61: Kmaurer | H61: 45735
E62: 59 | F62: Modified some of the formulas inside of the calc tab under Summit Flex - Removed a few unused bungee cords that we previously sold | G62: BShepherd | H62: 45741
E63: 60 | F63: UEU - Tracking Rail System was added to calc tab along with the necessary line items for it to be added. | G63: BShepherd | H63: 45741
E64: 61 | F64: Added UEU-TRS Flex Overhead Trolley Rail costs and weight | G64: Kmaurer | H64: 45743
E65: 62 | F65: Updated Flex mat to single SKU (SSFLEX69722) for the 2-piece mat | G65: Kmaurer | H65: 45743
E66: 63 | F66: Updated List tab to the G3 parts along with correcting a few minor pricing discrepancies and adding VLOOKUP between steel and trolley parts to List tab | G66: Kmaurer | H66: 45750
E67: 64 | F67: Added A-2349 Steamroller Converstion Kit to Lists and Calcs tabs | G67: Kmaurer | H67: 45756
E68: 65 | F68: Added SP0610CLM to Calcs, and Adventure Series Proposal tabs | G68: BShepherd | H68: 45766
E69: 66 | F69: Updated single and double Ladder leg sleeves to inner sleeves and added 6820-LAH button head 3/8" bolts for all ladder rung connections. | G69: Kmaurer | H69: 45771
... E94: 91 | F94: Updated 6820H-LB needed quantity to add F218*2 | G94: Kmaurer | H94: 46218

Sheet VLOOKUP
A1: Interlocking Floor Padding Calculator | D1: =F3&F12&F4&F5&F7&F8&F17&F18 -> SQ-2MBL2T | F1: =D1&"-"&F9&"x"&F10 -> SQ-2MBL2T-10x10 | J1: Horizontal Beams | M1: L Shape | N1: INTERIOR BEAM | O1: MONKEY BAR | P1: LADDER | R1: TOTAL
A2: LENGTH (Inches) | B2: 120 | H2: PART # | I2: DESCRIPTION | J2: 4 | K2: 7 | L2: 10
A3: WIDTH (Inches) | B3: 120 | D3: Design Layout | E3: Square | F3: {=_xlfn.IFS(E3="-","",E3="Square","SQ-",E3="rectangle","R-",E3="L Shape","L-",E3="T Shape","T-")} -> SQ- | H3: A-2245 | I3: =VLOOKUP(H3,Calcs!C:D,2,FALSE) -> Vertical Tall <80 w/Gusset | J3: =IF(E6=4,4,0) -> 4 | K3: =IF(E6=6,6,0) -> 0 | L3: =IF(E6=8,8,0) -> 0 | P3: =E7*-1 -> -2 | R3: =SUM(J3:N3)+SUM(O3:P3) -> 2
A4: AREA SQ FT | B4: =(B2/12)*(B3/12) -> 100 | D4: Monkey Bars | E4: Yes | F4: =IF(E4="Yes","MB","") -> MB | H4: A-2246 | I4: =VLOOKUP(H4,Calcs!C:D,2,FALSE) -> Vertical Tall <80 w/Gussets, Rungs & Handles | P4: =E7 -> 2 | R4: =SUM(J4:N4)+SUM(O4:P4) -> 2
A5: # of Tiles | B5: =B4/4 -> 25 | D5: # - Monkey Bar Sets | E5: 1 | F5: =IF(E5=2,2,"") | H5: A-2241 | I5: =VLOOKUP(H5,Calcs!C:D,2,FALSE) -> Corner Post <80 1-Way Weld Assembly | R5: =SUM(J5:N5)+SUM(O5:P5) -> 0
A6: 10% Overage | B6: =B5*1.1 -> 27.5 | D6: # - Legs | E6: 4 | H6: A-2242 | I6: =VLOOKUP(H6,Calcs!C:D,2,FALSE) -> Corner Post <80 2-Way Weld Assembly | J6: =IF(E6>0.01,4,0) -> 4 | M6: =IF(E3="L Shape",1,0) -> 0 | R6: =SUM(J6:N6)+SUM(O6:P6) -> 4
A7: 15% Overage | B7: =B5*1.15 -> 28.75 | D7: # - Ladders | E7: 2 | F7: {=_xlfn.IFS(E7=4,"L4",E7=0,"",E7=2,"L2",E7=1,"L1",E7=3,"L3")} -> L2 | H7: A-2243 | I7: =VLOOKUP(H7,Calcs!C:D,2,FALSE) -> Corner Post <80 3-Way Weld Assembly | K7: =IF(E6=6,2,0) -> 0 | L7: =IF(E6=8,4,0) -> 0 | M7: =IF(E3="L Shape",-2,0) -> 0 | R7: =SUM(J7:N7)+SUM(O7:P7) -> 0
D8: Trolley System | E8: Yes | F8: =IF(E8="no","","T") -> T | H8: A-2244 | I8: =VLOOKUP(H8,Calcs!C:D,2,FALSE) -> Corner Post <80 4-Way Weld Assembly | M8: =IF(E3="L Shape",1,0) -> 0 | R8: =SUM(J8:N8)+SUM(O8:P8) -> 0
A9: AREA SQ FT | B9: 895 | D9: Size LENGTH Ft (LONG) | E9: 10 | F9: =Discovery!B35/12 -> 10 | H9: A-2225 | I9: =VLOOKUP(H9,Calcs!C:D,2,FALSE) -> Mid Span 1-Way Saddle Alt Weld Assembly | N9: =E12*2 -> 2 | O9: =IF(E4="Yes",2,0) -> 2 | R9: =SUM(J9:N9)+SUM(O9:P9) -> 4
A10: # of Tiles | B10: =B9/4 -> 223.75 | D10: Size WIDTH Ft (SHORT) | E10: =F10 -> 10 | F10: =Discovery!B36/12 -> 10 | H10: P-2531 | I10: =VLOOKUP(H10,Calcs!C:D,2,FALSE) -> Ladder Leg Footless | P10: =E7 -> 2 | R10: =SUM(J10:N10)+SUM(O10:P10) -> 2
A11: 10% Overage | B11: =B10*1.1 -> 246.125 | D11: Size HEIGHT Ft | E11: =Discovery!C37 -> 8 | F11: =Discovery!B37/12 -> 8 | H11: A-2253 | I11: =VLOOKUP(H11,Calcs!C:D,2,FALSE) -> Single Leg Inner Ladder Sleeve Footless Weld Assembly | P11: =E7*1 -> 2 | R11: =SUM(J11:N11)+SUM(O11:P11) -> 2
A12: 15% Overage | B12: =B10*1.15 -> 257.3125 | D12: Interior Beams | E12: 1 | F12: =IF(E4="Yes",E12+1,E12) -> 2 | H12: A-2248 | I12: =VLOOKUP(H12,Calcs!C:D,2,FALSE) -> Double Leg Inner Ladder Sleeve | R12: =SUM(J12:N12)+SUM(O12:P12) -> 0
H13: P-2545 | I13: 5' Full Bay HSS Member Alt w/Logo | J13: =(VLOOKUP(H13,$D$58:$E$63,2,FALSE))+(VLOOKUP(H13,$D$67:$E$72,2,FALSE)) -> 0 | K13: =IF(AND(E3=6,E6=8),3,0) -> 0 | L13: =IF(AND(E3=8,E6=8),6,0) -> 0 | N13: =IF(E8=6,E11,0) -> 0 | O13: 0 | R13: =SUM(J13:N13)+SUM(O13:P13) -> 0
A14: GermBlock Ball Pit Calculator | D14: Design Fee | E14: No | F14: =IF(E14="Yes",2500,0) -> 0 | H14: P-2206 | I14: 6' Full Bay HSS Member Alt w/Logo | J14: =(VLOOKUP(H14,$D$58:$E$63,2,FALSE))+(VLOOKUP(H14,$D$67:$E$72,2,FALSE)) -> 0 | K14: =IF(AND(E4=6,E7=8),3,0) -> 0 | L14: =IF(AND(E4=8,E7=8),6,0) -> 0 | N14: =IF(E9=6,E12,0) -> 0 | O14: =(O20*-1)*0.5 -> 0 | R14: =SUM(J14:N14)+SUM(O14:P14) -> 0
A15: LENGTH (Inches) | B15: 72 | H15: P-2207 | I15: 7' Full Bay HSS Member Alt w/Logo | J15: =(VLOOKUP(H15,$D$58:$E$63,2,FALSE))+(VLOOKUP(H15,$D$67:$E$72,2,FALSE)) -> 0 | K15: =IF(AND(E5=6,E8=8),3,0) -> 0 | L15: =IF(AND(E5=8,E8=8),6,0) -> 0 | N15: =IF(E9=7,E12,0) -> 0 | O15: =(O21*-1)*0.5 -> 0 | R15: =SUM(J15:N15)+SUM(O15:P15) -> 0
A16: WIDTH (Inches) | B16: 72 | D16: Accessories | H16: A-2408 | I16: =VLOOKUP(H16,Calcs!C:D,2,FALSE) -> 8' Half Bay <80 HSS Member w/Splices & HDWE | J16: =(VLOOKUP(H16,$D$58:$E$63,2,FALSE))+(VLOOKUP(H16,$D$67:$E$72,2,FALSE)) -> 0 | K16: =IF(AND(E6=6,E9=8),3,0) -> 0 | L16: =IF(AND(E6=8,E9=8),6,0) -> 0 | N16: =IF(E9=8,E12,0) -> 0 | O16: =(O24*-1)*0.5 -> 0 | R16: =SUM(J16:N16)+SUM(O16:P16) -> 0
A17: HEIGHT (Inches) | B17: 24 | D17: Zip Line | E17: No | F17: =IF(E17="Yes","Z","") | H17: A-2409 | I17: =VLOOKUP(H17,Calcs!C:D,2,FALSE) -> 9' Half Bay <80 HSS Member w/Splices & HDWE | J17: =(VLOOKUP(H17,$D$61:E63,2,FALSE))+(VLOOKUP(H17,D70:E72,2,FALSE)) -> 0 | K17: =IF(AND(E6=6,E9=9),3,0) -> 0 | L17: =IF(AND(E6=8,E9=9),6,0) -> 0 | N17: =IF(E9=9,E12,0) -> 0 | O17: =(O25*-1)*0.5 -> 0 | R17: =SUM(J17:N17)+SUM(O17:P17) -> 0
A18: CUBIC Ft | B18: =(B15/12)*(B16/12)*(B17/12) -> 72 | D18: Frame Mount - Ball Rack | E18: No | F18: =IF(E18="Yes","R","") | H18: A-2410 | I18: =VLOOKUP(H18,Calcs!C:D,2,FALSE) -> 10' Half Bay <80 HSS Member w/Splices & HDWE | J18: =(VLOOKUP(H18,D61:E63,2,FALSE))+(VLOOKUP(H18,D70:E72,2,FALSE)) -> 4 | K18: =IF(AND(E6=6,E9=10),3,0) -> 0 | L18: =IF(AND(E6=8,E9=10),6,0) -> 0 | N18: =IF(E9=10,E12,0) -> 1 | O18: =(O26*-1)*0.5 -> -1 | R18: =SUM(J18:N18)+SUM(O18:P18) -> 4
D19: Slide | H19: P-2330 | I19: =VLOOKUP(H19,Calcs!C:D,2,FALSE) -> Monkey Bar / Ladder Rungs w/ 4 Threaded Holes | O19: =IF(E4="Yes",9,0) -> 9 | P19: =IF(E7>0.01,E7*5,0) -> 10 | R19: =SUM(J19:N19)+SUM(O19:P19) -> 19
A20: Balls Per Case | B20: 500 | D20: Slide | E20: No | H20: P-2216 | I20: 6' Full Bay Monkey Bar HSS Member w/Logo | O20: =IF(E55="Yes6",2,0) -> 0 | R20: =SUM(J20:N20)+SUM(O20:P20) -> 0
D21: Slide - Gray Upcharge | E21: No | H21: P-2217 | I21: 7' Full Bay Monkey Bar HSS Member w/Logo | O21: =IF(E54="Yes7",2,0) -> 0 | R21: =SUM(J21:N21)+SUM(O21:P21) -> 0
D22: Steamroller Ramp (3rd Party) | E22: No
A23: Ball Pit Cases Required | B23: =B18/7 -> 10.285714 | D23: Slide Conversion Kit | E23: No
D24: Climbing Wall | H24: A-2418 | I24: =VLOOKUP(H24,Calcs!C:D,2,FALSE) -> 8' Half Bay Monkey Bar HSS Member w/ Logo | O24: =IF(E55="Yes8",2,0) -> 0 | R24: =SUM(J24:N24)+SUM(O24:P24) -> 0
A25: Summit Safety Floor Mats | D25: Climbing Wall - Frame Mounted | E25: No | H25: A-2419 | I25: =VLOOKUP(H25,Calcs!C:D,2,FALSE) -> 9' Half Bay <80 Monkey Bar HSS w/Splices & HDWE | O25: =IF(E55="Yes9",2,0) -> 0 | R25: =SUM(J25:N25)+SUM(O25:P25) -> 0
A26: Each Roll is 6' Wide x 42' Long | D26: Climbing Wall - Safety Shield | E26: No | H26: A-2420 | I26: =VLOOKUP(H26,Calcs!C:D,2,FALSE) -> 10' Half Bay <80 Monkey Bar HSS w/Splices & HDWE | O26: =IF(E55="Yes10",2,0) -> 2 | R26: =SUM(J26:N26)+SUM(O26:P26) -> 2
A27: Cost Per SQ FT - Thickness | D27: Climbing Wall - Wall Mounted | E27: Yes | H27: P-2024 | I27: =VLOOKUP(H27,Calcs!C:D,2,FALSE) -> Zip Line HSS Tube | J27: =IF(E17="Yes",2,0) -> 0 | R27: =SUM(J27:N27)+SUM(O27:P27) -> 0
A28: 1-3/8" | B28: 4.75 | D28: Climbing Wall - Mat | E28: No | H28: P-2028 | I28: =VLOOKUP(H28,Calcs!C:D,2,FALSE) -> Base Plate Shield | J28: =J3*2 -> 8 | K28: =K3*2 -> 0 | L28: =L3*2 -> 0 | R28: =SUM(J28:N28)+SUM(O28:P28) -> 8
A29: 2" | B29: 5.75 | D29: Mats & Padding | H29: P-1032 | I29: =VLOOKUP(H29,Calcs!C:D,2,FALSE) -> 4.5' Full Bay HSS Member Alt w/Logo | R29: =SUM(J29:N29)+SUM(O29:P29) -> 0
A30: AREA SQ FT | B30: 21 | D30: Adventure Mat System - Floor | E30: Yes | F30: {=_xlfn.IFS(E6=6,2,E6=8,3,E6=4,1)} -> 1
D31: Adventure Mat System - Column | E31: Yes | F31: =IF(E31="Yes",E6,0) -> 4 | H31: PART # | I31: TROLLEY PARTS | J31: UNIT COUNT | R31: =R1 -> TOTAL
D32: Adventure Mat System - Ladder Leg | E32: Yes | F32: =E7 -> 2 | H32: P-2018 | I32: Trolley Bar | J32: =IF($E$8="Yes",1,0) -> 1 | R32: =J32 -> 1
D33: Adventure Mat System - CUSTOM | E33: No | H33: P-2025 | I33: Trolley Bar Plate | J33: =IF($E$8="Yes",2,0) -> 2 | R33: =J33 -> 2
D34: Ladder | H34: TR2000-A10 | I34: 10' Aluminum Enclosed Rail 550Lbs. Max Weight | J34: 0 | R34: =J34 -> 0
A35: LENGTH (Inches) | B35: 72 | D35: Ladder - Safety Shield | E35: No | H35: TR2000-A09 | I35: 9' Aluminum Enclosed Rail 550Lbs. Max Weight | J35: =IF($E$8="Yes",2,0) -> 2 | R35: =J35 -> 2
A36: WIDTH (Inches) | B36: 42 | D36: MISC | H36: TR2000-A08 | I36: 8' Aluminum Enclosed Rail 550Lbs. Max Weight | J36: 0 | R36: =J36 -> 0
A37: AREA SQ FT | B37: =(B35/12)*(B36/12) -> 21 | D37: Eldo Summit Climbing Wall | E37: No | H37: TR2000-A07 | I37: 7' Aluminum Enclosed Rail 550Lbs. Max Weight | J37: 0 | R37: =J37 -> 0
A38: ROLLS REQUIRED | B38: =B37/B30 -> 1 | D38: Interlocking Tile Mats | E38: No | H38: TRH2005 | I38: Universal Threaded Rod Hanger | J38: =IF($E$8="Yes",6,0) -> 6 | R38: =J38 -> 6
D39: Wheelchair Swing | H39: TRN2016 | I39: End Cap For Rail | J39: =IF($E$8="Yes",4,0) -> 4 | R39: =J39 -> 4
A40: AREA SQ FT | B40: 1000 | D40: Wheelchair Swing | E40: No | H40: TRT2001 | I40: Trolley For Rail | J40: =IF($E$8="Yes",2,0) -> 2 | R40: =J40 -> 2
A41: ROLLS REQUIRED | B41: =B40/B30 -> 47.619048 | R41: TOTAL
D42: Accessories Brackets
D43: # - Accessory Brackets | E43: 4
D44: # - 360 Swivel / 180 Rotational Eye Bolt | E44: 4
D45: # - 3/8" Non-Swivel Eye Bolts | E45: =E43-E44 -> 0
D47: # - 360 Swivel / 180 Rotational Eye Bolt | E47: 0
D48: # - 1/2" Forged Eye Bolts | E48: 12
D49: # Eye Bolt - Swing Hanger w/ Bearing | E49: 0 | F49: Sold in Packs of 2
D51: Number of V-Rings (10-PACK) | E51: 0
D52: Auto Locking Carabiner (4 Pack) | E52: 2 | F52: =(E48+E44)/4 -> 4
D53: Multi-Pocket Webbing Sling | E53: 0 | F53: =F52 -> 4
E54: =F3&"R-SSA-"&F9&F10&"CLM" -> SQ-R-SSA-1010CLM
E55: =E4&E9 -> Yes10
E56: =E4&E6 -> Yes4
D57: SHORT BEAMS (END CAPS)
D58: P-2206 | E58: =IF(E10=6,2,0) -> 0
D59: P-2545 | E59: =IF(E9=7,2,0) -> 0
D60: P-2207 | E60: =IF(E10=7,2,0) -> 0
D61: A-2408 | E61: =IF(E10=8,2,0) -> 0
D62: A-2409 | E62: =IF(E10=9,2,0) -> 0
D63: A-2410 | E63: =IF(E10=10,2,0) -> 2
D64: TOTAL | E64: =SUM(E61:E63) -> 2
D66: LONG BEAMS
D67: P-2206 | E67: =IF(E9=6,J2-E64,0) -> 0
D68: P-2545 | E68: =IF(E8=7,J1-E63,0) -> 0
D69: P-2207 | E69: =IF(E9=7,J2-E64,0) -> 0
D70: A-2408 | E70: =IF(E9=8,J2-E64,0) -> 0
D71: A-2409 | E71: =IF(E9=9,J2-E64,0) -> 0
D72: A-2410 | E72: =IF(E9=10,J2-E64,0) -> 2
D73: TOTAL | E73: =SUM(E70:E72) -> 2
D75: MATS
D76: SQ-R-SSA-1010CLM | E76: =IF(D76=$E$54,1,0) -> 1
D77: R-R-SSA-2010CLM | E77: =IF(D77=$E$54,2,0) -> 0
D78: R-R-SSA-3010CLM | E78: =IF(D78=$E$54,3,0) -> 0
D79: L-R-SSA-2020CLM | E79: =IF(D79=$E$54,3,0) -> 0
D80: SUBTOTAL - 10' x 10' Mat System | E80: =SUM(E76:E79) -> 1
D82: SQ-R-SSA-99CLM | E82: =IF(D82=$E$54,1,0) -> 0
D83: R-R-SSA-97CLM | E83: =IF(D83=$E$54,1,0) -> 0
D84: R-R-SSA-189CLM | E84: =IF(D84=$E$54,2,0) -> 0
D85: SUBTOTAL - 9' x 9' Mat System | E85: =SUM(E81:E84) -> 0
D87: SQ-R-SSA-88CLM | E87: =IF(D87=$E$54,1,0) -> 0
D88: R-R-SSA-168CLM | E88: =IF(D88=$E$54,2,0) -> 0
D89: SUBTOTAL - 8' x 8' Mat System | E89: =SUM(E86:E88) -> 0
D91: R-R-SSA-108CLM | E91: =IF(D91=$E$54,1,0) -> 0
D92: R-R-SSA-208CLM | E92: =IF(D92=$E$54,2,0) -> 0
D93: SUBTOTAL - 10' x 8' Mat System | E93: =SUM(E90:E92) -> 0
C96: R-R-SSA-106CLM | D96: R-SSA-1006CLM | E96: =IF(C96=$E$54,1,0) -> 0
C97: R-R-SSA-107CLM | D97: R-SSA-1007CLM | E97: =IF(C97=$E$54,1,0) -> 0
C98: R-R-SSA-108CLM | D98: R-SSA-1008CLM | E98: =IF(C98=$E$54,1,0) -> 0
C99: R-R-SSA-109CLM | D99: R-SSA-1009CLM | E99: =IF(C99=$E$54,1,0) -> 0
C100: R-R-SSA-1610CLM | D100: R-SSA-1610CLM | E100: =IF(C100=$E$54,1,0) -> 0
C101: R-R-SSA-207CLM | D101: R-SSA-2007CLM | E101: =IF(C101=$E$54,1,0) -> 0
C102: R-R-SSA-208CLM | D102: R-SSA-2008CLM | E102: =IF(C102=$E$54,1,0) -> 0
C103: R-R-SSA-2010CLM | D103: R-SSA-2010CLM | E103: =IF(C103=$E$54,1,0) -> 0
C104: R-R-SSA-86CLM | D104: R-SSA-0806CLM | E104: =IF(C104=$E$54,1,0) -> 0
C105: R-R-SSA-97CLM | D105: R-SSA-0907CLM | E105: =IF(C105=$E$54,1,0) -> 0
C106: R-R-SSA-98CLM | D106: R-SSA-0908CLM | E106: =IF(C106=$E$54,1,0) -> 0
C107: SQ-R-SSA-1010CLM | D107: R-SSA-1010CLM | E107: =IF(C107=$E$54,1,0) -> 1
... C110: R-R-SSA-98CLM | D110: R-SSA-0908CLM | E110: =IF(C110=$E$54,1,0) -> 0

Sheet Calcs
B1: STEEL PARTS | C1: TROLLEY PARTS
L2: Mark Up | M2: 1.3 | N2: =W5-W8 -> 10303.969 | S2: Financial Details
A3: ADVENTURE SERIES: FRAME COST
A4: UPC | C4: PART # | D4: DESCRIPTION | E4: VLOOKUP TEST | F4: ORDER QUANTITY | G4: PRICE PER PART | H4: Price Per w Tax (6.5%) | I4: WEIGHT (LB) | J4: TOTAL PER PART | K4: Total w Tax (6.5%) | L4: PRICE PER PART | M4: TOTAL PER PART | N4: MARK UP | O4: WEIGHT PER PART (LBS) | R4: STRUCTURE | S4: MATS | T4: TROLLEY | U4: ACCESSORIES | V4: HARDWARE | W4: TOTAL | X4: DISCOUNT PROPOSED | Y4: MAX DISCOUNT | Z4: FREIGHT & TAXES
B5: =IF(F5>=1,C5,"") -> A-2245 | C5: A-2245 | D5: Vertical Tall <80 w/Gusset | E5: =VLOOKUP(C5,VLOOKUP!H:R,11,FALSE) -> 2 | F5: =E5 -> 2 | G5: =VLOOKUP(C5,lists!I:L,4,FALSE) -> 242.5 | H5: =G5*(1+$M$1) -> 242.5 | I5: =F5*O5 -> 136.5 | J5: =F5*G5 -> 485 | K5: =J5*(1+$M$1) -> 485 | L5: =ROUND(H5*(1+$M$2),2) -> 557.75 | M5: =F5*L5 -> 1115.5 | N5: =IFERROR((M5/K5)-1,"") -> 1.3 | O5: 68.25 | Q5: Revenue | R5: =M36 -> 8692.85 | S5: =SUM(M68:M125) -> 3374.08 | T5: =M48 -> 3548.9 | U5: =M176-S5 -> 2548.36 | V5: =M220 -> 1777.95 | W5: =SUM(R5:V5) -> 19942.14 | X5: =W5-R19 -> 16275.84 | Y5: =Y8*2 -> 19276.342 | Z5: =IF('Adventure Series Proposal (USA)'!H235="TBD",0) -> 0
B6: =IF(F6>=1,C6,"") -> A-2246 | C6: A-2246 | D6: Vertical Tall <80 w/Gussets, Rungs & Handles | E6: =VLOOKUP(C6,VLOOKUP!H:R,11,FALSE) -> 2 | F6: =E6 -> 2 | G6: =VLOOKUP(C6,lists!I:L,4,FALSE) -> 242.5 | H6: =G6*(1+$M$1) -> 242.5 | I6: =F6*O6 -> 134.58 | J6: =F6*G6 -> 485 | K6: =J6*(1+$M$1) -> 485 | L6: =ROUND(H6*(1+$M$2),2) -> 557.75 | M6: =F6*L6 -> 1115.5 | N6: =IFERROR((M6/K6)-1,"") -> 1.3 | O6: 67.29
B7: =IF(F7>=1,C7,"") | C7: A-2241 | D7: Corner Post <80 1-Way Weld Assembly | E7: =IF(VLOOKUP!E3="T Shape",2,"") | G7: =VLOOKUP(C7,lists!I:L,4,FALSE) -> 73 | H7: =G7*(1+$M$1) -> 73 | I7: =F7*O7 -> 0 | J7: =F7*G7 -> 0 | K7: =J7*(1+$M$1) -> 0 | L7: =ROUND(H7*(1+$M$2),2) -> 167.9 | M7: =F7*L7 -> 0 | N7: =IFERROR((M7/K7)-1,"") | O7: 11.886 | Q7: % of Revenue | R7: =R5/$W$5 -> 0.43590357 | S7: =S5/$W$5 -> 0.16919348 | T7: =T5/$W$5 -> 0.17795984 | U7: =U5/$W$5 -> 0.12778769 | V7: =V5/$W$5 -> 0.089155427 | W7: =W5/$W$5 -> 1
B8: =IF(F8>=1,C8,"") -> A-2242 | C8: A-2242 | D8: Corner Post <80 2-Way Weld Assembly | E8: =VLOOKUP(C8,VLOOKUP!H:R,11,FALSE) -> 4 | F8: =E8 -> 4 | G8: =VLOOKUP(C8,lists!I:L,4,FALSE) -> 76.5 | H8: =G8*(1+$M$1) -> 76.5 | I8: =F8*O8 -> 59.728 | J8: =F8*G8 -> 306 | K8: =J8*(1+$M$1) -> 306 | L8: =ROUND(H8*(1+$M$2),2) -> 175.95 | M8: =F8*L8 -> 703.8 | N8: =IFERROR((M8/K8)-1,"") -> 1.3 | O8: 14.932 | Q8: COGS | R8: =K36 -> 3779.5 | S8: =SUM(J68:J125) -> 2332.9 | T8: =K48 -> 1543 | U8: =K176-S8 -> 1107.98 | V8: =K220 -> 874.791 | W8: =SUM(R8:V8) -> 9638.171 | X8: =W8 -> 9638.171 | Y8: =W8 -> 9638.171 | Z8: =Z5 -> 0
B9: =IF(F9>=1,C9,"") | C9: A-2243 | D9: Corner Post <80 3-Way Weld Assembly | E9: =VLOOKUP(C9,VLOOKUP!H:R,11,FALSE) -> 0 | F9: =E9 -> 0 | G9: =VLOOKUP(C9,lists!I:L,4,FALSE) -> 97 | H9: =G9*(1+$M$1) -> 97 | I9: =F9*O9 -> 0 | J9: =F9*G9 -> 0 | K9: =J9*(1+$M$1) -> 0 | L9: =ROUND(H9*(1+$M$2),2) -> 223.1 | M9: =F9*L9 -> 0 | N9: =IFERROR((M9/K9)-1,"") | O9: 17.979 | Q9: % of COGS | R9: =R8/$W$8 -> 0.39213872 | S9: =S8/$W$8 -> 0.242048 | T9: =T8/$W$8 -> 0.16009262 | U9: =U8/$W$8 -> 0.1149575 | V9: =V8/$W$8 -> 0.090763175 | W9: =W8/$W$8 -> 1
B10: =IF(F10>=1,C10,"") | C10: A-2244 | D10: Corner Post <80 4-Way Weld Assembly | E10: =VLOOKUP(C10,VLOOKUP!H:R,11,FALSE) -> 0 | F10: =E10 -> 0 | G10: =VLOOKUP(C10,lists!I:L,4,FALSE) -> 101 | H10: =G10*(1+$M$1) -> 101 | I10: =F10*O10 -> 0 | J10: =F10*G10 -> 0 | K10: =J10*(1+$M$1) -> 0 | L10: =ROUND(H10*(1+$M$2),2) -> 232.3 | M10: =F10*L10 -> 0 | N10: =IFERROR((M10/K10)-1,"") | O10: 21.025 | Q10: Gross Margin | R10: =R5/R8 -> 2.3 | S10: =S5/S8 -> 1.4463029 | T10: =IFERROR(T5/T8,0) -> 2.3 | U10: =U5/U8 -> 2.3000054 | V10: =V5/V8 -> 2.0324283 | W10: =W5-W8 -> 10303.969 | X10: =X5-X8 -> 6637.669 | Y10: =Y5-Y8 -> 9638.171 | Z10: =Z5-Z8 -> 0
C11: A-2022 | D11: Corner Post Multi-Level 1-Way Weld Assembly | G11: 72.5 | H11: =G11*(1+$M$1) -> 72.5 | I11: =F11*O11 -> 0 | J11: =F11*G11 -> 0 | K11: =J11*(1+$M$1) -> 0 | L11: =ROUND(H11*(1+$M$2),2) -> 166.75 | M11: =F11*L11 -> 0 | N11: =IFERROR((M11/K11)-1,"") | O11: 14.932 | Q11: Gross Margin % | W11: =(W5/W8)-1 -> 1.0690793 | X11: =(X5/X8)-1 -> 0.68868554 | Y11: =(Y5/Y8)-1 -> 1 | Z11: =(Z5/Z8)-1 -> #DIV/0!
B12: =IF(F12>=1,C12,"") -> A-2225 | C12: A-2225 | D12: Mid Span 1-Way Saddle Alt Weld Assembly | E12: =VLOOKUP(C12,VLOOKUP!H:R,11,FALSE) -> 4 | F12: =E12 -> 4 | G12: =VLOOKUP(C12,lists!I:L,4,FALSE) -> 46 | H12: =G12*(1+$M$1) -> 46 | I12: =F12*O12 -> 25.84 | J12: =F12*G12 -> 184 | K12: =J12*(1+$M$1) -> 184 | L12: =ROUND(H12*(1+$M$2),2) -> 105.8 | M12: =F12*L12 -> 423.2 | N12: =IFERROR((M12/K12)-1,"") -> 1.3 | O12: 6.46 | Q12: Net Margin % | W12: =1-(W8/W5) -> 0.51669324 | X12: =1-(X8/X5) -> 0.40782344 | Y12: =1-(Y8/Y5) -> 0.5 | Z12: =1-(Z8/Z5) -> #DIV/0!
B13: =IF(F13>=1,C13,"") -> P-2531 | C13: P-2531 | D13: Ladder Leg Footless | E13: =F13 -> 2 | F13: =IF(VLOOKUP!E7>0,VLOOKUP!E7,0) -> 2 | G13: =VLOOKUP(C13,lists!I:L,4,FALSE) -> 97.5 | H13: =G13*(1+$M$1) -> 97.5 | I13: =F13*O13 -> 61.82 | J13: =F13*G13 -> 195 | K13: =J13*(1+$M$1) -> 195 | L13: =ROUND(H13*(1+$M$2),2) -> 224.25 | M13: =F13*L13 -> 448.5 | N13: =IFERROR((M13/K13)-1,"") -> 1.3 | O13: 30.91 | Q13: Delta | W13: =W12-0.5 -> 0.016693244 | X13: =X12-0.5 -> -0.092176564 | Y13: =Y12-0.5 -> 0
B14: =IF(F14>=1,C14,"") -> A-2253 | C14: A-2253 | D14: Single Leg Inner Ladder Sleeve Footless Weld Assembly | E14: =VLOOKUP(C14,VLOOKUP!H:R,11,FALSE) -> 2 | F14: =E14 -> 2 | G14: =VLOOKUP(C14,lists!I:L,4,FALSE) -> 65.5 | H14: =G14*(1+$M$1) -> 65.5 | I14: =F14*O14 -> 8.98 | J14: =F14*G14 -> 131 | K14: =J14*(1+$M$1) -> 131 | L14: =ROUND(H14*(1+$M$2),2) -> 150.65 | M14: =F14*L14 -> 301.3 | N14: =IFERROR((M14/K14)-1,"") -> 1.3 | O14: 4.49 | W14: $ Margin over 50% | Y14: =X10-Y10 -> -3000.502
B15: =IF(F15>=1,C15,"") | C15: A-2248 | D15: Double Leg Inner Ladder Sleeve | E15: =VLOOKUP(C15,VLOOKUP!H:R,11,FALSE) -> 0 | F15: =E15 -> 0 | G15: =VLOOKUP(C15,lists!I:L,4,FALSE) -> 79 | H15: =G15*(1+$M$1) -> 79 | I15: =F15*O15 -> 0 | J15: =F15*G15 -> 0 | K15: =J15*(1+$M$1) -> 0 | L15: =ROUND(H15*(1+$M$2),2) -> 181.7 | M15: =F15*L15 -> 0 | N15: =IFERROR((M15/K15)-1,"") | O15: 10.51 | W15: % Margin over 50% | Y15: =X11-Y11 -> -0.31131446
B16: =IF(F16>=1,C16,"") | C16: P-2545 | D16: 5' Full Bay HSS Member Alt w/ Logo | E16: =VLOOKUP(C16,VLOOKUP!H:R,11,FALSE) -> 0 | F16: =E16 -> 0 | G16: =VLOOKUP(C16,lists!I:L,4,FALSE) -> 150 | H16: =G16*(1+$M$1) -> 150 | I16: =F16*O16 -> 0 | J16: =F16*G16 -> 0 | K16: =J16*(1+$M$1) -> 0 | L16: =ROUND(H16*(1+$M$2),2) -> 345 | M16: =F16*L16 -> 0 | N16: =IFERROR((M16/K16)-1,"") | O16: 30
B17: =IF(F17>=1,C17,"") | C17: P-2206 | D17: 6' Full Bay HSS Member Alt w/ Logo | E17: =VLOOKUP(C17,VLOOKUP!H:R,11,FALSE) -> 0 | F17: =E17 -> 0 | G17: =VLOOKUP(C17,lists!I:L,4,FALSE) -> 150 | H17: =G17*(1+$M$1) -> 150 | I17: =F17*O17 -> 0 | J17: =F17*G17 -> 0 | K17: =J17*(1+$M$1) -> 0 | L17: =ROUND(H17*(1+$M$2),2) -> 345 | M17: =F17*L17 -> 0 | N17: =IFERROR((M17/K17)-1,"") | O17: 35.8
B18: =IF(F18>=1,C18,"") | C18: P-2207 | D18: 7' Full Bay HSS Member Alt w/ Logo | E18: =VLOOKUP(C18,VLOOKUP!H:R,11,FALSE) -> 0 | F18: 0 | G18: =VLOOKUP(C18,lists!I:L,4,FALSE) -> 150 | H18: =G18*(1+$M$1) -> 150 | I18: =F18*O18 -> 0 | J18: =F18*G18 -> 0 | K18: =J18*(1+$M$1) -> 0 | L18: =ROUND(H18*(1+$M$2),2) -> 345 | M18: =F18*L18 -> 0 | N18: =IFERROR((M18/K18)-1,"") | O18: 42.5 | R18: Discount Offered | S18: Discount Offered % | U18: Discount % | V18: Discount $
B19: =IF(F19>=1,C19,"") | C19: A-2408 | D19: 8' Half Bay <80 HSS Member w/Splices & HDWE | E19: =VLOOKUP(C19,VLOOKUP!H:R,11,FALSE) -> 0 | F19: =E19 -> 0 | G19: =VLOOKUP(C19,lists!I:L,4,FALSE) -> 190 | H19: =G19*(1+$M$1) -> 190 | I19: =F19*O19 -> 0 | J19: =F19*G19 -> 0 | K19: =J19*(1+$M$1) -> 0 | L19: =ROUND(H19*(1+$M$2),2) -> 437 | M19: =F19*L19 -> 0 | N19: =IFERROR((M19/K19)-1,"") | O19: 49.26 | R19: 3666.3 | S19: =R19/W5 -> 0.18384687 | U19: 0 | V19: =W5*U19 -> 0
B20: =IF(F20>=1,C20,"") | C20: A-2409 | D20: 9' Half Bay <80 HSS Member w/Splices & HDWE | E20: =VLOOKUP(C20,VLOOKUP!H:R,11,FALSE) -> 0 | F20: 0 | G20: =VLOOKUP(C20,lists!I:L,4,FALSE) -> 200 | H20: =G20*(1+$M$1) -> 200 | I20: =F20*O20 -> 0 | J20: =F20*G20 -> 0 | K20: =J20*(1+$M$1) -> 0 | L20: =ROUND(H20*(1+$M$2),2) -> 460 | M20: =F20*L20 -> 0 | N20: =IFERROR((M20/K20)-1,"") | O20: 56.01
B21: =IF(F21>=1,C21,"") -> A-2410 | C21: A-2410 | D21: 10' Half Bay <80 HSS Member w/Splices & HDWE | E21: =VLOOKUP(C21,VLOOKUP!H:R,11,FALSE) -> 4 | F21: =E21 -> 4 | G21: =VLOOKUP(C21,lists!I:L,4,FALSE) -> 200 | H21: =G21*(1+$M$1) -> 200 | I21: =F21*O21 -> 271.6 | J21: =F21*G21 -> 800 | K21: =J21*(1+$M$1) -> 800 | L21: =ROUND(H21*(1+$M$2),2) -> 460 | M21: =F21*L21 -> 1840 | N21: =IFERROR((M21/K21)-1,"") -> 1.3 | O21: 67.9 | R21: Expiration Date | W21: 28277.23 | X21: 3931.2
B22: =IF(F22>=1,C22,"") -> P-2330 | C22: P-2330 | D22: Monkey Bar / Ladder Rungs w/ 4 Threaded Holes | E22: =VLOOKUP(C22,VLOOKUP!H:R,11,FALSE) -> 19 | F22: =E22 -> 19 | G22: =VLOOKUP(C22,lists!I:L,4,FALSE) -> 20.5 | H22: =G22*(1+$M$1) -> 20.5 | I22: =F22*O22 -> 45.41 | J22: =F22*G22 -> 389.5 | K22: =J22*(1+$M$1) -> 389.5 | L22: =ROUND(H22*(1+$M$2),2) -> 47.15 | M22: =F22*L22 -> 895.85 | N22: =IFERROR((M22/K22)-1,"") -> 1.3 | O22: 2.39 | R22: =TODAY()+6 -> 46231 | W22: 27892.38 | X22: 3510
B23: =IF(F23>=1,C23,"") | C23: P-2216 | D23: 6' Full Bay Monkey Bar HSS Member w/ Logo | E23: =VLOOKUP(C23,VLOOKUP!H:R,11,FALSE) -> 0 | F23: =E23 -> 0 | G23: =VLOOKUP(C23,lists!I:L,4,FALSE) -> 150 | H23: =G23*(1+$M$1) -> 150 | I23: =F23*O23 -> 0 | J23: =F23*G23 -> 0 | K23: =J23*(1+$M$1) -> 0 | L23: =ROUND(H23*(1+$M$2),2) -> 345 | M23: =F23*L23 -> 0 | N23: =IFERROR((M23/K23)-1,"") | O23: 34.85 | W23: =W21-W22 -> 384.85 | X23: =X21-X22 -> 421.2
B24: =IF(F24>=1,C24,"") | C24: P-2217 | D24: 7' Full Bay Monkey Bar HSS Member w/ Logo | E24: =VLOOKUP(C24,VLOOKUP!H:R,11,FALSE) -> 0 | F24: =E24 -> 0 | G24: =VLOOKUP(C24,lists!I:L,4,FALSE) -> 150 | H24: =G24*(1+$M$1) -> 150 | I24: =F24*O24 -> 0 | J24: =F24*G24 -> 0 | K24: =J24*(1+$M$1) -> 0 | L24: =ROUND(H24*(1+$M$2),2) -> 345 | M24: =F24*L24 -> 0 | N24: =IFERROR((M24/K24)-1,"") | O24: 41.41 | R24: MAX Discount | S24: MAX DISCOUNT %
B25: =IF(F25>=1,C25,"") | C25: A-2418 | D25: 8' Half Bay Monkey Bar HSS Member w/ Logo | E25: =VLOOKUP(C25,VLOOKUP!H:R,11,FALSE) -> 0 | F25: =E25 -> 0 | G25: =VLOOKUP(C25,lists!I:L,4,FALSE) -> 190 | H25: =G25*(1+$M$1) -> 190 | I25: =F25*O25 -> 0 | J25: =F25*G25 -> 0 | K25: =J25*(1+$M$1) -> 0 | L25: =ROUND(H25*(1+$M$2),2) -> 437 | M25: =F25*L25 -> 0 | N25: =IFERROR((M25/K25)-1,"") | O25: 47.97 | Q25: 100% of MAX | R25: =W5-Y5 -> 665.798 | S25: =(R25/W5) -> 0.033386487
B26: =IF(F26>=1,C26,"") | C26: A-2419 | D26: 9' Half Bay <80 Monkey Bar HSS w/Splices & HDWE | E26: =VLOOKUP(C26,VLOOKUP!H:R,11,FALSE) -> 0 | F26: =E26 -> 0 | G26: =VLOOKUP(C26,lists!I:L,4,FALSE) -> 200 | H26: =G26*(1+$M$1) -> 200 | I26: =F26*O26 -> 0 | J26: =F26*G26 -> 0 | K26: =J26*(1+$M$1) -> 0 | L26: =ROUND(H26*(1+$M$2),2) -> 460 | M26: =F26*L26 -> 0 | N26: =IFERROR((M26/K26)-1,"") | O26: 54.53 | Q26: 75% of MAX | R26: =R25*0.75 -> 499.3485 | S26: =R26/W5 -> 0.025039865
B27: =IF(F27>=1,C27,"") -> A-2420 | C27: A-2420 | D27: 10' Half Bay <80 Monkey Bar HSS w/Splices & HDWE | E27: =VLOOKUP(C27,VLOOKUP!H:R,11,FALSE) -> 2 | F27: =E27 -> 2 | G27: =VLOOKUP(C27,lists!I:L,4,FALSE) -> 200 | H27: =G27*(1+$M$1) -> 200 | I27: =F27*O27 -> 132.44 | J27: =F27*G27 -> 400 | K27: =J27*(1+$M$1) -> 400 | L27: =ROUND(H27*(1+$M$2),2) -> 460 | M27: =F27*L27 -> 920 | N27: =IFERROR((M27/K27)-1,"") -> 1.3 | O27: 66.22 | Q27: 50% of MAX | R27: =R25*0.5 -> 332.899 | S27: =R27/W5 -> 0.016693244
B28: =IF(F28>=1,C28,"") | C28: P-2024 | D28: Zip Line HSS Tube | E28: =IF(VLOOKUP!E17="Yes",2,0) -> 0 | F28: =E28 -> 0 | G28: =VLOOKUP(C28,lists!I:L,4,FALSE) -> 20 | H28: =G28*(1+$M$1) -> 20 | I28: =F28*O28 -> 0 | J28: =F28*G28 -> 0 | K28: =J28*(1+$M$1) -> 0 | L28: =ROUND(H28*(1.5),2) -> 30 | M28: =F28*L28 -> 0 | N28: =IFERROR((M28/K28)-1,"") | O28: 5.63 | Q28: 25% of MAX | R28: =R25*0.25 -> 166.4495 | S28: =R28/W5 -> 0.0083466218
B29: =IF(F29>=1,C29,"") | C29: A-2530 | D29: Zip Line Collar | E29: =IF(VLOOKUP!E17="Yes",4,0) -> 0 | F29: =E29 -> 0 | G29: =VLOOKUP(C29,lists!I:L,4,FALSE) -> 53 | H29: =G29*(1+$M$1) -> 53 | I29: =F29*O29 -> 0 | J29: =F29*G29 -> 0 | K29: =J29*(1+$M$1) -> 0 | L29: =ROUND(H29*(1.5),2) -> 79.5 | M29: =F29*L29 -> 0 | N29: =IFERROR((M29/K29)-1,"") | O29: 4.5
B30: =IF(F30>=1,C30,"") -> P-2124 | C30: P-2124 | D30: Quick Shift Saddle Bracket™ | E30: =VLOOKUP!E43 -> 4 | F30: =E30 -> 4 | G30: =VLOOKUP(C30,lists!I:L,4,FALSE) -> 51 | H30: =G30*(1+$M$1) -> 51 | I30: =F30*O30 -> 19.32 | J30: =F30*G30 -> 204 | K30: =J30*(1+$M$1) -> 204 | L30: =ROUND(H30*(1+$M$2),2) -> 117.3 | M30: =F30*L30 -> 469.2 | N30: =IFERROR((M30/K30)-1,"") -> 1.3 | O30: 4.83
B31: =IF(F31>=1,C31,"") -> P-2028 | C31: P-2028 | D31: Base Plate Shield | E31: =VLOOKUP(C31,VLOOKUP!H:R,11,FALSE) -> 8 | F31: =E31 -> 8 | G31: =VLOOKUP(C31,lists!I:L,4,FALSE) -> 25 | H31: =G31*(1+$M$1) -> 25 | I31: =F31*O31 -> 22.48 | J31: =F31*G31 -> 200 | K31: =J31*(1+$M$1) -> 200 | L31: =ROUND(H31*(1+$M$2),2) -> 57.5 | M31: =F31*L31 -> 460 | N31: =IFERROR((M31/K31)-1,"") -> 1.3 | O31: 2.81
B32: =IF(F32>=1,C32,"") | C32: P-2500 | D32: Safety First Climbing Shield (48" x 18") | E32: =IF(VLOOKUP!E26="Yes",1,0) -> 0 | F32: =E32 -> 0 | G32: =VLOOKUP(C32,lists!I:L,4,FALSE) -> 52 | H32: =G32*(1+$M$1) -> 52 | I32: =F32*O32 -> 0 | J32: =F32*G32 -> 0 | K32: =J32*(1+$M$1) -> 0 | L32: =ROUND(H32*(1+$M$2),2) -> 119.6 | M32: =F32*L32 -> 0 | N32: =IFERROR((M32/K32)-1,"") | O32: 24.5 | R32: Repeat Customer Discount
B33: =IF(F33>=1,C33,"") | C33: P-2501 | D33: Safety First Ladder Climbing Shield (90° Angle) | E33: =IF(Discovery!C37>8.1,VLOOKUP!E6*2,0) -> 0 | F33: =E33 -> 0 | G33: =VLOOKUP(C33,lists!I:L,4,FALSE) -> 52 | H33: =G33*(1+$M$1) -> 52 | I33: 22 | J33: =F33*G33 -> 0 | K33: =J33*(1+$M$1) -> 0 | L33: =ROUND(H33*(1+$M$2),2) -> 119.6 | M33: =F33*L33 -> 0 | N33: =IFERROR((M33/K33)-1,"") | O33: 22 | R33: 0.15 | S33: =W5*R33 -> 2991.321
B34: =IF(F34>=1,C34,"") | C34: P-2502 | D34: Safety First Ladder Climbing Shield (50° Angle) | E34: =IF(VLOOKUP!E35="Yes",VLOOKUP!E7,0) -> 0 | F34: =E34 -> 0 | G34: =VLOOKUP(C34,lists!I:L,4,FALSE) -> 52 | H34: =G34*(1+$M$1) -> 52 | I34: 23 | J34: =F34*G34 -> 0 | K34: =J34*(1+$M$1) -> 0 | L34: =ROUND(H34*(1+$M$2),2) -> 119.6 | M34: =F34*L34 -> 0 | N34: =IFERROR((M34/K34)-1,"") | O34: 22.3
B35: =IF(F35>=1,C35,"") | C35: P-1032 | D35: 4.5' Full Bay HSS Member Alt w/Logo | E35: =VLOOKUP(C35,VLOOKUP!H:R,10,FALSE) -> 0 | F35: =E35 -> 0 | G35: 155 | H35: =G35*(1+$M$1) -> 155 | I35: =F35*O35 -> 0 | J35: =F35*G35 -> 0 | K35: =J35*(1+$M$1) -> 0 | L35: =ROUND(H35*(1+$M$2),2) -> 356.5 | M35: =F35*L35 -> 0 | N35: =IFERROR((M35/K35)-1,"") | O35: 61.1
E36: =SUM(E5:E35) -> 53 | F36: =SUM(F5:F35) -> 53 | J36: SUBTOTAL | K36: =SUM(J5:J35) -> 3779.5 | L36: SUBTOTAL | M36: =SUM(M5:M35) -> 8692.85
A38: TROLLEY PARTS
B39: =IF(F39>=1,C39,"") -> P-2018 | C39: P-2018 | D39: Trolley Bar | E39: =VLOOKUP(C39,VLOOKUP!H:R,11,FALSE) -> 1 | F39: =E39 -> 1 | G39: =VLOOKUP(C39,[1]lists!I:L,4,FALSE) -> 14 | H39: =G39*(1+$M$1) -> 14 | I39: =F39*O39 -> 2.27 | J39: =F39*G39 -> 14 | K39: =J39*(1+$M$1) -> 14 | L39: =ROUND(H39*(1+$M$2),2) -> 32.2 | M39: =F39*L39 -> 32.2 | N39: =IFERROR((M39/K39)-1,"") -> 1.3 | O39: 2.27
B40: =IF(F40>=1,C40,"") -> P-2025 | C40: P-2025 | D40: Trolley Bar Plate | E40: =VLOOKUP(C40,VLOOKUP!H:R,11,FALSE) -> 2 | F40: =E40 -> 2 | G40: =VLOOKUP(C40,[1]lists!I:L,4,FALSE) -> 12 | H40: =G40*(1+$M$1) -> 12 | I40: =F40*O40 -> 0.594 | J40: =F40*G40 -> 24 | K40: =J40*(1+$M$1) -> 24 | L40: =ROUND(H40*(1+$M$2),2) -> 27.6 | M40: =F40*L40 -> 55.2 | N40: =IFERROR((M40/K40)-1,"") -> 1.3 | O40: 0.297
B41: =IF(F41>=1,"SSG-TR-A10","") | C41: TR2000-A10 | D41: 10' Aluminum Enclosed Rail 550lbs. Max Weight | E41: =VLOOKUP(C41,VLOOKUP!H:R,11,FALSE) -> 0 | F41: =E41 -> 0 | G41: =VLOOKUP(C41,[1]lists!I:M,5,FALSE) -> 215.1 | H41: =G41*(1+$M$1) -> 215.1 | I41: =F41*O41 -> 0 | J41: =F41*G41 -> 0 | K41: =J41*(1+$M$1) -> 0 | L41: =ROUND(H41*(1+$M$2),2) -> 494.73 | M41: =F41*L41 -> 0 | N41: =IFERROR((M41/K41)-1,"") | O41: 26.17
B42: =IF(F42>=1,"SSG-TR-A09","") -> SSG-TR-A09 | C42: TR2000-A09 | D42: 9' Aluminum Enclosed Rail 550lbs. Max Weight | E42: =VLOOKUP(C42,VLOOKUP!H:R,11,FALSE) -> 2 | F42: =E42 -> 2 | G42: =VLOOKUP(C42,[1]lists!I:M,5,FALSE) -> 193.5 | H42: =G42*(1+$M$1) -> 193.5 | I42: =F42*O42 -> 47.12 | J42: =F42*G42 -> 387 | K42: =J42*(1+$M$1) -> 387 | L42: =ROUND(H42*(1+$M$2),2) -> 445.05 | M42: =F42*L42 -> 890.1 | N42: =IFERROR((M42/K42)-1,"") -> 1.3 | O42: 23.56
B43: =IF(F43>=1,"SSG-TR-A08","") | C43: TR2000-A08 | D43: 8' Aluminum Enclosed Rail 550lbs. Max Weight | E43: =VLOOKUP(C43,VLOOKUP!H:R,11,FALSE) -> 0 | F43: =E43 -> 0 | G43: =VLOOKUP(C43,[1]lists!I:M,5,FALSE) -> 171 | H43: =G43*(1+$M$1) -> 171 | I43: =F43*O43 -> 0 | J43: =F43*G43 -> 0 | K43: =J43*(1+$M$1) -> 0 | L43: =ROUND(H43*(1+$M$2),2) -> 393.3 | M43: =F43*L43 -> 0 | N43: =IFERROR((M43/K43)-1,"") | O43: 20.94
B44: =IF(F44>=1,"SSG-TR-A07","") | C44: TR2000-A07 | D44: 7' Aluminum Enclosed Rail 550lbs. Max Weight | E44: =VLOOKUP(C44,VLOOKUP!H:R,11,FALSE) -> 0 | F44: =E44 -> 0 | G44: =VLOOKUP(C44,[1]lists!I:M,5,FALSE) -> 151.2 | H44: =G44*(1+$M$1) -> 151.2 | I44: =F44*O44 -> 0 | J44: =F44*G44 -> 0 | K44: =J44*(1+$M$1) -> 0 | L44: =ROUND(H44*(1+$M$2),2) -> 347.76 | M44: =F44*L44 -> 0 | N44: =IFERROR((M44/K44)-1,"") | O44: 18.32
B45: =IF(F45>=1,"SSG-TRH","") -> SSG-TRH | C45: TRH2005 | D45: Universal Threaded Rod Hanger | E45: =VLOOKUP(C45,VLOOKUP!H:R,11,FALSE) -> 6 | F45: =E45 -> 6 | G45: =VLOOKUP(C45,[1]lists!I:M,5,FALSE) -> 113 | H45: =G45*(1+$M$1) -> 113 | I45: =F45*O45 -> 12.36 | J45: =F45*G45 -> 678 | K45: =J45*(1+$M$1) -> 678 | L45: =ROUND(H45*(1+$M$2),2) -> 259.9 | M45: =F45*L45 -> 1559.4 | N45: =IFERROR((M45/K45)-1,"") -> 1.3 | O45: 2.06
B46: =IF(F46>=1,"SSG-TRN","") -> SSG-TRN | C46: TRN2016 | D46: End Cap for Rail | E46: =VLOOKUP(C46,VLOOKUP!H:R,11,FALSE) -> 4 | F46: =E46 -> 4 | G46: =VLOOKUP(C46,[1]lists!I:M,5,FALSE) -> 57 | H46: =G46*(1+$M$1) -> 57 | I46: =F46*O46 -> 7.08 | J46: =F46*G46 -> 228 | K46: =J46*(1+$M$1) -> 228 | L46: =ROUND(H46*(1+$M$2),2) -> 131.1 | M46: =F46*L46 -> 524.4 | N46: =IFERROR((M46/K46)-1,"") -> 1.3 | O46: 1.77
B47: =IF(F47>=1,"SSG-TRT","") -> SSG-TRT | C47: TRT2001 | D47: Trolley for Rail | E47: =VLOOKUP(C47,VLOOKUP!H:R,11,FALSE) -> 2 | F47: =E47 -> 2 | G47: =VLOOKUP(C47,[1]lists!I:M,5,FALSE) -> 106 | H47: =G47*(1+$M$1) -> 106 | I47: =F47*O47 -> 2.74 | J47: =F47*G47 -> 212 | K47: =J47*(1+$M$1) -> 212 | L47: =ROUND(H47*(1+$M$2),2) -> 243.8 | M47: =F47*L47 -> 487.6 | N47: =IFERROR((M47/K47)-1,"") -> 1.3 | O47: 1.37
E48: =SUM(E39:E47) -> 17 | F48: =SUM(F39:F47) -> 17 | J48: SUBTOTAL | K48: =SUM(J39:J47) -> 1543 | L48: SUBTOTAL | M48: =SUM(M39:M47) -> 3548.9
A50: SENSORY GYM ACCESSORIES | Q50: SUPPLIER | R50: OUTSOURCED SUPPLIER
B51: =IF(F51>=1,C51,"") | C51: A-2216 | D51: Summit Adventure Slide | E51: Blue | F51: =IF(VLOOKUP!E20="yes-Blue",1,0) -> 0 | G51: 252 | H51: =G51*(1+$M$1) -> 252 | I51: =F51*O51 -> 0 | J51: =F51*G51 -> 0 | K51: =J51*(1+$M$1) -> 0 | L51: =ROUND(1155,2) -> 1155 | M51: =F51*L51 -> 0 | N51: =IFERROR((M51/K51)-1,"") | O51: 19
B52: =IF(F52>=1,C52,"") | C52: A-2216 | D52: Summit Adventure Slide | E52: Green | F52: =IF(VLOOKUP!E20="yes-Green",1,0) -> 0 | G52: 252 | H52: =G52*(1+$M$1) -> 252 | I52: =F52*O52 -> 0 | J52: =F52*G52 -> 0 | K52: =J52*(1+$M$1) -> 0 | L52: =ROUND(L51+G55-G54,2) -> 1155 | M52: =F52*L52 -> 0 | N52: =IFERROR((M52/K52)-1,"")
C53: A-2216 | D53: Summit Adventure Slide
B54: =IF(F54>=1,C54,"") | C54: B01MUEBGVK | D54: Summit Adventure Slide - 2Piece Plastic Scoop Slide | E54: Blue | F54: =IF(VLOOKUP!E20="yes-Blue",1,0) -> 0 | G54: 136 | H54: =G54*(1+$M$1) -> 136 | I54: =F54*O54 -> 0 | J54: =F54*G54 -> 0 | K54: =J54*(1+$M$1) -> 0 | L54: =L51 -> 1155 | N54: =IFERROR((M54/K54)-1,"") | Q54: Amazon | R54: Outsourced
B55: =IF(F55>=1,C55,"") | C55: B0018L8RJG | D55: Summit Adventure Slide - 2Piece Plastic Scoop Slide | E55: Green | F55: =IF(VLOOKUP!E20="yes-Green",1,0) -> 0 | G55: 136 | H55: =G55*(1+$M$1) -> 136 | I55: =F55*O55 -> 0 | J55: =F55*G55 -> 0 | K55: =J55*(1+$M$1) -> 0 | L55: =ROUND(L54+G60-G59,2) -> 1028.71 | N55: =IFERROR((M55/K55)-1,"") | Q55: Amazon | R55: Outsourced
B56: =IF(F56>=1,C56,"") | C56: WS8203 | D56: Summit Adventure Slide - Gray Slide Upcharge | F56: =IF(VLOOKUP!E21="YES",1,0) -> 0 | G56: 347 | H56: =G56*(1+$M$1) -> 347 | I56: =F56*O56 -> 0 | J56: =F56*G56 -> 0 | K56: =J56*(1+$M$1) -> 0 | L56: =ROUND(H56*(1+0.41),2) -> 489.27 | M56: =F56*L56 -> 0
B57: =IF(F57>=1,C57,"") | C57: 150045 | D57: Steamroller Ramp | E57: =IF(VLOOKUP!E22="YES",1,0) -> 0 | F57: =IF(VLOOKUP!E22="YES",1,0) -> 0 | G57: 977 | H57: =G57*(1+$M$1) -> 977 | I57: =F57*O57 -> 0 | J57: =F57*G57 -> 0 | K57: =J57*(1+$M$1) -> 0 | L57: =ROUND(H57*(1+0.41),2) -> 1377.57 | M57: =F57*L57 -> 0 | R57: Outsourced
B58: =IF(F58>=1,C58,"") | C58: A-2349 | D58: Adventure Steamroller/Scooter Board - Conversion Kit (Required) | F58: {=IFERROR(_xlfn.IFS(VLOOKUP!E23="Yes",1,F57=1,1,VLOOKUP!E23="No",),"")} -> 0 | G58: 81 | H58: =G58*(1+$M$1) -> 81 | I58: =IFERROR(F58*O58,"") -> 0 | J58: =F58*G58 -> 0 | K58: =J58*(1+$M$1) -> 0 | L58: =ROUND(H58*1.5,2) -> 121.5 | M58: =F58*L58 -> 0 | O58: 3.5
B59: =IF(F59>=1,C59,"") | C59: B07V3J9S2R | D59: 10' x 8' - Climbing Cargo Net Black | F59: 0 | G59: =307.99*1.15 -> 354.1885 | H59: =G59*(1+$M$1) -> 354.1885 | I59: =F59*O59 -> 0 | J59: =F59*G59 -> 0 | K59: =J59*(1+$M$1) -> 0 | L59: =ROUND(H59*1.5,2) -> 531.28 | M59: =F59*L59 -> 0 | N59: =IFERROR((M59/K59)-1,"") | O59: 11 | Q59: Amazon | R59: Outsourced
B60: =IF(F60>=1,C60,"") | C60: B07TSDMPNQ | D60: 8' x 6' - Climbing Cargo Net Black | F60: 0 | G60: =182.32*1.25 -> 227.9 | H60: =G60*(1+$M$1) -> 227.9 | I60: =F60*O60 -> 0 | J60: =F60*G60 -> 0 | K60: =J60*(1+$M$1) -> 0 | L60: =ROUND(H60*1.5,2) -> 341.85 | M60: =F60*L60 -> 0 | N60: =IFERROR((M60/K60)-1,"") | O60: 11 | Q60: Amazon | R60: Outsourced
B61: =IF(F61>=1,C61,"") | C61: SSG-SA-CFM | D61: Adventure Climbing Wall - Frame Mounted (Includes Climbing Holds) | F61: =IF(VLOOKUP!E25="Yes",1,0) -> 0 | G61: =VLOOKUP(C61,lists!I:L,4,FALSE) -> 825 | H61: =G61*(1+$M$1) -> 825 | I61: =F61*O61 -> 0 | J61: =F61*G61 -> 0 | K61: =J61*(1+$M$1) -> 0 | L61: =ROUND(H61*(1+$M$2),2) -> 1897.5 | M61: =F61*L61 -> 0 | N61: =IFERROR((M61/K61)-1,"") | O61: 170
B62: =IF(F62>=1,C62,"") -> SSG-SA-CWM | C62: SSG-SA-CWM | D62: Adventure Climbing Wall - Wall Mounted-Metal Studs (Includes Climbing Holds) | F62: =IF(VLOOKUP!E27="Yes",1,0) -> 1 | G62: =VLOOKUP(C62,lists!I:L,4,FALSE) -> 1062 | H62: =G62*(1+$M$1) -> 1062 | I62: =F62*O62 -> 241 | J62: =F62*G62 -> 1062 | K62: =J62*(1+$M$1) -> 1062 | L62: =ROUND(H62*(1+$M$2),2) -> 2442.6 | M62: =F62*L62 -> 2442.6 | O62: 241
B63: =IF(F63>=1,C63,"") | C63: T11412 | D63: Adjustable Indoor Climbing Wall | F63: 0 | G63: 1199.95 | H63: =G63*(1+$M$1) -> 1199.95 | I63: =F63*O63 -> 0 | J63: =F63*G63 -> 0 | K63: =J63*(1+$M$1) -> 0 | L63: =ROUND(H63*(1+0.69837076544856),2) -> 2037.96 | M63: =F63*L63 -> 0 | N63: =IFERROR((M63/K63)-1,"") | R63: Outsourced
B64: =IF(F64>=1,C64,"") | C64: SSG-SA-HOLDS | D64: Colored Climbing Holds | G64: 35.99 | H64: =G64*(1+$M$1) -> 35.99 | I64: =F64*O64 -> 0 | J64: =F64*G64 -> 0 | K64: =J64*(1+$M$1) -> 0 | L64: =ROUND(H64*(1+0.69837076544856),2) -> 61.12 | M64: =F64*L64 -> 0 | N64: =IFERROR((M64/K64)-1,"")
B65: =IF(F65>=1,C65,"") | C65: SSG-SA-HOLD-SCREWS | D65: Climbing Hold Connection Hardware | G65: 28.46 | H65: =G65*(1+$M$1) -> 28.46 | I65: =F65*O65 -> 0 | J65: =F65*G65 -> 0 | K65: =J65*(1+$M$1) -> 0 | L65: =ROUND(H65*(1+0.69837076544856),2) -> 48.34 | M65: =F65*L65 -> 0 | N65: =IFERROR((M65/K65)-1,"")
B66: =IF(F66>=1,C66,"") | C66: SSG-SA-CLIMB-WALL-MOUNT-KIT-ONLY | D66: Adventure Climbing Wall - Conversion Kit | G66: 185.34 | H66: =G66*(1+$M$1) -> 185.34 | I66: =F66*O66 -> 0 | J66: =F66*G66 -> 0 | K66: =J66*(1+$M$1) -> 0 | L66: =ROUND(H66*(1+0.69837076544856),2) -> 314.78 | M66: =F66*L66 -> 0
B67: =IF(F67>=1,C67,"") | C67: K-5000 | D67: Adventure Frame Mount Therapy Ball Rack (Length: 6') | E67: =IF(VLOOKUP!E18="Yes",1,0) -> 0 | F67: =E67 -> 0 | G67: =VLOOKUP(C67,lists!I:L,4,FALSE) -> 192 | H67: =G67*(1+$M$1) -> 192 | I67: =F67*O67 -> 0 | J67: =F67*G67 -> 0 | K67: =J67*(1+$M$1) -> 0 | L67: =ROUND(H67*(1+0.69837076544856),2) -> 326.09 | M67: =F67*L67 -> 0
B68: =IF(F68>=1,C68,"") -> SSCW67 | C68: SSCW67 | D68: Adventure Complete Column Wrap (67" x 4.875" x 3.5" x 1.375" ) | E68: =IF(VLOOKUP!E31="no",0,E5) -> 2 | F68: =E68 -> 2 | G68: 145 | H68: =G68*(1+$M$1) -> 145 | I68: =F68*O68 -> 0 | J68: =F68*G68 -> 290 | K68: =J68*(1+$M$1) -> 290 | L68: =ROUND(G68*1.525,2) -> 221.13 | M68: =F68*L68 -> 442.26 | N68: =IFERROR((M68/K68)-1,"") -> 0.52503448 | Q68: Resilite
B69: =IF(F69>=1,C69,"") -> SSUSP67 | C69: SSUSP67 | D69: Adventure U Shaped Safety Column Wrap (67" x 3.5" x 4.875" x 3.5" x 1.375" ) | E69: =IF(VLOOKUP!E31="no",0,E6) -> 2 | F69: 2 | G69: 155 | H69: =G69*(1+$M$1) -> 155 | I69: =F69*O69 -> 0 | J69: =F69*G69 -> 310 | K69: =J69*(1+$M$1) -> 310 | L69: =ROUND(G69*1.525,2) -> 236.38 | M69: =F69*L69 -> 472.76 | N69: =IFERROR((M69/K69)-1,"") -> 0.52503226 | Q69: Resilite
B70: =IF(F70>=1,C70,"") -> SSUSP72 | C70: SSUSP72 | D70: Adventure U Shaped Column Wrap Ladder Leg (72" x 2" x 3.875" x 2" x 1.375" ) | E70: =IF(VLOOKUP!E32="Yes",VLOOKUP!E7,0) -> 2 | F70: =E70 -> 2 | G70: 132 | H70: =G70*(1+$M$1) -> 132 | I70: =F70*O70 -> 0 | J70: =F70*G70 -> 264 | K70: =J70*(1+$M$1) -> 264 | L70: =ROUND(G70*1.525,2) -> 201.3 | M70: =F70*L70 -> 402.6 | N70: =IFERROR((M70/K70)-1,"") -> 0.525 | Q70: Resilite
B71: =IF(F71>=1,C71,"") | C71: SSTBW515 | D71: Zip Line Cable Safety Cover | E71: =IF(VLOOKUP!E17="Yes",1,0) -> 0 | F71: =E71 -> 0 | G71: 20 | H71: =G71*(1+$M$1) -> 20 | I71: =F71*O71 -> 0 | J71: =F71*G71 -> 0 | K71: =J71*(1+$M$1) -> 0 | L71: 34.5 | M71: =F71*L71 -> 0 | N71: =IFERROR((M71/K71)-1,"") | Q71: Resilite
A72: RESILITE 3.25" | B72: =IF(F72>=1,C72,"") | C72: R-SSA-0808CLM | D72: Adventure Floor Mat System (8' x 8' x 3.25") | E72: =IF(VLOOKUP!$E$30="Yes",VLOOKUP(C72,VLOOKUP!$D$96:$E$109,2,FALSE),0) -> 0 | F72: =E72 -> 0 | G72: =VLOOKUP(C72,'Resilite Mat Cost List'!$A$22:$H$49,8,FALSE) -> 989.85 | H72: =G72*(1+$M$1) -> 989.85 | I72: =F72*O72 -> 0 | J72: =F72*G72 -> 0 | K72: =J72*(1+$M$1) -> 0 | L72: =ROUND(H72*1.4,2) -> 1385.79 | M72: =F72*L72 -> 0 | N72: =IFERROR((M72/K72)-1,"")
B73: =IF(F73>=1,C73,"") | C73: R-SSA-0806CLM | D73: Adventure Floor Mat System (8' x 6' x 3.25") | E73: =IF(VLOOKUP!$E$30="Yes",VLOOKUP(C73,VLOOKUP!$D$96:$E$109,2,FALSE),0) -> 0 | F73: =E73 -> 0 | G73: =VLOOKUP(C73,'Resilite Mat Cost List'!$A$22:$H$49,8,FALSE) -> 773.88 | H73: =G73*(1+$M$1) -> 773.88 | I73: =F73*O73 -> 0 | J73: =F73*G73 -> 0 | K73: =J73*(1+$M$1) -> 0 | L73: =ROUND(H73*1.4,2) -> 1083.43 | M73: =F73*L73 -> 0 | N73: =IFERROR((M73/K73)-1,"")
B74: =IF(F74>=1,C74,"") | C74: R-SSA-0909CLM | D74: Adventure Floor Mat System (9' x 9' x 3.25") | E74: =IF(VLOOKUP!$E$30="Yes",VLOOKUP(C74,VLOOKUP!$D$96:$E$109,2,FALSE),0) -> 0 | F74: =E74 -> 0 | G74: =VLOOKUP(C74,'Resilite Mat Cost List'!$A$22:$H$49,8,FALSE) -> 1217.59 | H74: =G74*(1+$M$1) -> 1217.59 | I74: =F74*O74 -> 0 | J74: =F74*G74 -> 0 | K74: =J74*(1+$M$1) -> 0 | L74: =ROUND(H74*1.4,2) -> 1704.63 | M74: =F74*L74 -> 0 | N74: =IFERROR((M74/K74)-1,"")
B75: =IF(F75>=1,C75,"") | C75: R-SSA-0908CLM | D75: Adventure Floor Mat System (9' x 8' x 3.25") | E75: =IF(VLOOKUP!$E$30="Yes",VLOOKUP(C75,VLOOKUP!$D$96:$E$109,2,FALSE),0) -> 0 | F75: =E75 -> 0 | G75: =VLOOKUP(C75,'Resilite Mat Cost List'!$A$22:$H$49,8,FALSE) -> 1097.83 | H75: =G75*(1+$M$1) -> 1097.83 | I75: =F75*O75 -> 0 | J75: =F75*G75 -> 0 | K75: =J75*(1+$M$1) -> 0 | L75: =ROUND(H75*1.4,2) -> 1536.96 | M75: =F75*L75 -> 0 | N75: =IFERROR((M75/K75)-1,"")
B76: =IF(F76>=1,C76,"") | C76: R-SSA-0907CLM | D76: Adventure Floor Mat System (9' x 7' x 3.25") | E76: =IF(VLOOKUP!$E$30="Yes",VLOOKUP(C76,VLOOKUP!$D$96:$E$109,2,FALSE),0) -> 0 | F76: =E76 -> 0 | G76: =VLOOKUP(C76,'Resilite Mat Cost List'!$A$22:$H$49,8,FALSE) -> 978.07 | H76: =G76*(1+$M$1) -> 978.07 | I76: =F76*O76 -> 0 | J76: =F76*G76 -> 0 | K76: =J76*(1+$M$1) -> 0 | L76: =ROUND(H76*1.4,2) -> 1369.3 | M76: =F76*L76 -> 0 | N76: =IFERROR((M76/K76)-1,"")
B77: =IF(F77>=1,C77,"") -> R-SSA-1010CLM | C77: R-SSA-1010CLM | D77: Adventure Floor Mat System (10' x 10' x 3.25") | E77: =IF(VLOOKUP!$E$30="Yes",VLOOKUP(C77,VLOOKUP!$D$96:$E$109,2,FALSE),0) -> 1 | F77: =E77 -> 1 | G77: =VLOOKUP(C77,'Resilite Mat Cost List'!$A$22:$H$49,8,FALSE) -> 1468.9 | H77: =G77*(1+$M$1) -> 1468.9 | I77: =F77*O77 -> 0 | J77: =F77*G77 -> 1468.9 | K77: =J77*(1+$M$1) -> 1468.9 | L77: =ROUND(H77*1.4,2) -> 2056.46 | M77: =F77*L77 -> 2056.46 | N77: =IFERROR((M77/K77)-1,"") -> 0.4
B78: =IF(F78>=1,C78,"") | C78: R-SSA-1009CLM | D78: Adventure Floor Mat System (10' x 9' x 3.25") | E78: =IF(VLOOKUP!$E$30="Yes",VLOOKUP(C78,VLOOKUP!$D$96:$E$109,2,FALSE),0) -> 0 | F78: =E78 -> 0 | G78: =VLOOKUP(C78,'Resilite Mat Cost List'!$A$22:$H$49,8,FALSE) -> 1337.36 | H78: =G78*(1+$M$1) -> 1337.36 | I78: =F78*O78 -> 0 | J78: =F78*G78 -> 0 | K78: =J78*(1+$M$1) -> 0 | L78: =ROUND(H78*1.4,2) -> 1872.3 | M78: =F78*L78 -> 0 | N78: =IFERROR((M78/K78)-1,"")
B79: =IF(F79>=1,C79,"") | C79: R-SSA-1008CLM | D79: Adventure Floor Mat System (10' x 8' x 3.25") | E79: =IF(VLOOKUP!$E$30="Yes",VLOOKUP(C79,VLOOKUP!$D$96:$E$109,2,FALSE),0) -> 0 | F79: =E79 -> 0 | G79: =VLOOKUP(C79,'Resilite Mat Cost List'!$A$22:$H$49,8,FALSE) -> 1205.81 | H79: =G79*(1+$M$1) -> 1205.81 | I79: =F79*O79 -> 0 | J79: =F79*G79 -> 0 | K79: =J79*(1+$M$1) -> 0 | L79: =ROUND(H79*1.4,2) -> 1688.13 | M79: =F79*L79 -> 0 | N79: =IFERROR((M79/K79)-1,"")
B80: =IF(F80>=1,C80,"") | C80: R-SSA-1007CLM | D80: Adventure Floor Mat System (10' x 7' x 3.25") | E80: =IF(VLOOKUP!$E$30="Yes",VLOOKUP(C80,VLOOKUP!$D$96:$E$109,2,FALSE),0) -> 0 | F80: =E80 -> 0 | G80: =VLOOKUP(C80,'Resilite Mat Cost List'!$A$22:$H$49,8,FALSE) -> 1074.27 | H80: =G80*(1+$M$1) -> 1074.27 | I80: =F80*O80 -> 0 | J80: =F80*G80 -> 0 | K80: =J80*(1+$M$1) -> 0 | L80: =ROUND(H80*1.4,2) -> 1503.98 | M80: =F80*L80 -> 0 | N80: =IFERROR((M80/K80)-1,"")
B81: =IF(F81>=1,C81,"") | C81: R-SSA-1006CLM | D81: Adventure Floor Mat System (10' x 6' x CLM-3.25") | E81: =IF(VLOOKUP!$E$30="Yes",VLOOKUP(C81,VLOOKUP!$D$96:$E$109,2,FALSE),0) -> 0 | F81: =E81 -> 0 | G81: =VLOOKUP(C81,'Resilite Mat Cost List'!$A$22:$H$49,8,FALSE) -> 942.73 | H81: =G81*(1+$M$1) -> 942.73 | I81: =F81*O81 -> 0 | J81: =F81*G81 -> 0 | K81: =J81*(1+$M$1) -> 0 | L81: =ROUND(H81*1.4,2) -> 1319.82 | M81: =F81*L81 -> 0 | N81: =IFERROR((M81/K81)-1,"")
B82: =IF(F82>=1,C82,"") | C82: R-SSA-2010CLM | D82: Adventure Floor Mat System (20' x 10' x CLM-3.25") | E82: =IF(VLOOKUP!$E$30="Yes",VLOOKUP(C82,VLOOKUP!$D$96:$E$109,2,FALSE),0) -> 0 | F82: =E82 -> 0 | G82: =VLOOKUP(C82,'Resilite Mat Cost List'!$A$22:$H$49,8,FALSE) -> 2784.33 | H82: =G82*(1+$M$1) -> 2784.33 | I82: =F82*O82 -> 0 | J82: =F82*G82 -> 0 | K82: =J82*(1+$M$1) -> 0 | L82: =ROUND(H82*1.4,2) -> 3898.06 | M82: =F82*L82 -> 0 | N82: =IFERROR((M82/K82)-1,"")
B83: =IF(F83>=1,C83,"") | C83: R-SSA-2008CLM | D83: Adventure Floor Mat System (20' x 8' x CLM-3.25") | E83: =IF(VLOOKUP!$E$30="Yes",VLOOKUP(C83,VLOOKUP!$D$96:$E$109,2,FALSE),0) -> 0 | F83: =E83 -> 0 | G83: =VLOOKUP(C83,'Resilite Mat Cost List'!$A$22:$H$49,8,FALSE) -> 2285.65 | H83: =G83*(1+$M$1) -> 2285.65 | I83: =F83*O83 -> 0 | J83: =F83*G83 -> 0 | K83: =J83*(1+$M$1) -> 0 | L83: =ROUND(H83*1.4,2) -> 3199.91 | M83: =F83*L83 -> 0 | N83: =IFERROR((M83/K83)-1,"")
B84: =IF(F84>=1,C84,"") | C84: R-SSA-2007CLM | D84: Adventure Floor Mat System (20' x 7' x CLM-3.25") | E84: =IF(VLOOKUP!$E$30="Yes",VLOOKUP(C84,VLOOKUP!$D$96:$E$109,2,FALSE),0) -> 0 | F84: =E84 -> 0 | G84: =VLOOKUP(C84,'Resilite Mat Cost List'!$A$22:$H$49,8,FALSE) -> 2036.3 | H84: =G84*(1+$M$1) -> 2036.3 | I84: =F84*O84 -> 0 | J84: =F84*G84 -> 0 | K84: =J84*(1+$M$1) -> 0 | L84: =ROUND(H84*1.4,2) -> 2850.82 | M84: =F84*L84 -> 0 | N84: =IFERROR((M84/K84)-1,"")
B85: =IF(F85>=1,C85,"") | C85: R-SSA-1610CLM | D85: Adventure Floor Mat System (16' x 10' x CLM-3.25") | E85: =IF(VLOOKUP!$E$30="Yes",VLOOKUP(C85,VLOOKUP!$D$96:$E$109,2,FALSE),0) -> 0 | F85: =E85 -> 0 | G85: =VLOOKUP(C85,'Resilite Mat Cost List'!$A$22:$H$49,8,FALSE) -> 2258.16 | H85: =G85*(1+$M$1) -> 2258.16 | I85: =F85*O85 -> 0 | J85: =F85*G85 -> 0 | K85: =J85*(1+$M$1) -> 0 | L85: =ROUND(H85*1.4,2) -> 3161.42 | M85: =F85*L85 -> 0 | N85: =IFERROR((M85/K85)-1,"")
A86: RESILITE 2" | B86: =IF(F86>=1,C86,"") | C86: R-SSA-88CLM-2 | D86: Adventure Floor Mat System (8' x 8' x 2") | G86: =VLOOKUP(C86,'Resilite Mat Cost List'!$A$22:$H$49,8,FALSE) -> 642.81 | H86: =G86*(1+$M$1) -> 642.81 | I86: =F86*O86 -> 0 | J86: =F86*G86 -> 0 | K86: =J86*(1+$M$1) -> 0 | L86: =ROUND(H86*1.4,2) -> 899.93 | M86: =F86*L86 -> 0 | N86: =IFERROR((M86/K86)-1,"")
B87: =IF(F87>=1,C87,"") | C87: R-SSA-86CLM-2 | D87: Adventure Floor Mat System (8' x 6' x 2") | G87: =VLOOKUP(C87,'Resilite Mat Cost List'!$A$22:$H$49,8,FALSE) -> 502.56 | H87: =G87*(1+$M$1) -> 502.56 | I87: =F87*O87 -> 0 | J87: =F87*G87 -> 0 | K87: =J87*(1+$M$1) -> 0 | L87: =ROUND(H87*1.4,2) -> 703.58 | M87: =F87*L87 -> 0 | N87: =IFERROR((M87/K87)-1,"")
B88: =IF(F88>=1,C88,"") | C88: R-SSA-99CLM-2 | D88: Adventure Floor Mat System (9' x 9' x 2") | G88: =VLOOKUP(C88,'Resilite Mat Cost List'!$A$22:$H$49,8,FALSE) -> 790.71 | H88: =G88*(1+$M$1) -> 790.71 | I88: =F88*O88 -> 0 | J88: =F88*G88 -> 0 | K88: =J88*(1+$M$1) -> 0 | L88: =ROUND(H88*1.4,2) -> 1106.99 | M88: =F88*L88 -> 0 | N88: =IFERROR((M88/K88)-1,"")
B89: =IF(F89>=1,C89,"") | C89: R-SSA-98CLM-2 | D89: Adventure Floor Mat System (9' x 8' x 2") | G89: =VLOOKUP(C89,'Resilite Mat Cost List'!$A$22:$H$49,8,FALSE) -> 712.94 | H89: =G89*(1+$M$1) -> 712.94 | I89: =F89*O89 -> 0 | J89: =F89*G89 -> 0 | K89: =J89*(1+$M$1) -> 0 | L89: =ROUND(H89*1.4,2) -> 998.12 | M89: =F89*L89 -> 0 | N89: =IFERROR((M89/K89)-1,"")
B90: =IF(F90>=1,C90,"") | C90: R-SSA-97CLM-2 | D90: Adventure Floor Mat System (9' x 7' x 2") | G90: =VLOOKUP(C90,'Resilite Mat Cost List'!$A$22:$H$49,8,FALSE) -> 635.16 | H90: =G90*(1+$M$1) -> 635.16 | I90: =F90*O90 -> 0 | J90: =F90*G90 -> 0 | K90: =J90*(1+$M$1) -> 0 | L90: =ROUND(H90*1.4,2) -> 889.22 | M90: =F90*L90 -> 0 | N90: =IFERROR((M90/K90)-1,"")
B91: =IF(F91>=1,C91,"") | C91: R-SSA-1010CLM-2 | D91: Adventure Floor Mat System (10' x 10' x 2") | G91: =VLOOKUP(C91,'Resilite Mat Cost List'!$A$22:$H$49,8,FALSE) -> 953.91 | H91: =G91*(1+$M$1) -> 953.91 | I91: =F91*O91 -> 0 | J91: =F91*G91 -> 0 | K91: =J91*(1+$M$1) -> 0 | L91: =ROUND(H91*1.4,2) -> 1335.47 | M91: =F91*L91 -> 0 | N91: =IFERROR((M91/K91)-1,"")
B92: =IF(F92>=1,C92,"") | C92: R-SSA-1009CLM-2 | D92: Adventure Floor Mat System (10' x 9' x 2") | G92: =VLOOKUP(C92,'Resilite Mat Cost List'!$A$22:$H$49,8,FALSE) -> 868.49 | H92: =G92*(1+$M$1) -> 868.49 | I92: =F92*O92 -> 0 | J92: =F92*G92 -> 0 | K92: =J92*(1+$M$1) -> 0 | L92: =ROUND(H92*1.4,2) -> 1215.89 | M92: =F92*L92 -> 0 | N92: =IFERROR((M92/K92)-1,"")
B93: =IF(F93>=1,C93,"") | C93: R-SSA-1008CLM-2 | D93: Adventure Floor Mat System (10' x 8' x 2") | G93: =VLOOKUP(C93,'Resilite Mat Cost List'!$A$22:$H$49,8,FALSE) -> 783.06 | H93: =G93*(1+$M$1) -> 783.06 | I93: =F93*O93 -> 0 | J93: =F93*G93 -> 0 | K93: =J93*(1+$M$1) -> 0 | L93: =ROUND(H93*1.4,2) -> 1096.28 | M93: =F93*L93 -> 0 | N93: =IFERROR((M93/K93)-1,"")
B94: =IF(F94>=1,C94,"") | C94: R-SSA-1007CLM-2 | D94: Adventure Floor Mat System (10' x 7' x 2") | G94: =VLOOKUP(C94,'Resilite Mat Cost List'!$A$22:$H$49,8,FALSE) -> 697.64 | H94: =G94*(1+$M$1) -> 697.64 | I94: =F94*O94 -> 0 | J94: =F94*G94 -> 0 | K94: =J94*(1+$M$1) -> 0 | L94: =ROUND(H94*1.4,2) -> 976.7 | M94: =F94*L94 -> 0 | N94: =IFERROR((M94/K94)-1,"")
B95: =IF(F95>=1,C95,"") | C95: R-SSA-1006CLM-2 | D95: Adventure Floor Mat System (10' x 6' x CLM-2") | G95: =VLOOKUP(C95,'Resilite Mat Cost List'!$A$22:$H$49,8,FALSE) -> 612.21 | H95: =G95*(1+$M$1) -> 612.21 | I95: =F95*O95 -> 0 | J95: =F95*G95 -> 0 | K95: =J95*(1+$M$1) -> 0 | L95: =ROUND(H95*1.4,2) -> 857.09 | M95: =F95*L95 -> 0 | N95: =IFERROR((M95/K95)-1,"")
B96: =IF(F96>=1,C96,"") | C96: R-SSA-2010CLM-2 | D96: Adventure Floor Mat System (20' x 10' x CLM-2") | G96: =VLOOKUP(C96,'Resilite Mat Cost List'!$A$22:$H$49,8,FALSE) -> 1808.16 | H96: =G96*(1+$M$1) -> 1808.16 | I96: =F96*O96 -> 0 | J96: =F96*G96 -> 0 | K96: =J96*(1+$M$1) -> 0 | L96: =ROUND(H96*1.4,2) -> 2531.42 | M96: =F96*L96 -> 0 | N96: =IFERROR((M96/K96)-1,"")
B97: =IF(F97>=1,C97,"") | C97: R-SSA-2008CLM-2 | D97: Adventure Floor Mat System (20' x 8' x CLM-2") | G97: =VLOOKUP(C97,'Resilite Mat Cost List'!$A$22:$H$49,8,FALSE) -> 1484.31 | H97: =G97*(1+$M$1) -> 1484.31 | I97: =F97*O97 -> 0 | J97: =F97*G97 -> 0 | K97: =J97*(1+$M$1) -> 0 | L97: =ROUND(H97*1.4,2) -> 2078.03 | M97: =F97*L97 -> 0 | N97: =IFERROR((M97/K97)-1,"")
B98: =IF(F98>=1,C98,"") | C98: R-SSA-2007CLM-2 | D98: Adventure Floor Mat System (20' x 7' x CLM-2") | G98: =VLOOKUP(C98,'Resilite Mat Cost List'!$A$22:$H$49,8,FALSE) -> 1466.46 | H98: =G98*(1+$M$1) -> 1466.46 | I98: =F98*O98 -> 0 | J98: =F98*G98 -> 0 | K98: =J98*(1+$M$1) -> 0 | L98: =ROUND(H98*1.4,2) -> 2053.04 | M98: =F98*L98 -> 0 | N98: =IFERROR((M98/K98)-1,"")
B99: =IF(F99>=1,C99,"") | C99: R-SSA-1610CLM-2 | D99: Adventure Floor Mat System (16' x 10' x CLM-2") | G99: =VLOOKUP(C99,'Resilite Mat Cost List'!$A$22:$H$49,8,FALSE) -> 1322.39 | H99: =G99*(1+$M$1) -> 1322.39 | I99: =F99*O99 -> 0 | J99: =F99*G99 -> 0 | K99: =J99*(1+$M$1) -> 0 | L99: =ROUND(H99*1.4,2) -> 1851.35 | M99: =F99*L99 -> 0 | N99: =IFERROR((M99/K99)-1,"")
B100: =IF(F100>=1,C100,"") | C100: CUST-LOGO | D100: Custom Branding Setup (Logo Application on Mats & Padding) | F100: 0 | G100: 1250 | H100: =G100*(1+$M$1) -> 1250 | I100: =F100*O100 -> 0 | J100: =F100*G100 -> 0 | K100: =J100*(1+$M$1) -> 0 | L100: =ROUND(H100*1.25,2) -> 1562.5 | M100: =F100*L100 -> 0 | N100: =IFERROR((M100/K100)-1,"")
B101: =IF(F101>=1,C101,"") | C101: EXTENSION | D101: ="Adventure Floor Mat System Extensions - "&'Resilite Mat Cost List'!F15&" Sq Ft of Padding Around Frame" -> Adventure Floor Mat System Extensions - 168 Sq Ft of Padding Around Frame | F101: 0 | G101: ='Resilite Mat Cost List'!H15 -> 2315.04 | H101: =G101*(1+$M$1) -> 2315.04 | I101: =F101*O101 -> 0 | J101: =F101*G101 -> 0 | K101: =J101*(1+$M$1) -> 0 | L101: ='Resilite Mat Cost List'!I15 -> 3472.56 | M101: =F101*L101 -> 0 | N101: =IFERROR((M101/K101)-1,"") | Q101: Resilite
B102: =IF(F102>=1,C102,"") | C102: CUSTOM | D102: Custom Mat Design & Size | E102: - | F102: 0 | G102: 0 | H102: =G102*(1+$M$1) -> 0 | I102: =F102*O102 -> 0 | J102: =F102*G102 -> 0 | K102: =J102*(1+$M$1) -> 0 | L102: =H102*1.515 -> 0 | M102: =F102*L102 -> 0 | N102: =IFERROR((M102/K102)-1,"") | Q102: Resilite
...

Sheet Goldberg Order Details
A4: SUMMIT PRODUCT ORDER FORM
A5: Job: | B5: =Discovery!B3 -> Soar Autism Center - South Fort Collins
A6: Submission Date: | B6: =TODAY() -> 46225
A7: Shipment Details: | B7: =Discovery!B2 -> Tyler Galiotto
B8: =Discovery!B3 -> Soar Autism Center - South Fort Collins
B9: =Discovery!B7 -> 3801 Automation Way
B10: =Discovery!B8&" "&Discovery!B9 -> Fort Collins, CO 80525
A11: Phone: | B11: =Discovery!B11 -> 5203895979
A12: Email: | B12: =Discovery!B12
A13: Total Steel Weight: | B13: =CEILING(SUM(E18:E45)+5,10)&" (STEEL) LBS"&IF(Calcs!F47>0," + "&CEILING(SUM(Calcs!I41:I47),5)&" (TROLLEY) LBS"&" ="&(CEILING(SUM(E18:E45)+5,10)+CEILING(SUM(Calcs!I41:I47),5))&" TOTAL","")&" **DOESN'T INCLUDE HARDWARE OR CRATING**" -> 930 (STEEL) LBS + 70 (TROLLEY) LBS =1000 TOTAL **DOESN'T INCLUDE HARDWARE OR CRATING**
A14: Estimated Shipment Quote: | B14: =Discovery!B19 -> TBD
A15: Delivery Type: | B15: Lift Gate
A16: Powder Coat Brand: | B16: =Discovery!B44 -> Cardinal
A17: LINE # | B17: DESCRIPTION | C17: QTY PER UNIT | D17: Powder Color | E17: Weight (lbs) | F17: PRICE EACH | G17: TOTAL PRICE PER UNIT
A18: A-2245 | B18: =VLOOKUP(A18,Calcs!C5:D35,2,FALSE) -> Vertical Tall <80 w/Gusset | C18: =VLOOKUP(A18,Calcs!$C$5:$F$260,4,FALSE) -> 2 | D18: =Discovery!B47 -> CHANGEME | E18: =(VLOOKUP(A18,Calcs!$C$5:$O$298,13,FALSE))*C18 -> 136.5 | F18: =VLOOKUP(A18,lists!I:L,4,FALSE) -> 242.5 | G18: =C18*F18 -> 485
A19: A-2246 | B19: =VLOOKUP(A19,Calcs!C6:D40,2,FALSE) -> Vertical Tall <80 w/Gussets, Rungs & Handles | C19: =VLOOKUP(A19,Calcs!$C$5:$F$260,4,FALSE) -> 2 | D19: =Discovery!B47 -> CHANGEME | E19: =(VLOOKUP(A19,Calcs!$C$5:$O$298,13,FALSE))*C19 -> 134.58 | F19: =VLOOKUP(A19,lists!I:L,4,FALSE) -> 242.5 | G19: =C19*F19 -> 485
A20: A-2241 | B20: =VLOOKUP(A20,Calcs!C7:D42,2,FALSE) -> Corner Post <80 1-Way Weld Assembly | C20: =VLOOKUP(A20,Calcs!$C$5:$F$260,4,FALSE) -> 0 | D20: =Discovery!B48 -> CHANGEME | E20: =(VLOOKUP(A20,Calcs!$C$5:$O$298,13,FALSE))*C20 -> 0 | F20: =VLOOKUP(A20,lists!I:L,4,FALSE) -> 73 | G20: =C20*F20 -> 0
A21: A-2242 | B21: =VLOOKUP(A21,Calcs!C8:D43,2,FALSE) -> Corner Post <80 2-Way Weld Assembly | C21: =VLOOKUP(A21,Calcs!$C$5:$F$260,4,FALSE) -> 4 | D21: =Discovery!B48 -> CHANGEME | E21: =(VLOOKUP(A21,Calcs!$C$5:$O$298,13,FALSE))*C21 -> 59.728 | F21: =VLOOKUP(A21,lists!I:L,4,FALSE) -> 76.5 | G21: =C21*F21 -> 306
A22: A-2243 | B22: =VLOOKUP(A22,Calcs!C9:D44,2,FALSE) -> Corner Post <80 3-Way Weld Assembly | C22: =VLOOKUP(A22,Calcs!$C$5:$F$260,4,FALSE) -> 0 | D22: =Discovery!B48 -> CHANGEME | E22: =(VLOOKUP(A22,Calcs!$C$5:$O$298,13,FALSE))*C22 -> 0 | F22: =VLOOKUP(A22,lists!I:L,4,FALSE) -> 97 | G22: =C22*F22 -> 0
A23: A-2244 | B23: =VLOOKUP(A23,Calcs!C10:D45,2,FALSE) -> Corner Post <80 4-Way Weld Assembly | C23: =VLOOKUP(A23,Calcs!$C$5:$F$260,4,FALSE) -> 0 | D23: =Discovery!B48 -> CHANGEME | E23: =(VLOOKUP(A23,Calcs!$C$5:$O$298,13,FALSE))*C23 -> 0 | F23: =VLOOKUP(A23,lists!I:L,4,FALSE) -> 101 | G23: =C23*F23 -> 0
A24: A-2225 | B24: =VLOOKUP(A24,Calcs!C12:D46,2,FALSE) -> Mid Span 1-Way Saddle Alt Weld Assembly | C24: =VLOOKUP(A24,Calcs!$C$5:$F$260,4,FALSE) -> 4 | D24: =Discovery!B48 -> CHANGEME | E24: =(VLOOKUP(A24,Calcs!$C$5:$O$298,13,FALSE))*C24 -> 25.84 | F24: =VLOOKUP(A24,lists!I:L,4,FALSE) -> 46 | G24: =C24*F24 -> 184
A25: P-2531 | B25: =VLOOKUP(A25,Calcs!C13:D47,2,FALSE) -> Ladder Leg Footless | C25: =VLOOKUP(A25,Calcs!$C$5:$F$260,4,FALSE) -> 2 | D25: =Discovery!B49 -> CHANGEME | E25: =(VLOOKUP(A25,Calcs!$C$5:$O$298,13,FALSE))*C25 -> 61.82 | F25: =VLOOKUP(A25,lists!I:L,4,FALSE) -> 97.5 | G25: =C25*F25 -> 195
A26: A-2253 | B26: =VLOOKUP(A26,Calcs!C14:D59,2,FALSE) -> Single Leg Inner Ladder Sleeve Footless Weld Assembly | C26: =VLOOKUP(A26,Calcs!$C$5:$F$260,4,FALSE) -> 2 | D26: =Discovery!B49 -> CHANGEME | E26: =(VLOOKUP(A26,Calcs!$C$5:$O$298,13,FALSE))*C26 -> 8.98 | F26: =VLOOKUP(A26,lists!I:L,4,FALSE) -> 65.5 | G26: =C26*F26 -> 131
A27: A-2248 | B27: =VLOOKUP(A27,Calcs!C15:D60,2,FALSE) -> Double Leg Inner Ladder Sleeve | C27: =VLOOKUP(A27,Calcs!$C$5:$F$260,4,FALSE) -> 0 | D27: =Discovery!B49 -> CHANGEME | E27: =(VLOOKUP(A27,Calcs!$C$5:$O$298,13,FALSE))*C27 -> 0 | F27: =VLOOKUP(A27,lists!I:L,4,FALSE) -> 79 | G27: =C27*F27 -> 0
A28: P-2206 | B28: 6' Full Bay HSS Member Alt W/Logo | C28: =VLOOKUP(A28,Calcs!$C$5:$F$260,4,FALSE) -> 0 | D28: =Discovery!B48 -> CHANGEME | E28: =(VLOOKUP(A28,Calcs!$C$5:$O$298,13,FALSE))*C28 -> 0 | F28: =VLOOKUP(A28,lists!I:L,4,FALSE) -> 150 | G28: =C28*F28 -> 0
A29: p-2207 | B29: 7' Full Bay HSS Member Alt w/ Logo | C29: =VLOOKUP(A29,Calcs!$C$5:$F$260,4,FALSE) -> 0 | D29: =Discovery!B48 -> CHANGEME | E29: =(VLOOKUP(A29,Calcs!$C$5:$O$298,13,FALSE))*C29 -> 0 | F29: =VLOOKUP(A29,lists!I:L,4,FALSE) -> 150 | G29: =C29*F29 -> 0
A30: A-2408 | B30: =VLOOKUP(A30,Calcs!C19:D61,2,FALSE) -> 8' Half Bay <80 HSS Member w/Splices & HDWE | C30: =VLOOKUP(A30,Calcs!$C$5:$F$260,4,FALSE) -> 0 | D30: =Discovery!B48 -> CHANGEME | E30: =(VLOOKUP(A30,Calcs!$C$5:$O$298,13,FALSE))*C30 -> 0 | F30: =VLOOKUP(A30,lists!I:L,4,FALSE) -> 190 | G30: =C30*F30 -> 0
A31: A-2409 | B31: =VLOOKUP(A31,Calcs!C20:D68,2,FALSE) -> 9' Half Bay <80 HSS Member w/Splices & HDWE | C31: =VLOOKUP(A31,Calcs!$C$5:$F$260,4,FALSE) -> 0 | D31: =Discovery!B48 -> CHANGEME | E31: =(VLOOKUP(A31,Calcs!$C$5:$O$298,13,FALSE))*C31 -> 0 | F31: =VLOOKUP(A31,lists!I:L,4,FALSE) -> 200 | G31: =C31*F31 -> 0
A32: A-2410 | B32: =VLOOKUP(A32,Calcs!C21:D71,2,FALSE) -> 10' Half Bay <80 HSS Member w/Splices & HDWE | C32: =VLOOKUP(A32,Calcs!$C$5:$F$260,4,FALSE) -> 4 | D32: =Discovery!B48 -> CHANGEME | E32: =(VLOOKUP(A32,Calcs!$C$5:$O$298,13,FALSE))*C32 -> 271.6 | F32: =VLOOKUP(A32,lists!I:L,4,FALSE) -> 200 | G32: =C32*F32 -> 800
A33: P-2330 | B33: =VLOOKUP(A33,Calcs!C22:D71,2,FALSE) -> Monkey Bar / Ladder Rungs w/ 4 Threaded Holes | C33: =VLOOKUP(A33,Calcs!$C$5:$F$260,4,FALSE) -> 19 | D33: =Discovery!B49 -> CHANGEME | E33: =(VLOOKUP(A33,Calcs!$C$5:$O$298,13,FALSE))*C33 -> 45.41 | F33: =VLOOKUP(A33,lists!I:L,4,FALSE) -> 20.5 | G33: =C33*F33 -> 389.5
A34: A-2418 | B34: =VLOOKUP(A34,Calcs!C25:D71,2,FALSE) -> 8' Half Bay Monkey Bar HSS Member w/ Logo | C34: =VLOOKUP(A34,Calcs!$C$5:$F$260,4,FALSE) -> 0 | D34: =Discovery!B48 -> CHANGEME | E34: =(VLOOKUP(A34,Calcs!$C$5:$O$298,13,FALSE))*C34 -> 0 | F34: =VLOOKUP(A34,lists!I:L,4,FALSE) -> 190 | G34: =C34*F34 -> 0
A35: A-2419 | B35: =VLOOKUP(A35,Calcs!C26:D104,2,FALSE) -> 9' Half Bay <80 Monkey Bar HSS w/Splices & HDWE | C35: =VLOOKUP(A35,Calcs!$C$5:$F$260,4,FALSE) -> 0 | D35: =Discovery!B48 -> CHANGEME | E35: =(VLOOKUP(A35,Calcs!$C$5:$O$298,13,FALSE))*C35 -> 0 | F35: =VLOOKUP(A35,lists!I:L,4,FALSE) -> 200 | G35: =C35*F35 -> 0
A36: A-2420 | B36: =VLOOKUP(A36,Calcs!C27:D105,2,FALSE) -> 10' Half Bay <80 Monkey Bar HSS w/Splices & HDWE | C36: =VLOOKUP(A36,Calcs!$C$5:$F$260,4,FALSE) -> 2 | D36: =Discovery!B48 -> CHANGEME | E36: =(VLOOKUP(A36,Calcs!$C$5:$O$298,13,FALSE))*C36 -> 132.44 | F36: =VLOOKUP(A36,lists!I:L,4,FALSE) -> 200 | G36: =C36*F36 -> 400
A37: P-2024 | B37: =VLOOKUP(A37,Calcs!C28:D130,2,FALSE) -> Zip Line HSS Tube | C37: =VLOOKUP(A37,Calcs!$C$5:$F$260,4,FALSE) -> 0 | D37: =Discovery!B48 -> CHANGEME | E37: =(VLOOKUP(A37,Calcs!$C$5:$O$298,13,FALSE))*C37 -> 0 | F37: =VLOOKUP(A37,lists!I:L,4,FALSE) -> 20 | G37: =C37*F37 -> 0
A38: A-2530 | B38: ADVENTURE ZIPLINE COLLAR STIFFENER WELD ASSY | C38: =VLOOKUP(A38,Calcs!$C$5:$F$260,4,FALSE) -> 0 | D38: =Discovery!B48 -> CHANGEME | E38: =(VLOOKUP(A38,Calcs!$C$5:$O$298,13,FALSE))*C38 -> 0 | F38: =VLOOKUP(A38,lists!I:L,4,FALSE) -> 53 | G38: =C38*F38 -> 0
A39: P-2124 | B39: =VLOOKUP(A39,Calcs!C30:D132,2,FALSE) -> Quick Shift Saddle Bracket™ | C39: =VLOOKUP(A39,Calcs!$C$5:$F$260,4,FALSE) -> 4 | D39: =Discovery!B49 -> CHANGEME | E39: =(VLOOKUP(A39,Calcs!$C$5:$O$298,13,FALSE))*C39 -> 19.32 | F39: =VLOOKUP(A39,lists!I:L,4,FALSE) -> 51 | G39: =C39*F39 -> 204
A40: P-2028 | B40: =VLOOKUP(A40,Calcs!C31:D133,2,FALSE) -> Base Plate Shield | C40: =VLOOKUP(A40,Calcs!$C$5:$F$260,4,FALSE) -> 8 | D40: =Discovery!B47 -> CHANGEME | E40: =(VLOOKUP(A40,Calcs!$C$5:$O$298,13,FALSE))*C40 -> 22.48 | F40: =VLOOKUP(A40,lists!I:L,4,FALSE) -> 25 | G40: =C40*F40 -> 200
A41: P-2500 | B41: CLIMBING WALL SHIELD | C41: =VLOOKUP(A41,Calcs!$C$5:$F$260,4,FALSE) -> 0 | D41: =Discovery!B48 -> CHANGEME | E41: =(VLOOKUP(A41,Calcs!$C$5:$O$298,13,FALSE))*C41 -> 0 | F41: =VLOOKUP(A41,lists!I:L,4,FALSE) -> 52 | G41: =C41*F41 -> 0
A42: P-2501 | B42: LADDER TOP SHIELD 90 DEGREE | C42: =VLOOKUP(A42,Calcs!$C$5:$F$260,4,FALSE) -> 0 | D42: =Discovery!B48 -> CHANGEME | E42: =(VLOOKUP(A42,Calcs!$C$5:$O$298,13,FALSE))*C42 -> 0 | F42: =VLOOKUP(A42,lists!I:L,4,FALSE) -> 52 | G42: =C42*F42 -> 0
A43: P-2502 | B43: LADDER TOP SHIELD 50 DEGREE | C43: =VLOOKUP(A43,Calcs!$C$5:$F$260,4,FALSE) -> 0 | D43: =Discovery!B48 -> CHANGEME | E43: =(VLOOKUP(A43,Calcs!$C$5:$O$298,13,FALSE))*C43 -> 0 | F43: =VLOOKUP(A43,lists!I:L,4,FALSE) -> 52 | G43: =C43*F43 -> 0
A44: P-2018 | B44: =VLOOKUP(A44,Calcs!C35:D134,2,FALSE) -> Trolley Bar | C44: =VLOOKUP(A44,Calcs!$C$5:$F$260,4,FALSE) -> 1 | D44: =Discovery!B49 -> CHANGEME | E44: =(VLOOKUP(A44,Calcs!$C$5:$O$298,13,FALSE))*C44 -> 2.27 | F44: =VLOOKUP(A44,lists!I:L,4,FALSE) -> 14 | G44: =C44*F44 -> 14
A45: P-2025 | B45: =VLOOKUP(A45,Calcs!C39:D135,2,FALSE) -> Trolley Bar Plate | C45: =VLOOKUP(A45,Calcs!$C$5:$F$260,4,FALSE) -> 2 | D45: =Discovery!B49 -> CHANGEME | E45: =(VLOOKUP(A45,Calcs!$C$5:$O$298,13,FALSE))*C45 -> 0.594 | F45: =VLOOKUP(A45,lists!I:L,4,FALSE) -> 12 | G45: =C45*F45 -> 24
A46: A-2216 | B46: SummitAdventure Slide | C46: =Calcs!F51+Calcs!F52 -> 0 | D46: =Discovery!B50 -> CHANGEME | E46: =(VLOOKUP(A46,Calcs!$C$5:$O$298,13,FALSE))*C46 -> 0 | F46: =Calcs!G51 -> 252 | G46: =C46*F46 -> 0
A47: SSG-BLUE-SLIDE | B47: Summit Adventure Blue 2-piece Plastic Slide | C47: =Calcs!F51 -> 0 | F47: 0 | G47: 0
A48: SSG-GREEN-SLIDE | B48: Summit Adventure Green 2-piece Plastic Slide | C48: =Calcs!F52 -> 0 | F48: 0 | G48: 0
A49: SSG-SA-CFM | B49: SummitAdventure Climbing Wall - Frame Mounted (No Climb Holds) | C49: =Calcs!F61 -> 0 | D49: =Discovery!B51 -> CHANGEME | E49: =(VLOOKUP(A49,Calcs!$C$5:$O$298,13,FALSE))*C49 -> 0 | F49: =Calcs!G61 -> 825 | G49: =C49*F49 -> 0
A50: SSG-SA-CWM | B50: SummitAdventure Climbing Wall - Wall Mounted (No Climb Holds) | C50: =Calcs!F62 -> 1 | D50: =Discovery!B51 -> CHANGEME | E50: =(VLOOKUP(A50,Calcs!$C$5:$O$298,13,FALSE))*C50 -> 241 | F50: =Calcs!G62 -> 1062 | G50: =C50*F50 -> 1062
A51: A-2349 | B51: WELD ASSY; EXTENDED LADDER RUNG FOR STEAMROLLER | C51: =VLOOKUP(A51,Calcs!C:K,4,FALSE) -> 0 | D51: =Discovery!B49 -> CHANGEME | E51: =(VLOOKUP(A51,Calcs!$C$5:$O$298,13,FALSE))*C51 -> 0 | F51: =VLOOKUP(A51,lists!I:M,4,FALSE) -> 81 | G51: =C51*F51 -> 0
A52: 6820H-LAD | B52: PLAYGROUND HANDLES, GATE HANDLES 1 HANDLE (B08K2V5G6T) | C52: =Calcs!F183 -> 4 | F52: =VLOOKUP(A52,lists!I:L,4,FALSE) -> 15 | G52: =C52*F52 -> 60
A53: 6820H-LAK | B53: 1/2" x 4" Strong-Tie THD50400H Titen HD Screw Anchor, Zinc | C53: =Calcs!F184 -> 17 | F53: =VLOOKUP(A53,lists!I:L,4,FALSE) -> 2.75 | G53: =C53*F53 -> 46.75
A54: 6820H-LDD | B54: 3/8 DOUBLE SWIVEL EYE BOLT (AAC BRKT SWIVEL OPTION) | C54: =Calcs!F185 -> 4 | F54: 2 | G54: =C54*F54 -> 8
A55: 6820H-LAC-G | B55: EYE BOLT; 3/8-16 X .75 LENGTH | C55: =Calcs!F186 -> 0 | F55: =VLOOKUP(A55,lists!I:L,4,FALSE) -> 6 | G55: =C55*F55 -> 0
A56: 6820H-LP | B56: EYE BOLT; 1/2-13 X 4 LENGTH | C56: =Calcs!F187 -> 12 | F56: =VLOOKUP(A56,lists!I:L,4,FALSE) -> 8.95 | G56: =C56*F56 -> 107.4
A57: 6820H-LY | B57: EYE BOLT; 1/4-20 X 2 LENGTH | C57: =Calcs!F189 -> 2 | F57: =VLOOKUP(A57,lists!I:L,4,FALSE) -> 6.5 | G57: =C57*F57 -> 13
A58: 6820H-LAI | B58: QUICK SHIFT BRACKET BENT PIN W/LANYARD | C58: =Calcs!F190 -> 8 | F58: 0.1 | G58: =C58*F58 -> 0.8
A59: 6820H-LC | B59: HEX NYLON INSERT LOCK NUT, ZINC PLATED GRADE 5 STEEL, 1/2-13 | C59: =Calcs!F191 -> 64 | F59: =VLOOKUP(A59,lists!I:L,4,FALSE) -> 0.34 | G59: =C59*F59 -> 21.76
A60: 6820H-LX | B60: FLAT SHOULDER ROD END BOLT 5/16-18 X 1 SHANK THREAD | C60: =Calcs!F192 -> 2 | F60: =VLOOKUP(A60,lists!I:L,4,FALSE) -> 15.5 | G60: =C60*F60 -> 31
A61: 6820H-LF | B61: HEX NYLON INSERT LOCK NUT, ZINC PLATED GRADE 5 STEEL, 3/8-16 | C61: =Calcs!F193 -> 5 | F61: =VLOOKUP(A61,lists!I:L,4,FALSE) -> 0.25 | G61: =C61*F61 -> 1.25
A62: 6820H-LB | B62: WASHER 1/2 FLAT Zinc plated grade 5 steel | C62: =Calcs!F194 -> 137 | F62: =VLOOKUP(A62,lists!I:L,4,FALSE) -> 0.18 | G62: =C62*F62 -> 24.66
A63: 6820H-LA | B63: HEX BOLT, ZINC PLATED GRADE 5 STEEL, 1/2-13 X 4-1/2" | C63: =Calcs!F195 -> 44 | F63: =VLOOKUP(A63,lists!I:L,4,FALSE) -> 1 | G63: =C63*F63 -> 44
A64: 6820H-LAG | B64: HEX BOLT, ZINC PLATED GRADE 5 STEEL, 1/2-13 X 4" | C64: =Calcs!F196 -> 0 | F64: =VLOOKUP(A64,lists!I:L,4,FALSE) -> 0.95
A65: 6820H-LH | B65: TAP BOLT, ZINC PLATED GRADE 5 STEEL, 3/8-16 X 2-1/4" | C65: =Calcs!F197 -> 0 | F65: =VLOOKUP(A65,lists!I:L,4,FALSE) -> 0.55 | G65: =C65*F65 -> 0
A66: 6820H-LG | B66: TAP BOLT, ZINC PLATED GRADE 5 STEEL, 3/8-16 X 1-3/4" | C66: =Calcs!F198 -> 19 | F66: =VLOOKUP(A66,lists!I:L,4,FALSE) -> 0.4 | G66: =C66*F66 -> 7.6
A67: 6820H-LI | B67: HEX BOLT, ZINC PLATED GRADE 5 STEEL, 1/4-20 X 2-3/4" | C67: =Calcs!F199 -> 4 | F67: =VLOOKUP(A67,lists!I:L,4,FALSE) -> 0.26 | G67: =C67*F67 -> 1.04
A68: 6820H-LJ | B68: HEX BOLT, ZINC PLATED GRADE 5 STEEL, 1/4-20 X 4" | C68: =Calcs!F200 -> 4 | F68: =VLOOKUP(A68,lists!I:L,4,FALSE) -> 0.5 | G68: =C68*F68 -> 2
A69: 6820H-LK | B69: USS FLAT WASHER, ZINC PLATED GRADE 5 STEEL, 1/4 | C69: =Calcs!F201 -> 18 | F69: =VLOOKUP(A69,lists!I:L,4,FALSE) -> 0.09 | G69: =C69*F69 -> 1.62
A70: 6820H-LL | B70: HEX NYLON INSERT LOCK NUT, ZINC PLATED GRADE 5 STEEL, 1/4-20 | C70: =Calcs!F202 -> 10 | F70: =VLOOKUP(A70,lists!I:L,4,FALSE) -> 0.14 | G70: =C70*F70 -> 1.4
A71: 6820H-LT | B71: COUPLING NUT, ZINC PLATED STEEL, 5/16-18 X 1-3/4 | C71: =Calcs!F203 -> 2 | F71: =VLOOKUP(A71,lists!I:L,4,FALSE) -> 1.25 | G71: =C71*F71 -> 2.5
A72: 6820H-LAB | B72: HEX NUT, ZINC PLATED GRADE 5 STEEL, 5/16-18 | C72: =Calcs!F204 -> 8 | F72: =VLOOKUP(A72,lists!I:L,4,FALSE) -> 0.11 | G72: =C72*F72 -> 0.88
A73: 6820H-LAA | B73: LOCK WASHER, ZINC PLATED STEEL, 5/16 | C73: =Calcs!F205 -> 10 | F73: =VLOOKUP(A73,lists!I:L,4,FALSE) -> 0.07 | G73: =C73*F73 -> 0.7
A74: 6820H-LU | B74: USS FLAT WASHER, ZINC PLATED GRADE 5 STEEL, 5/16 | C74: =Calcs!F206 -> 22 | F74: =VLOOKUP(A74,lists!I:L,4,FALSE) -> 0.09 | G74: =C74*F74 -> 1.98
A75: 6820H-LV | B75: HEX BOLT, ZINC PLATED GRADE 5 STEEL, 5/16"-18 X 1" | C75: =Calcs!F207 -> 14 | F75: =VLOOKUP(A75,lists!I:L,4,FALSE) -> 0.3 | G75: =C75*F75 -> 4.2
A76: 6820H-LW | B76: HEX NYLON INSERT LOCK NUT, ZINC PLATED GRADE 5 STEEL, 5/16-18 | C76: =Calcs!F208 -> 4 | F76: =VLOOKUP(A76,lists!I:L,4,FALSE) -> 0.17 | G76: =C76*F76 -> 0.68
... A86: 6820H-LAJ | B86: HEX BOLT, ZINC PLATED GRADE 5 STEEL, 1/2-13 X 5" | C86: =Calcs!F218 -> 0 | F86: =VLOOKUP(A86,lists!I:L,4,FALSE) -> 1.74 | G86: =C86*F86 -> 0
A87: 6820H-LAL | B87: 1/2" X 4.25" Strong-Bolt 2 Wedge Anchor, Zinc | C87: 0 | F87: 0 | G87: 0
A88: 6820H-LAN | B88: 60" Multi-Pocket Black Sling | C88: =VLOOKUP!E53 -> 0 | F88: 0 | G88: 0
A89: TR2000-A09 | B89: 9' Aluminum Enclosed Rail 550lbs. Max Weight | C89: =Calcs!F42 -> 2 | F89: 0 | G89: =C89*F89 -> 0
A90: TRH2005 | B90: Universal Threaded Rod Hanger | C90: =Calcs!F45 -> 6 | F90: 0 | G90: =C90*F90 -> 0
A91: TRN2016 | B91: End Cap for Rail | C91: =Calcs!F46 -> 4 | F91: 0 | G91: =C91*F91 -> 0
A92: TRT2001 | B92: Trolley for Rail | C92: =Calcs!F47 -> 2 | F92: 0 | G92: =C92*F92 -> 0
A93: ZIPLINE-WIRE | B93: Zip Line Wire Rope | C93: =VLOOKUP(A93,Calcs!$C$5:$F$260,4,FALSE) -> 0 | F93: 0 | G93: =C93*F93 -> 0
A94: ZIPLINE-TROLLEY | B94: Zip Line Trolley | C94: =VLOOKUP(A94,Calcs!$C$5:$F$260,4,FALSE) -> 0 | F94: 0 | G94: =C94*F94 -> 0
A95: SSG-SA-SWIVEL-EYE | B95: SUMMIT ADVENTURE STAND ALONE SWING & SWIVEL EYEBOLT | C95: =VLOOKUP(A95,Calcs!$C$5:$F$260,4,FALSE) -> 0 | F95: 0 | G95: 0
G101: =C101*F101 -> 0
G102: =C102*F102 -> 0
B104: Sub Total | G104: =SUM(G18:G103) -> 5308.7
B105: Prismatic Custom Color Upcharge | G105: =IF(B16="Prismatic-Other",Discovery!B45,IF(B16="Prismatic",250,0)) -> 0
B106: Crating Charge | G106: 100
B107: Shipping Estimate | G107: =B14 -> TBD
B109: Grand Total | G109: =SUM(G104:G107) -> 5408.7

Sheet Sensory Space Proposal
B1: Summit Sensory Gym | J1: PSF File Name | K1: =B10&" - PSF 73 - "&TEXT(H9,"MMDDYYYY") -> Soar Autism Center - South Fort Collins - PSF 73 - 07222026
B2: 6150 S Geneva Court | J2: Proposal File Name | K2: =B10&" - "&F9&" - "&TEXT(H9,"MMDDYYYY") -> Soar Autism Center - South Fort Collins - SENSORY-SS-260722-001 - 07222026
B3: Englewood, CO 80111
B4: Phone: 720-457-5500
B5: Fax: 720-242-8085
B6: Support@SummitSensory.com
B8: CUSTOMER INFO | F8: PROPOSAL | H8: DATE
B9: =Discovery!B2 -> Tyler Galiotto | F9: ="SENSORY-" & UPPER(LEFT(B10,1) & RIGHT(B10,1)) & "-" & TEXT(H9,"yymmdd") & "-" & TEXT( IF(AND(ISNUMBER(K11),K11>0), K11, COUNTIFS($B$10:B10,B10,$H$9:H9,H9) ), "000") -> SENSORY-SS-260722-001 | H9: =TODAY() -> 46225
B10: =Discovery!B3 -> Soar Autism Center - South Fort Collins | F10: PROJECT ID # | H10: VALID UNTIL
B11: =Discovery!B4 -> 3801 Automation Way | F11: ="SSG-"&Discovery!B13 -> SSG-12552093278 | H11: =H9+6 -> 46231 | J11: Proposal # Override | K11: 0
B12: =Discovery!B5&" "&Discovery!B6&" "&Discovery!B10 -> Fort Collins, CO 80525 United States
B14: PROPOSAL DETAILS
B15: SENSORY ROOM EQUIPMENT & SUPPLIES - ITEMIZED PRODUCT PROPOSAL
B18: DESCRIPTION | C18: ITEM # | D18: SKU | E18: PRODUCT NOTES | F18: QTY | G18: FREIGHT COST (USD) | H18: TOTAL COST (USD)
C19: 1 | G19: 0 | H19: =F19+G19 -> 0
C20: =C19+1 -> 2 | G20: 0 | H20: =F20+G20 -> 0
C21: =C20+1 -> 3 | G21: 0 | H21: =F21+G21 -> 0
C22: =C21+1 -> 4 | G22: 0 | H22: =F22+G22 -> 0
C23: =C22+1 -> 5 | G23: 0 | H23: =F23+G23 -> 0
C24: =C23+1 -> 6 | G24: 0 | H24: =F24+G24 -> 0
C25: =C24+1 -> 7 | G25: 0 | H25: =F25+G25 -> 0
C26: =C25+1 -> 8 | G26: 0 | H26: =F26+G26 -> 0
C27: =C26+1 -> 9 | G27: 0 | H27: =F27+G27 -> 0
C28: =C27+1 -> 10 | G28: 0 | H28: =F28+G28 -> 0
C29: =C28+1 -> 11 | G29: 0 | H29: =F29+G29 -> 0
C30: =C29+1 -> 12 | G30: 0 | H30: =F30+G30 -> 0
C31: =C30+1 -> 13 | G31: 0 | H31: =F31+G31 -> 0
... C195: =C194+1 -> 177 | G195: 0 | H195: =F195+G195 -> 0
F196: SUBTOTAL: | H196: =SUM(H19:H195) -> 0
F197: ESTIMATED TAXES: | H197: 0
F198: TOTAL PROPOSAL: | H198: =H196+H197 -> 0
B200: IMPORTANT PROPOSAL DETAILS: This proposal serves as a detailed estimate of the total cost for the products and services outlined and does not constitute an invoice. Once signed and returned, it becomes a binding agreement, confirming acceptance of the order and associated payment terms. A 50% deposit is required to initiate production, with the remaining balance due prior to shipment. The signed proposal may be returned by mail or fax using the contact information provided above. For payments made by credit card, a 3.5% processing fee will be added to the total amount.
B202: CRATING & FREIGHT FEES: Final crating and freight charges will be calculated and invoiced at the time of shipment based on the actual costs incurred and the rates in effect at that time. Summit makes no representations or warranties, express or implied, regarding the availability or stability of crating costs or freight rates prior to shipment, and Buyer acknowledges and agrees that such charges may increase or decrease between the date of proposal and the shipment date.
B205: Customer Acceptance
B210: Signature | D210: Printed Name | G210: Date
B212: If you have any questions, please feel free to contact Bryan Shepherd at 720-457-5500 / Bryan@SummitSensory.com

Sheet Adventure Series Proposal (USA)
B1: Summit Sensory Gym | J1: PSF File Name | K1: =B10&" - "&VLOOKUP!F1&" - PSFv73 - "&TEXT(H9,"MMDDYYYY") -> Soar Autism Center - South Fort Collins - SQ-2MBL2T-10x10 - PSFv73 - 07222026
B2: 6150 S Geneva Court | J2: Proposal File Name | K2: =B10&" - "&VLOOKUP!F1&" - Proposal "&F9&" - "&TEXT(H9,"MMDDYYYY") -> Soar Autism Center - South Fort Collins - SQ-2MBL2T-10x10 - Proposal ADV-SS-260722-001 - 07222026
B3: Englewood, CO 80111
B4: Phone: 720-457-5500
B5: Fax: 720-242-8085
B6: Support@SummitSensory.com
B8: CUSTOMER INFO | F8: PROPOSAL | H8: DATE
B9: =Discovery!B2 -> Tyler Galiotto | F9: ="ADV-" & UPPER(LEFT(B10,1) & RIGHT(B10,1)) & "-" & TEXT(H9,"yymmdd") & "-" & TEXT( IF(AND(ISNUMBER(K11),K11>0), K11, COUNTIFS($B$10:B10,B10,$H$9:H9,H9) ), "000") -> ADV-SS-260722-001 | H9: =TODAY() -> 46225
B10: =Discovery!B3 -> Soar Autism Center - South Fort Collins | F10: PROJECT ID # | H10: VALID UNTIL
B11: =Discovery!B4 -> 3801 Automation Way | F11: ="SSG-"&Discovery!B13 -> SSG-12552093278 | H11: =H9+6 -> 46231 | J11: Proposal # Override | K11: 0
B12: =Discovery!B5&" "&Discovery!B6 -> Fort Collins, CO 80525 | F12: FREIGHT WEIGHT (lbs) | H12: =Calcs!I176+100 -> 1376.862
B13: =Discovery!B10 -> United States | J13: Freight Weight Conversion
J14: lbs | K14: =H12 -> 1376.862
B15: PROPOSAL DETAILS | J15: kgs | K15: =K14/2.205 -> 624.42721
B16: ="Summit Adventure Series "&VLOOKUP!D1&" - "&Discovery!B28&"Design & Fabrication of "&(VLOOKUP!F9)&"' X "&(VLOOKUP!F10)&"' Sensory Gym Structure"&IF(Calcs!F22>0," w Monkey Bars","")&IF(Calcs!F47>0," & Trolley System","") -> Summit Adventure Series SQ-2MBL2T - Design & Fabrication of 10' X 10' Sensory Gym Structure w Monkey Bars & Trolley System
B19: DESCRIPTION | D19: SKU | F19: QTY | G19: UNIT PRICE (USD) | H19: AMOUNT
B20: =VLOOKUP!F1&" - ITEMIZED" -> SQ-2MBL2T-10x10 - ITEMIZED | F20: TITL
B21: =IFERROR(VLOOKUP(D21,Calcs!B:G,3,FALSE),"") -> Vertical Tall <80 w/Gusset | D21: A-2245 | F21: =IFERROR(VLOOKUP(D21,Calcs!B:F,5,FALSE),"") -> 2 | G21: =IFERROR(VLOOKUP(D21,Calcs!B:M,11,FALSE),"") -> 557.75 | H21: =IFERROR(VLOOKUP(D21,Calcs!B:M,12,FALSE),"") -> 1115.5
B22: =IFERROR(VLOOKUP(D22,Calcs!B:G,3,FALSE),"") -> Vertical Tall <80 w/Gussets, Rungs & Handles | D22: A-2246 | F22: =IFERROR(VLOOKUP(D22,Calcs!B:F,5,FALSE),"") -> 2 | G22: =IFERROR(VLOOKUP(D22,Calcs!B:M,11,FALSE),"") -> 557.75 | H22: =IFERROR(VLOOKUP(D22,Calcs!B:M,12,FALSE),"") -> 1115.5
B23: =IFERROR(VLOOKUP(D23,Calcs!B:G,3,FALSE),"") | D23: A-2241 | F23: =IFERROR(VLOOKUP(D23,Calcs!B:F,5,FALSE),"") | G23: =IFERROR(VLOOKUP(D23,Calcs!B:M,11,FALSE),"") | H23: =IFERROR(VLOOKUP(D23,Calcs!B:M,12,FALSE),"")
B24: =IFERROR(VLOOKUP(D24,Calcs!B:G,3,FALSE),"") -> Corner Post <80 2-Way Weld Assembly | D24: A-2242 | F24: =IFERROR(VLOOKUP(D24,Calcs!B:F,5,FALSE),"") -> 4 | G24: =IFERROR(VLOOKUP(D24,Calcs!B:M,11,FALSE),"") -> 175.95 | H24: =IFERROR(VLOOKUP(D24,Calcs!B:M,12,FALSE),"") -> 703.8
B25: =IFERROR(VLOOKUP(D25,Calcs!B:G,3,FALSE),"") | D25: A-2243 | F25: =IFERROR(VLOOKUP(D25,Calcs!B:F,5,FALSE),"") | G25: =IFERROR(VLOOKUP(D25,Calcs!B:M,11,FALSE),"") | H25: =IFERROR(VLOOKUP(D25,Calcs!B:M,12,FALSE),"")
B26: =IFERROR(VLOOKUP(D26,Calcs!B:G,3,FALSE),"") | D26: A-2244 | F26: =IFERROR(VLOOKUP(D26,Calcs!B:F,5,FALSE),"") | G26: =IFERROR(VLOOKUP(D26,Calcs!B:M,11,FALSE),"") | H26: =IFERROR(VLOOKUP(D26,Calcs!B:M,12,FALSE),"")
B27: =IFERROR(VLOOKUP(D27,Calcs!B:G,3,FALSE),"") | D27: A-2022 | F27: =IFERROR(VLOOKUP(D27,Calcs!B:F,5,FALSE),"") | G27: =IFERROR(VLOOKUP(D27,Calcs!B:M,11,FALSE),"") | H27: =IFERROR(VLOOKUP(D27,Calcs!B:M,12,FALSE),"")
B28: =IFERROR(VLOOKUP(D28,Calcs!B:G,3,FALSE),"") -> Mid Span 1-Way Saddle Alt Weld Assembly | D28: A-2225 | F28: =IFERROR(VLOOKUP(D28,Calcs!B:F,5,FALSE),"") -> 4 | G28: =IFERROR(VLOOKUP(D28,Calcs!B:M,11,FALSE),"") -> 105.8 | H28: =IFERROR(VLOOKUP(D28,Calcs!B:M,12,FALSE),"") -> 423.2
B29: =IFERROR(VLOOKUP(D29,Calcs!B:G,3,FALSE),"") -> Ladder Leg Footless | D29: P-2531 | F29: =IFERROR(VLOOKUP(D29,Calcs!B:F,5,FALSE),"") -> 2 | G29: =IFERROR(VLOOKUP(D29,Calcs!B:M,11,FALSE),"") -> 224.25 | H29: =IFERROR(VLOOKUP(D29,Calcs!B:M,12,FALSE),"") -> 448.5
B30: =IFERROR(VLOOKUP(D30,Calcs!B:G,3,FALSE),"") -> Single Leg Inner Ladder Sleeve Footless Weld Assembly | D30: A-2253 | F30: =IFERROR(VLOOKUP(D30,Calcs!B:F,5,FALSE),"") -> 2 | G30: =IFERROR(VLOOKUP(D30,Calcs!B:M,11,FALSE),"") -> 150.65 | H30: =IFERROR(VLOOKUP(D30,Calcs!B:M,12,FALSE),"") -> 301.3
B31: =IFERROR(VLOOKUP(D31,Calcs!B:G,3,FALSE),"") | D31: A-2248 | F31: =IFERROR(VLOOKUP(D31,Calcs!B:F,5,FALSE),"") | G31: =IFERROR(VLOOKUP(D31,Calcs!B:M,11,FALSE),"") | H31: =IFERROR(VLOOKUP(D31,Calcs!B:M,12,FALSE),"")
B32: =IFERROR(VLOOKUP(D32,Calcs!B:G,3,FALSE),"") | D32: P-2545 | F32: =IFERROR(VLOOKUP(D32,Calcs!B:F,5,FALSE),"") | G32: =IFERROR(VLOOKUP(D32,Calcs!B:M,11,FALSE),"") | H32: =IFERROR(VLOOKUP(D32,Calcs!B:M,12,FALSE),"")
... B50: =IFERROR(VLOOKUP(D50,Calcs!B:G,3,FALSE),"") | D50: P-1032 | F50: =IFERROR(VLOOKUP(D50,Calcs!B:F,5,FALSE),"") | G50: =IFERROR(VLOOKUP(D50,Calcs!B:M,11,FALSE),"") | H50: =IFERROR(VLOOKUP(D50,Calcs!B:M,12,FALSE),"")
B51: =IF(VLOOKUP!E14="yES","Professional Design & Rendering Consulting","") | D51: DESIGN | F51: =IFERROR(VLOOKUP(D51,Calcs!B:F,5,FALSE),"") | G51: =IFERROR(VLOOKUP(D51,Calcs!B:M,11,FALSE),"") | H51: =IFERROR(VLOOKUP(D51,Calcs!B:M,12,FALSE),"")
B52: SUBTOTAL | F52: SUB | H52: =SUM(H21:H51) -> 8223.65
F53: HOLD
B54: DUAL TROLLEY SYSTEM (Optional) | F54: TITL
B55: Unquoted | F55: UQ-TR
B56: =IFERROR(VLOOKUP(D56,Calcs!B:G,3,FALSE),"") -> Trolley Bar | D56: P-2018 | F56: =IFERROR(VLOOKUP(D56,Calcs!B:F,5,FALSE),"") -> 1 | G56: =IFERROR(VLOOKUP(D56,Calcs!B:M,11,FALSE),"") -> 32.2 | H56: =IFERROR(VLOOKUP(D56,Calcs!B:Z,12,FALSE),"") -> 32.2
B57: =IFERROR(VLOOKUP(D57,Calcs!B:G,3,FALSE),"") -> Trolley Bar Plate | D57: P-2025 | F57: =IFERROR(VLOOKUP(D57,Calcs!B:F,5,FALSE),"") -> 2 | G57: =IFERROR(VLOOKUP(D57,Calcs!B:M,11,FALSE),"") -> 27.6 | H57: =IFERROR(VLOOKUP(D57,Calcs!B:Z,12,FALSE),"") -> 55.2
B58: =IFERROR(VLOOKUP(D58,Calcs!B:G,3,FALSE),"") | D58: SSG-TR-A10 | F58: =IFERROR(VLOOKUP(D58,Calcs!B:F,5,FALSE),"") | G58: =IFERROR(VLOOKUP(D58,Calcs!B:M,11,FALSE),"") | H58: =IFERROR(VLOOKUP(D58,Calcs!B:Z,12,FALSE),"")
B59: =IFERROR(VLOOKUP(D59,Calcs!B:G,3,FALSE),"") -> 9' Aluminum Enclosed Rail 550lbs. Max Weight | D59: SSG-TR-A09 | F59: =IFERROR(VLOOKUP(D59,Calcs!B:F,5,FALSE),"") -> 2 | G59: =IFERROR(VLOOKUP(D59,Calcs!B:M,11,FALSE),"") -> 445.05 | H59: =IFERROR(VLOOKUP(D59,Calcs!B:Z,12,FALSE),"") -> 890.1
B60: =IFERROR(VLOOKUP(D60,Calcs!B:G,3,FALSE),"") | D60: SSG-TR-A08 | F60: =IFERROR(VLOOKUP(D60,Calcs!B:F,5,FALSE),"") | G60: =IFERROR(VLOOKUP(D60,Calcs!B:M,11,FALSE),"") | H60: =IFERROR(VLOOKUP(D60,Calcs!B:Z,12,FALSE),"")
B61: =IFERROR(VLOOKUP(D61,Calcs!B:G,3,FALSE),"") | D61: SSG-TR-A07 | F61: =IFERROR(VLOOKUP(D61,Calcs!B:F,5,FALSE),"") | G61: =IFERROR(VLOOKUP(D61,Calcs!B:M,11,FALSE),"") | H61: =IFERROR(VLOOKUP(D61,Calcs!B:Z,12,FALSE),"")
B62: =IFERROR(VLOOKUP(D62,Calcs!B:G,3,FALSE),"") -> Universal Threaded Rod Hanger | D62: SSG-TRH | F62: =IFERROR(VLOOKUP(D62,Calcs!B:F,5,FALSE),"") -> 6 | G62: =IFERROR(VLOOKUP(D62,Calcs!B:M,11,FALSE),"") -> 259.9 | H62: =IFERROR(VLOOKUP(D62,Calcs!B:Z,12,FALSE),"") -> 1559.4
B63: =IFERROR(VLOOKUP(D63,Calcs!B:G,3,FALSE),"") -> End Cap for Rail | D63: SSG-TRN | F63: =IFERROR(VLOOKUP(D63,Calcs!B:F,5,FALSE),"") -> 4 | G63: =IFERROR(VLOOKUP(D63,Calcs!B:M,11,FALSE),"") -> 131.1 | H63: =IFERROR(VLOOKUP(D63,Calcs!B:Z,12,FALSE),"") -> 524.4
B64: =IFERROR(VLOOKUP(D64,Calcs!B:G,3,FALSE),"") -> Trolley for Rail | D64: SSG-TRT | F64: =IFERROR(VLOOKUP(D64,Calcs!B:F,5,FALSE),"") -> 2 | G64: =IFERROR(VLOOKUP(D64,Calcs!B:M,11,FALSE),"") -> 243.8 | H64: =IFERROR(VLOOKUP(D64,Calcs!B:Z,12,FALSE),"") -> 487.6
B65: SUBTOTAL | F65: SUB | H65: =SUM(H56:H64) -> 3548.9
F66: HOLD
B67: THERAPEUTIC ACTIVITY & ADVENTURE COMPONENTS (Optional) | F67: TITL
B68: Unquoted | F68: UQ-OP
B69: Summit Adventure Slide System | F69: =IF(SUM(F70:F73)>=1,1,"")
B70: =IFERROR(VLOOKUP(D70,Calcs!B:G,3,FALSE),"") | C70: * | D70: A-2216 | E70: *Popular Addition | F70: =IFERROR(VLOOKUP(D70,Calcs!B:F,5,FALSE),"") | G70: =IFERROR(VLOOKUP(D70,Calcs!B:M,11,FALSE),"") | H70: =IFERROR(VLOOKUP(D70,Calcs!B:N,12,FALSE),"")
B71: =IFERROR(VLOOKUP(D71,Calcs!B:G,3,FALSE),"") | D71: WS8203 | E71: *Passthrough Cost | F71: =IFERROR(VLOOKUP(D71,Calcs!B:F,5,FALSE),0) -> 0 | G71: =IFERROR(VLOOKUP(D71,Calcs!B:M,11,FALSE),"") | H71: =IFERROR(VLOOKUP(D71,Calcs!B:N,12,FALSE),"")
B72: =IF(F68>0.99,"Passthrough Freight Charge (Required)",0) -> Passthrough Freight Charge (Required) | D72: 3RD-FREIGHT-SLIDE | E72: *Passthrough Cost | F72: =IF(F71>=1,1,0) -> 0 | H72: =IF(F72=1,"TBD","")
B73: =IFERROR(VLOOKUP(D73,Calcs!B:G,3,FALSE),"") | D73: 150045 | F73: =IFERROR(VLOOKUP(D73,Calcs!B:F,5,FALSE),0) -> 0 | G73: =IFERROR(VLOOKUP(D73,Calcs!B:M,11,FALSE),"") | H73: =IFERROR(VLOOKUP(D73,Calcs!B:N,12,FALSE),"")
B74: =IF(F70>0.99,"Passthrough Freight Charge (Required)",0) -> Passthrough Freight Charge (Required) | D74: 3RD-FREIGHT | E74: *Passthrough Cost | F74: =IF(F73>=1,1,0) -> 0 | H74: =IF(F74=1,"TBD","")
B75: =IFERROR(VLOOKUP(D75,Calcs!B:G,3,FALSE),"") | D75: A-2349 | F75: =IFERROR(VLOOKUP(D75,Calcs!B:F,5,FALSE),0) -> 0 | G75: =IFERROR(VLOOKUP(D75,Calcs!B:M,11,FALSE),"") | H75: =IFERROR(VLOOKUP(D75,Calcs!B:N,12,FALSE),"")
B77: Climbing Wall & Safety Accessories | F77: =IF(SUM(F78:F80)>=1,1,"") -> 1
B78: =IFERROR(VLOOKUP(D78,Calcs!B:G,3,FALSE),"") | C78: * | D78: SSG-SA-CFM | E78: *Popular Addition | F78: =IFERROR(VLOOKUP(D78,Calcs!B:F,5,FALSE),"") | G78: =IFERROR(VLOOKUP(D78,Calcs!B:M,11,FALSE),"") | H78: =IFERROR(VLOOKUP(D78,Calcs!B:N,12,FALSE),"")
B79: =IFERROR(VLOOKUP(D79,Calcs!B:G,3,FALSE),"") | D79: P-2500 | F79: =IFERROR(VLOOKUP(D79,Calcs!B:F,5,FALSE),"") | G79: =IFERROR(VLOOKUP(D79,Calcs!B:M,11,FALSE),"") | H79: =IFERROR(VLOOKUP(D79,Calcs!B:N,12,FALSE),"")
B80: =IFERROR(VLOOKUP(D80,Calcs!B:G,3,FALSE),"") -> Adventure Climbing Wall - Wall Mounted-Metal Studs (Includes Climbing Holds) | D80: SSG-SA-CWM | E80: *Popular Addition | F80: =IFERROR(VLOOKUP(D80,Calcs!B:F,5,FALSE),"") -> 1 | G80: =IFERROR(VLOOKUP(D80,Calcs!B:M,11,FALSE),"") -> 2442.6 | H80: =IFERROR(VLOOKUP(D80,Calcs!B:N,12,FALSE),"") -> 2442.6
B81: Ladder - Safety Accessories | F81: =IF(SUM(F82)>=1,1,"")
B82: =IFERROR(VLOOKUP(D82,Calcs!B:G,3,FALSE),"") | D82: P-2502 | F82: =IFERROR(VLOOKUP(D82,Calcs!B:F,5,FALSE),"") | G82: =IFERROR(VLOOKUP(D82,Calcs!B:M,11,FALSE),"") | H82: =IFERROR(VLOOKUP(D82,Calcs!B:N,12,FALSE),"")
B83: =IFERROR(VLOOKUP(D83,Calcs!B:G,3,FALSE),"") | D83: K-5000 | F83: =IFERROR(VLOOKUP(D83,Calcs!B:F,5,FALSE),"") | G83: =IFERROR(VLOOKUP(D83,Calcs!B:M,11,FALSE),"") | H83: =IFERROR(VLOOKUP(D83,Calcs!B:N,12,FALSE),"")
B84: =IFERROR(VLOOKUP(D84,Calcs!B:G,3,FALSE),"") | D84: T11412 | F84: =IFERROR(VLOOKUP(D84,Calcs!B:F,5,FALSE),"") | G84: =IFERROR(VLOOKUP(D84,Calcs!B:M,11,FALSE),"") | H84: =IFERROR(VLOOKUP(D84,Calcs!B:N,12,FALSE),"")
B85: =IF(B84="adjustable Indoor Climbing Wall","Adjustable Indoor Climbing Wall - Freight Charge","") | D85: T11412-FREIGHT | F85: =IF(F84=1,1,"") | G85: =IFERROR(VLOOKUP(D85,Calcs!B:M,11,FALSE),"") | H85: =IFERROR(VLOOKUP(D85,Calcs!B:N,12,FALSE),"")
B86: Therapeutic Swing & Sensory Equipment Package | F86: =IF(SUM(F87:F117)>=1,1,"")
B87: =IFERROR(VLOOKUP(D87,Calcs!B:G,3,FALSE),"") | C87: * | D87: B07V3J9S2R | E87: *Popular Addition | F87: =IFERROR(VLOOKUP(D87,Calcs!B:F,5,FALSE),"") | G87: =IFERROR(VLOOKUP(D87,Calcs!B:M,11,FALSE),"") | H87: =IFERROR(VLOOKUP(D87,Calcs!B:N,12,FALSE),"")
B88: =IFERROR(VLOOKUP(D88,Calcs!B:G,3,FALSE),"") | D88: B07TSDMPNQ | E88: *Popular Addition | F88: =IFERROR(VLOOKUP(D88,Calcs!B:F,5,FALSE),"") | G88: =IFERROR(VLOOKUP(D88,Calcs!B:M,11,FALSE),"") | H88: =IFERROR(VLOOKUP(D88,Calcs!B:N,12,FALSE),"")
B89: =IFERROR(VLOOKUP(D89,Calcs!B:G,3,FALSE),"") | C89: * | D89: B0BGDQF46S | F89: =IFERROR(VLOOKUP(D89,Calcs!B:F,5,FALSE),"") | G89: =IFERROR(VLOOKUP(D89,Calcs!B:M,11,FALSE),"") | H89: =IFERROR(VLOOKUP(D89,Calcs!B:N,12,FALSE),"")
B90: =IFERROR(VLOOKUP(D90,Calcs!B:G,3,FALSE),"") | C90: * | D90: B0193YG8GI | F90: =IFERROR(VLOOKUP(D90,Calcs!B:F,5,FALSE),"") | G90: =IFERROR(VLOOKUP(D90,Calcs!B:M,11,FALSE),"") | H90: =IFERROR(VLOOKUP(D90,Calcs!B:N,12,FALSE),"")
B91: =IFERROR(VLOOKUP(D91,Calcs!B:G,3,FALSE),"") | C91: * | D91: B07MC3144W | F91: =IFERROR(VLOOKUP(D91,Calcs!B:F,5,FALSE),"") | G91: =IFERROR(VLOOKUP(D91,Calcs!B:M,11,FALSE),"") | H91: =IFERROR(VLOOKUP(D91,Calcs!B:N,12,FALSE),"")
B92: =IFERROR(VLOOKUP(D92,Calcs!B:G,3,FALSE),"") | C92: * | D92: B07PQHSZPR | F92: =IFERROR(VLOOKUP(D92,Calcs!B:F,5,FALSE),"") | G92: =IFERROR(VLOOKUP(D92,Calcs!B:M,11,FALSE),"") | H92: =IFERROR(VLOOKUP(D92,Calcs!B:N,12,FALSE),"")
B93: =IFERROR(VLOOKUP(D93,Calcs!B:G,3,FALSE),"") | C93: * | D93: B07ZQZD6WX | F93: =IFERROR(VLOOKUP(D93,Calcs!B:F,5,FALSE),"") | G93: =IFERROR(VLOOKUP(D93,Calcs!B:M,11,FALSE),"") | H93: =IFERROR(VLOOKUP(D93,Calcs!B:N,12,FALSE),"")
B94: =IFERROR(VLOOKUP(D94,Calcs!B:G,3,FALSE),"") | C94: * | D94: B08DTP539F | F94: =IFERROR(VLOOKUP(D94,Calcs!B:F,5,FALSE),"") | G94: =IFERROR(VLOOKUP(D94,Calcs!B:M,11,FALSE),"") | H94: =IFERROR(VLOOKUP(D94,Calcs!B:N,12,FALSE),"")
B95: =IFERROR(VLOOKUP(D95,Calcs!B:G,3,FALSE),"") | C95: * | D95: B01C3I4SL8 | E95: *Popular Addition | F95: =IFERROR(VLOOKUP(D95,Calcs!B:F,5,FALSE),"") | G95: =IFERROR(VLOOKUP(D95,Calcs!B:M,11,FALSE),"") | H95: =IFERROR(VLOOKUP(D95,Calcs!B:N,12,FALSE),"")
B96: =IFERROR(VLOOKUP(D96,Calcs!B:G,3,FALSE),"") | D96: SFCS48 | E96: *Climbing Safety | F96: =IFERROR(VLOOKUP(D96,Calcs!B:F,5,FALSE),"") | G96: =IFERROR(VLOOKUP(D96,Calcs!B:M,11,FALSE),"") | H96: =IFERROR(VLOOKUP(D96,Calcs!B:N,12,FALSE),"")
D97: SP150 | E97: *Popular Addition | F97: =IFERROR(VLOOKUP(D97,Calcs!B:F,5,FALSE),"") | G97: =IFERROR(VLOOKUP(D97,Calcs!B:M,11,FALSE),"") | H97: =IFERROR(VLOOKUP(D97,Calcs!B:N,12,FALSE),"")
D98: SP5000 | E98: *Popular Addition | F98: =IFERROR(VLOOKUP(D98,Calcs!B:F,5,FALSE),"") | G98: =IFERROR(VLOOKUP(D98,Calcs!B:M,11,FALSE),"") | H98: =IFERROR(VLOOKUP(D98,Calcs!B:N,12,FALSE),"")
D99: B07918TH4Q | E99: *Popular Addition | F99: =IFERROR(VLOOKUP(D99,Calcs!B:F,5,FALSE),"") | G99: =IFERROR(VLOOKUP(D99,Calcs!B:M,11,FALSE),"") | H99: =IFERROR(VLOOKUP(D99,Calcs!B:N,12,FALSE),"")
B100: =IFERROR(VLOOKUP(D100,Calcs!B:G,3,FALSE),"") | C100: * | D100: 120040 | F100: =IFERROR(VLOOKUP(D100,Calcs!B:F,5,FALSE),0) -> 0 | G100: =IFERROR(VLOOKUP(D100,Calcs!B:M,11,FALSE),"") | H100: =IFERROR(VLOOKUP(D100,Calcs!B:N,12,FALSE),"")
B101: =IF(F100>0.99,"Passthrough Freight Charge (Required)","") | D101: 3RD-FREIGHT | F101: =IF(F100>=1,1,0) -> 0 | H101: =IF(F101=1,"TBD","")
B102: =IFERROR(VLOOKUP(D102,Calcs!B:G,3,FALSE),"") | C102: * | D102: 120050 | E102: *Popular Addition | F102: =IFERROR(VLOOKUP(D102,Calcs!B:F,5,FALSE),0) -> 0 | G102: =IFERROR(VLOOKUP(D102,Calcs!B:M,11,FALSE),"") | H102: =IFERROR(VLOOKUP(D102,Calcs!B:N,12,FALSE),"")
B103: =IF(F102>0.99,"Passthrough Freight Charge (Required)","") | D103: 3RD-FREIGHT | F103: =IF(F102>=1,1,0) -> 0 | H103: =IF(F103=1,"TBD","")
B104: =IFERROR(VLOOKUP(D104,Calcs!B:G,3,FALSE),"") | D104: 120077 | F104: =IFERROR(VLOOKUP(D104,Calcs!B:F,5,FALSE),0) -> 0 | G104: =IFERROR(VLOOKUP(D104,Calcs!B:M,11,FALSE),"") | H104: =IFERROR(VLOOKUP(D104,Calcs!B:N,12,FALSE),"")
B105: =IF(F104>0.99,"Passthrough Freight Charge (Required)","") | D105: 3RD-FREIGHT | F105: =IF(F104>=1,1,0) -> 0 | H105: =IF(F105=1,"TBD","")
B106: =IFERROR(VLOOKUP(D106,Calcs!B:G,3,FALSE),"") | D106: 1909 | F106: =IFERROR(VLOOKUP(D106,Calcs!B:F,5,FALSE),0) -> 0 | G106: =IFERROR(VLOOKUP(D106,Calcs!B:M,11,FALSE),"") | H106: =IFERROR(VLOOKUP(D106,Calcs!B:N,12,FALSE),"")
B107: =IF(F106>0.99,"Passthrough Freight Charge (Required)","") | D107: 3RD-FREIGHT | F107: =IF(F106>=1,1,0) -> 0 | H107: =IF(F107=1,"TBD","")
B108: =IFERROR(VLOOKUP(D108,Calcs!B:G,3,FALSE),"") | D108: B0894XNGJP | F108: =IFERROR(VLOOKUP(D108,Calcs!B:F,5,FALSE),"") | G108: =IFERROR(VLOOKUP(D108,Calcs!B:M,11,FALSE),"") | H108: =IFERROR(VLOOKUP(D108,Calcs!B:N,12,FALSE),"")
B109: =IFERROR(VLOOKUP(D109,Calcs!B:G,3,FALSE),"") | D109: B092QYLLL2 | E109: *Popular Addition | F109: =IFERROR(VLOOKUP(D109,Calcs!B:F,5,FALSE),"") | G109: =IFERROR(VLOOKUP(D109,Calcs!B:M,11,FALSE),"") | H109: =IFERROR(VLOOKUP(D109,Calcs!B:N,12,FALSE),"")
B110: =IFERROR(VLOOKUP(D110,Calcs!B:G,3,FALSE),"") | D110: 815DBLESTK | E110: *Extremely Strong | F110: =IFERROR(VLOOKUP(D110,Calcs!B:F,5,FALSE),"") | G110: =IFERROR(VLOOKUP(D110,Calcs!B:M,11,FALSE),"") | H110: =IFERROR(VLOOKUP(D110,Calcs!B:N,12,FALSE),"")
B111: =IFERROR(VLOOKUP(D111,Calcs!B:G,3,FALSE),"") | D111: 382-408_x000D_ | F111: =IFERROR(VLOOKUP(D111,Calcs!B:F,5,FALSE),"") | G111: =IFERROR(VLOOKUP(D111,Calcs!B:M,11,FALSE),"") | H111: =IFERROR(VLOOKUP(D111,Calcs!B:N,12,FALSE),"")
B112: =IFERROR(VLOOKUP(D112,Calcs!B:G,3,FALSE),"") | D112: XL-PLAT | F112: =IFERROR(VLOOKUP(D112,Calcs!B:F,5,FALSE),"") | G112: =IFERROR(VLOOKUP(D112,Calcs!B:M,11,FALSE),"") | H112: =IFERROR(VLOOKUP(D112,Calcs!B:N,12,FALSE),"")
B113: =IFERROR(VLOOKUP(D113,Calcs!B:G,3,FALSE),"") | D113: B07Z79ZCZX | E113: *Popular Addition | F113: =IFERROR(VLOOKUP(D113,Calcs!B:F,5,FALSE),"") | G113: =IFERROR(VLOOKUP(D113,Calcs!B:M,11,FALSE),"") | H113: =IFERROR(VLOOKUP(D113,Calcs!B:N,12,FALSE),"")
B114: =IFERROR(VLOOKUP(D114,Calcs!B:G,3,FALSE),"") | D114: 48RACK | E114: *Popular Addition | F114: =IFERROR(VLOOKUP(D114,Calcs!B:F,5,FALSE),"") | G114: =IFERROR(VLOOKUP(D114,Calcs!B:M,11,FALSE),"") | H114: =IFERROR(VLOOKUP(D114,Calcs!B:N,12,FALSE),"")
B115: =IFERROR(VLOOKUP(D115,Calcs!B:G,3,FALSE),"") | D115: 382-411 | F115: =IFERROR(VLOOKUP(D115,Calcs!B:F,5,FALSE),"") | G115: =IFERROR(VLOOKUP(D115,Calcs!B:M,11,FALSE),"") | H115: =IFERROR(VLOOKUP(D115,Calcs!B:N,12,FALSE),"")
B116: =IFERROR(VLOOKUP(D116,Calcs!B:G,3,FALSE),"") | D116: B09XV985JJ | F116: =IFERROR(VLOOKUP(D116,Calcs!B:F,5,FALSE),"") | G116: =IFERROR(VLOOKUP(D116,Calcs!B:M,11,FALSE),"") | H116: =IFERROR(VLOOKUP(D116,Calcs!B:N,12,FALSE),"")
D117: B0C4YB8D64
B118: Essential Carabiners & Connectors | F118: =IF(SUM(F119:F122)>=1,1,"") -> 1
B119: =IFERROR(VLOOKUP(D119,Calcs!B:G,3,FALSE),"") -> Auto Locking Carabiner Clips - 28KN (6172lbs) Heavy Duty Carabiner (4 Pack) | D119: B0CDVDZSB1 | E119: *Popular Addition | F119: =IFERROR(VLOOKUP(D119,Calcs!B:F,5,FALSE),0) -> 2 | G119: =IFERROR(VLOOKUP(D119,Calcs!B:M,11,FALSE),"") -> 52.88 | H119: =IFERROR(VLOOKUP(D119,Calcs!B:N,12,FALSE),"") -> 105.76
B120: =IFERROR(VLOOKUP(D120,Calcs!B:G,3,FALSE),"") | D120: B0937DRYYF | E120: *Popular Addition | F120: =IFERROR(VLOOKUP(D120,Calcs!B:F,5,FALSE),"") | G120: =IFERROR(VLOOKUP(D120,Calcs!B:M,11,FALSE),"") | H120: =IFERROR(VLOOKUP(D120,Calcs!B:N,12,FALSE),"")
B121: =IFERROR(VLOOKUP(D121,Calcs!B:G,3,FALSE),"") | D121: B07MB985GW | E121: *Popular Addition | F121: =IFERROR(VLOOKUP(D121,Calcs!B:F,5,FALSE),"") | G121: =IFERROR(VLOOKUP(D121,Calcs!B:M,11,FALSE),"") | H121: =IFERROR(VLOOKUP(D121,Calcs!B:N,12,FALSE),"")
...

Sheet LOAN CALC - INCLUDE
L1: PREFERRED LEASE RATES | U1: File Name: | V1: =A9&" - Financing Options - Amount $"&TRUNC(A17)&" - "&TEXT(E7,"MMDDYYYY") -> Soar Autism Center - South Fort Collins - Financing Options - Amount $18229 - 07222026
L2: EQUIPMENT | N2: MONTHLY TERM
N3: 12 | O3: 24 | P3: 36 | Q3: 48 | R3: 60
L4: 3000 | M4: 4999 | N4: 0 | O4: 0.05622 | P4: 0.04088 | Q4: 0.03334 | R4: 0
L5: 5000 | M5: 9999 | N5: 0.0959 | O5: 0.05016 | P5: 0.03514 | Q5: 0.02769 | R5: 0.02324
L6: 10000 | M6: 14999 | N6: 0.09156 | O6: 0.04753 | P6: 0.03301 | Q6: 0.02577 | R6: 0.02144
A7: Customer Information | D7: Date Presented | E7: =TODAY() -> 46225 | L7: 15000 | M7: 24999 | N7: 0.0907 | O7: 0.04708 | P7: 0.0327 | Q7: 0.02553 | R7: 0.02124
A8: =ZAPIER!C5 -> Tyler Galiotto | L8: 25000 | M8: 34999 | N8: 0.08984 | O8: 0.04663 | P8: 0.03239 | Q8: 0.02528 | R8: 0.02104
A9: =ZAPIER!D5 -> Soar Autism Center - South Fort Collins | D9: Questions? Contact | L9: 35000 | M9: 49999 | N9: 0.08932 | O9: 0.04641 | P9: 0.03223 | Q9: 0.02516 | R9: 0.02094
A10: =ZAPIER!E5 -> 3801 Automation Way | D10: Chandler Kinsey | L10: 50000 | M10: 74999 | N10: 0.08889 | O10: 0.04608 | P10: 0.03197 | Q10: 0.02494 | R10: 0.02073
A11: =ZAPIER!G5&", "&ZAPIER!H5&" "&ZAPIER!I5 -> CO, 80525 United States | D11: 800-541-6370 | L11: 75000 | M11: 99999 | N11: 0.08846 | O11: 0.04586 | P11: 0.03182 | Q11: 0.02482 | R11: 0.02063
A12: =ZAPIER!K5 | D12: ckinsey@ryancapital.com | L12: 100000 | M12: 199999 | N12: 0.08802 | O12: 0.04563 | P12: 0.03166 | Q12: 0.02469 | R12: 0.02053
A13: =ZAPIER!#REF! -> #REF!
A16: Estimated Loan Amount | C16: Term (Months) | D16: 12 | E16: 24 | F16: 36 | G16: 48 | H16: 60
A17: ='Adventure Series Proposal (USA)'!H238 -> 18229.05 | C17: Monthly Payment | D17: {=_xlfn.IFS($A$17<$L$4,"",$A$17<$L$5,$A$17*N4,$A$17<$L$6,$A$17*N5,$A$17<$L$7,$A$17*N6,$A$17<$L$8,$A$17*N7,$A$17<$L$9,$A$17*N8,$A$17<$L$10,$A$17*N9,$A$17>$M$9,"OVER",TRUE,"")} -> 1653.3748 | E17: {=_xlfn.IFS($A$17<$L$4,"",$A$17<$L$5,$A$17*O4,$A$17<$L$6,$A$17*O5,$A$17<$L$7,$A$17*O6,$A$17<$L$8,$A$17*O7,$A$17<$L$9,$A$17*O8,$A$17<$L$10,$A$17*O9,$A$17>$M$9,"OVER",TRUE,"")} -> 858.22367 | F17: {=_xlfn.IFS($A$17<$L$4,"",$A$17<$L$5,$A$17*P4,$A$17<$L$6,$A$17*P5,$A$17<$L$7,$A$17*P6,$A$17<$L$8,$A$17*P7,$A$17<$L$9,$A$17*P8,$A$17<$L$10,$A$17*P9,$A$17>$M$9,"OVER",TRUE,"")} -> 596.08993 | G17: {=_xlfn.IFS($A$17<$L$4,"",$A$17<$L$5,$A$17*Q4,$A$17<$L$6,$A$17*Q5,$A$17<$L$7,$A$17*Q6,$A$17<$L$8,$A$17*Q7,$A$17<$L$9,$A$17*Q8,$A$17<$L$10,$A$17*Q9,$A$17>$M$9,"OVER",TRUE,"")} -> 465.38765 | H17: {=_xlfn.IFS($A$17<$L$4,"",$A$17<$L$5,$A$17*R4,$A$17<$L$6,$A$17*R5,$A$17<$L$7,$A$17*R6,$A$17<$L$8,$A$17*R7,$A$17<$L$9,$A$17*R8,$A$17<$L$10,$A$17*R9,$A$17>$M$9,"OVER",TRUE,"")} -> 387.18502
C19: First & Last Payment in Advance
C20: (Payments are Subject to Credit Approval)
A22: Tax Benefits
A25: Section 179 Business Deduction:
A26: Businesses may immediately expense the cost of any Section 179 property and deduct the expense in the year the property is placed into service. The new maximum deduction is 1 million.
A28: Tax Benefit for this Investment:
A29: Cost of Equipment | D29: =A17 -> 18229.05
A30: Section 179 Deduction | D30: =D29 -> 18229.05
A31: 50% Bonus Depreciation | D31: 0
A32: Regular First Year Depreciation Deduction | D32: 0
A33: Total First Year Deduction | D33: =D30 -> 18229.05
A35: Cash Savings on Your Equipment Purchase | D35: =D33*0.21 -> 3828.1005
A36: % Savings on Your Equipment Purchase | D36: =D35/D33 -> 0.21
A38: Net Cost of Equipment After Tax Deductions | D38: =D33-D35 -> 14400.949
A40: What Does Net Cost of Equipment After Tax Deductions Mean?
A41: This represents the actual cost of the equipment once the value of tax deductions/credits is applied. In other words, it’s the net cost to your organization after factoring in tax savings—making it a more accurate reflection of the investment.

Sheet Adventure Series Proposal (CAN)
B1: Summit Sensory Gym | J1: PSF File Name | K1: =B10&" - "&VLOOKUP!F1&" - PSFv73 - "&TEXT(H9,"MMDDYYYY") -> Soar Autism Center - South Fort Collins - SQ-2MBL2T-10x10 - PSFv73 - 07222026
B2: 6150 S Geneva Court | J2: Proposal File Name | K2: =B10&" - "&VLOOKUP!F1&" - Proposal "&F9&" - "&TEXT(H9,"MMDDYYYY") -> Soar Autism Center - South Fort Collins - SQ-2MBL2T-10x10 - Proposal ADV-SS-260722-001 - 07222026
B3: Englewood, CO 80111
B4: Phone: 720-457-5500
B5: Fax: 720-242-8085
B6: Support@SummitSensory.com
B8: CUSTOMER INFO | F8: PROPOSAL | H8: DATE
B9: =Discovery!B2 -> Tyler Galiotto | F9: ="ADV-" & UPPER(LEFT(B10,1) & RIGHT(B10,1)) & "-" & TEXT(H9,"yymmdd") & "-" & TEXT( IF(AND(ISNUMBER(K11),K11>0), K11, COUNTIFS($B$10:B10,B10,$H$9:H9,H9) ), "000") -> ADV-SS-260722-001 | H9: =TODAY() -> 46225
B10: =Discovery!B3 -> Soar Autism Center - South Fort Collins | F10: PROJECT ID # | H10: VALID UNTIL
B11: =Discovery!B4 -> 3801 Automation Way | F11: ="SSG-"&Discovery!B13 -> SSG-12552093278 | H11: =H9+6 -> 46231 | J11: Proposal # Override | K11: 0
B12: =Discovery!B5&" "&Discovery!B6 -> Fort Collins, CO 80525 | F12: FREIGHT WEIGHT (lbs) | H12: =Calcs!I176+100 -> 1376.862
B13: =Discovery!B10 -> United States | J13: Freight Weight Conversion
J14: lbs | K14: =H12 -> 1376.862
B15: PROPOSAL DETAILS | J15: kgs | K15: =K14/2.205 -> 624.42721
B16: ="Summit Adventure Series "&VLOOKUP!D1&" - "&Discovery!B28&"Design & Fabrication of "&(VLOOKUP!F9)&"' X "&(VLOOKUP!F10)&"' Sensory Gym Structure"&IF(Calcs!F22>0," w Monkey Bars","")&IF(Calcs!F47>0," & Trolley System","") -> Summit Adventure Series SQ-2MBL2T - Design & Fabrication of 10' X 10' Sensory Gym Structure w Monkey Bars & Trolley System
B19: DESCRIPTION | D19: SKU | F19: QTY | G19: UNIT PRICE (USD) | H19: AMOUNT
B20: =VLOOKUP!F1&" - ITEMIZED" -> SQ-2MBL2T-10x10 - ITEMIZED | F20: TITL
B21: =IFERROR(VLOOKUP(D21,Calcs!B:G,3,FALSE),"") -> Vertical Tall <80 w/Gusset | D21: A-2245 | F21: =IFERROR(VLOOKUP(D21,Calcs!B:F,5,FALSE),"") -> 2 | G21: =IFERROR(VLOOKUP(D21,Calcs!B:M,11,FALSE),"") -> 557.75 | H21: =IFERROR(VLOOKUP(D21,Calcs!B:M,12,FALSE),"") -> 1115.5
B22: =IFERROR(VLOOKUP(D22,Calcs!B:G,3,FALSE),"") -> Vertical Tall <80 w/Gussets, Rungs & Handles | D22: A-2246 | F22: =IFERROR(VLOOKUP(D22,Calcs!B:F,5,FALSE),"") -> 2 | G22: =IFERROR(VLOOKUP(D22,Calcs!B:M,11,FALSE),"") -> 557.75 | H22: =IFERROR(VLOOKUP(D22,Calcs!B:M,12,FALSE),"") -> 1115.5
B23: =IFERROR(VLOOKUP(D23,Calcs!B:G,3,FALSE),"") | D23: A-2241 | F23: =IFERROR(VLOOKUP(D23,Calcs!B:F,5,FALSE),"") | G23: =IFERROR(VLOOKUP(D23,Calcs!B:M,11,FALSE),"") | H23: =IFERROR(VLOOKUP(D23,Calcs!B:M,12,FALSE),"")
B24: =IFERROR(VLOOKUP(D24,Calcs!B:G,3,FALSE),"") -> Corner Post <80 2-Way Weld Assembly | D24: A-2242 | F24: =IFERROR(VLOOKUP(D24,Calcs!B:F,5,FALSE),"") -> 4 | G24: =IFERROR(VLOOKUP(D24,Calcs!B:M,11,FALSE),"") -> 175.95 | H24: =IFERROR(VLOOKUP(D24,Calcs!B:M,12,FALSE),"") -> 703.8
B25: =IFERROR(VLOOKUP(D25,Calcs!B:G,3,FALSE),"") | D25: A-2243 | F25: =IFERROR(VLOOKUP(D25,Calcs!B:F,5,FALSE),"") | G25: =IFERROR(VLOOKUP(D25,Calcs!B:M,11,FALSE),"") | H25: =IFERROR(VLOOKUP(D25,Calcs!B:M,12,FALSE),"")
B26: =IFERROR(VLOOKUP(D26,Calcs!B:G,3,FALSE),"") | D26: A-2244 | F26: =IFERROR(VLOOKUP(D26,Calcs!B:F,5,FALSE),"") | G26: =IFERROR(VLOOKUP(D26,Calcs!B:M,11,FALSE),"") | H26: =IFERROR(VLOOKUP(D26,Calcs!B:M,12,FALSE),"")
B27: =IFERROR(VLOOKUP(D27,Calcs!B:G,3,FALSE),"") | D27: A-2022 | F27: =IFERROR(VLOOKUP(D27,Calcs!B:F,5,FALSE),"") | G27: =IFERROR(VLOOKUP(D27,Calcs!B:M,11,FALSE),"") | H27: =IFERROR(VLOOKUP(D27,Calcs!B:M,12,FALSE),"")
B28: =IFERROR(VLOOKUP(D28,Calcs!B:G,3,FALSE),"") -> Mid Span 1-Way Saddle Alt Weld Assembly | D28: A-2225 | F28: =IFERROR(VLOOKUP(D28,Calcs!B:F,5,FALSE),"") -> 4 | G28: =IFERROR(VLOOKUP(D28,Calcs!B:M,11,FALSE),"") -> 105.8 | H28: =IFERROR(VLOOKUP(D28,Calcs!B:M,12,FALSE),"") -> 423.2
B29: =IFERROR(VLOOKUP(D29,Calcs!B:G,3,FALSE),"") -> Ladder Leg Footless | D29: P-2531 | F29: =IFERROR(VLOOKUP(D29,Calcs!B:F,5,FALSE),"") -> 2 | G29: =IFERROR(VLOOKUP(D29,Calcs!B:M,11,FALSE),"") -> 224.25 | H29: =IFERROR(VLOOKUP(D29,Calcs!B:M,12,FALSE),"") -> 448.5
B30: =IFERROR(VLOOKUP(D30,Calcs!B:G,3,FALSE),"") -> Single Leg Inner Ladder Sleeve Footless Weld Assembly | D30: A-2253 | F30: =IFERROR(VLOOKUP(D30,Calcs!B:F,5,FALSE),"") -> 2 | G30: =IFERROR(VLOOKUP(D30,Calcs!B:M,11,FALSE),"") -> 150.65 | H30: =IFERROR(VLOOKUP(D30,Calcs!B:M,12,FALSE),"") -> 301.3
B31: =IFERROR(VLOOKUP(D31,Calcs!B:G,3,FALSE),"") | D31: A-2248 | F31: =IFERROR(VLOOKUP(D31,Calcs!B:F,5,FALSE),"") | G31: =IFERROR(VLOOKUP(D31,Calcs!B:M,11,FALSE),"") | H31: =IFERROR(VLOOKUP(D31,Calcs!B:M,12,FALSE),"")
B32: =IFERROR(VLOOKUP(D32,Calcs!B:G,3,FALSE),"") | D32: P-2545 | F32: =IFERROR(VLOOKUP(D32,Calcs!B:F,5,FALSE),"") | G32: =IFERROR(VLOOKUP(D32,Calcs!B:M,11,FALSE),"") | H32: =IFERROR(VLOOKUP(D32,Calcs!B:M,12,FALSE),"")
... B43: =IFERROR(VLOOKUP(D43,Calcs!B:G,3,FALSE),"") -> 10' Half Bay <80 Monkey Bar HSS w/Splices & HDWE | D43: A-2420 | F43: =IFERROR(VLOOKUP(D43,Calcs!B:F,5,FALSE),"") -> 2 | G43: =IFERROR(VLOOKUP(D43,Calcs!B:M,11,FALSE),"") -> 460 | H43: =IFERROR(VLOOKUP(D43,Calcs!B:M,12,FALSE),"") -> 920
B44: =IFERROR(VLOOKUP(D44,Calcs!B:G,3,FALSE),"") | D44: P-2024 | F44: =IFERROR(VLOOKUP(D44,Calcs!B:F,5,FALSE),0) -> 0 | G44: =IFERROR(VLOOKUP(D44,Calcs!B:M,11,FALSE),"") | H44: =IFERROR(VLOOKUP(D44,Calcs!B:M,12,FALSE),"")
B45: =IFERROR(VLOOKUP(D45,Calcs!B:G,3,FALSE),"") | D45: A-2530 | F45: =IFERROR(VLOOKUP(D45,Calcs!B:F,5,FALSE),"") | G45: =IFERROR(VLOOKUP(D45,Calcs!B:M,11,FALSE),"") | H45: =IFERROR(VLOOKUP(D45,Calcs!B:M,12,FALSE),"")
B46: =IFERROR(VLOOKUP(D46,Calcs!B:G,3,FALSE),"") -> Base Plate Shield | D46: P-2028 | F46: =IFERROR(VLOOKUP(D46,Calcs!B:F,5,FALSE),"") -> 8 | G46: =IFERROR(VLOOKUP(D46,Calcs!B:M,11,FALSE),"") -> 57.5 | H46: =IFERROR(VLOOKUP(D46,Calcs!B:M,12,FALSE),"") -> 460
B47: =IFERROR(VLOOKUP(D47,Calcs!B:G,3,FALSE),"") | D47: P-2500 | F47: =IFERROR(VLOOKUP(D47,Calcs!B:F,5,FALSE),"") | G47: =IFERROR(VLOOKUP(D47,Calcs!B:M,11,FALSE),"") | H47: =IFERROR(VLOOKUP(D47,Calcs!B:M,12,FALSE),"")
B48: =IFERROR(VLOOKUP(D48,Calcs!B:G,3,FALSE),"") | D48: P-2501 | F48: =IFERROR(VLOOKUP(D48,Calcs!B:F,5,FALSE),"") | G48: =IFERROR(VLOOKUP(D48,Calcs!B:M,11,FALSE),"") | H48: =IFERROR(VLOOKUP(D48,Calcs!B:M,12,FALSE),"")
B49: =IFERROR(VLOOKUP(D49,Calcs!B:G,3,FALSE),"") | D49: P-2502 | F49: =IFERROR(VLOOKUP(D49,Calcs!B:F,5,FALSE),"") | G49: =IFERROR(VLOOKUP(D49,Calcs!B:M,11,FALSE),"") | H49: =IFERROR(VLOOKUP(D49,Calcs!B:M,12,FALSE),"")
B50: =IFERROR(VLOOKUP(D50,Calcs!B:G,3,FALSE),"") | D50: P-1032 | F50: =IFERROR(VLOOKUP(D50,Calcs!B:F,5,FALSE),"") | G50: =IFERROR(VLOOKUP(D50,Calcs!B:M,11,FALSE),"") | H50: =IFERROR(VLOOKUP(D50,Calcs!B:M,12,FALSE),"")
B51: =IF(VLOOKUP!E14="yES","Professional Design & Rendering Consulting","") | D51: DESIGN | F51: =IFERROR(VLOOKUP(D51,Calcs!B:F,5,FALSE),"") | G51: =IFERROR(VLOOKUP(D51,Calcs!B:M,11,FALSE),"") | H51: =IFERROR(VLOOKUP(D51,Calcs!B:M,12,FALSE),"")
B52: SUBTOTAL | F52: SUB | H52: =SUM(H21:H51) -> 8223.65
B54: *This portion of the order will be consolidated with other structural and hardware components and shipped together as part of the primary shipment. Mat and padding systems are manufactured separately and will ship independently.
F55: HOLD
B56: DUAL TROLLEY SYSTEM (Optional) | F56: TITL
B57: Unquoted | F57: UQ-TR
B58: =IFERROR(VLOOKUP(D58,Calcs!B:G,3,FALSE),"") -> Trolley Bar | D58: P-2018 | F58: =IFERROR(VLOOKUP(D58,Calcs!B:F,5,FALSE),"") -> 1 | G58: =IFERROR(VLOOKUP(D58,Calcs!B:M,11,FALSE),"") -> 32.2 | H58: =IFERROR(VLOOKUP(D58,Calcs!B:Z,12,FALSE),"") -> 32.2
B59: =IFERROR(VLOOKUP(D59,Calcs!B:G,3,FALSE),"") -> Trolley Bar Plate | D59: P-2025 | F59: =IFERROR(VLOOKUP(D59,Calcs!B:F,5,FALSE),"") -> 2 | G59: =IFERROR(VLOOKUP(D59,Calcs!B:M,11,FALSE),"") -> 27.6 | H59: =IFERROR(VLOOKUP(D59,Calcs!B:Z,12,FALSE),"") -> 55.2
B60: =IFERROR(VLOOKUP(D60,Calcs!B:G,3,FALSE),"") | D60: SSG-TR-A10 | F60: =IFERROR(VLOOKUP(D60,Calcs!B:F,5,FALSE),"") | G60: =IFERROR(VLOOKUP(D60,Calcs!B:M,11,FALSE),"") | H60: =IFERROR(VLOOKUP(D60,Calcs!B:Z,12,FALSE),"")
B61: =IFERROR(VLOOKUP(D61,Calcs!B:G,3,FALSE),"") -> 9' Aluminum Enclosed Rail 550lbs. Max Weight | D61: SSG-TR-A09 | F61: =IFERROR(VLOOKUP(D61,Calcs!B:F,5,FALSE),"") -> 2 | G61: =IFERROR(VLOOKUP(D61,Calcs!B:M,11,FALSE),"") -> 445.05 | H61: =IFERROR(VLOOKUP(D61,Calcs!B:Z,12,FALSE),"") -> 890.1
B62: =IFERROR(VLOOKUP(D62,Calcs!B:G,3,FALSE),"") | D62: SSG-TR-A08 | F62: =IFERROR(VLOOKUP(D62,Calcs!B:F,5,FALSE),"") | G62: =IFERROR(VLOOKUP(D62,Calcs!B:M,11,FALSE),"") | H62: =IFERROR(VLOOKUP(D62,Calcs!B:Z,12,FALSE),"")
B63: =IFERROR(VLOOKUP(D63,Calcs!B:G,3,FALSE),"") | D63: SSG-TR-A07 | F63: =IFERROR(VLOOKUP(D63,Calcs!B:F,5,FALSE),"") | G63: =IFERROR(VLOOKUP(D63,Calcs!B:M,11,FALSE),"") | H63: =IFERROR(VLOOKUP(D63,Calcs!B:Z,12,FALSE),"")
B64: =IFERROR(VLOOKUP(D64,Calcs!B:G,3,FALSE),"") -> Universal Threaded Rod Hanger | D64: SSG-TRH | F64: =IFERROR(VLOOKUP(D64,Calcs!B:F,5,FALSE),"") -> 6 | G64: =IFERROR(VLOOKUP(D64,Calcs!B:M,11,FALSE),"") -> 259.9 | H64: =IFERROR(VLOOKUP(D64,Calcs!B:Z,12,FALSE),"") -> 1559.4
B65: =IFERROR(VLOOKUP(D65,Calcs!B:G,3,FALSE),"") -> End Cap for Rail | D65: SSG-TRN | F65: =IFERROR(VLOOKUP(D65,Calcs!B:F,5,FALSE),"") -> 4 | G65: =IFERROR(VLOOKUP(D65,Calcs!B:M,11,FALSE),"") -> 131.1 | H65: =IFERROR(VLOOKUP(D65,Calcs!B:Z,12,FALSE),"") -> 524.4
B66: =IFERROR(VLOOKUP(D66,Calcs!B:G,3,FALSE),"") -> Trolley for Rail | D66: SSG-TRT | F66: =IFERROR(VLOOKUP(D66,Calcs!B:F,5,FALSE),"") -> 2 | G66: =IFERROR(VLOOKUP(D66,Calcs!B:M,11,FALSE),"") -> 243.8 | H66: =IFERROR(VLOOKUP(D66,Calcs!B:Z,12,FALSE),"") -> 487.6
B67: SUBTOTAL | F67: SUB | H67: =SUM(H58:H66) -> 3548.9
B69: *This portion of the order will be shipped together with other structural and hardware components as part of the primary shipment. Mat and padding systems will be fulfilled and shipped separately.
F70: HOLD
B71: SENSORY GYM ACCESSORIES (Optional) | F71: TITL
B72: Unquoted | F72: UQ-OP
B73: Summit Adventure Slide System | F73: =IF(SUM(F74:F77)>=1,1,"")
B74: =IFERROR(VLOOKUP(D74,Calcs!B:G,3,FALSE),"") | C74: * | D74: A-2216 | E74: *Popular Addition | F74: =IFERROR(VLOOKUP(D74,Calcs!B:F,5,FALSE),"") | G74: =IFERROR(VLOOKUP(D74,Calcs!B:M,11,FALSE),"") | H74: =IFERROR(VLOOKUP(D74,Calcs!B:N,12,FALSE),"")
B75: =IFERROR(VLOOKUP(D75,Calcs!B:G,3,FALSE),"") | D75: WS8203 | E75: *Passthrough Cost | F75: =IFERROR(VLOOKUP(D75,Calcs!B:F,5,FALSE),"") | G75: =IFERROR(VLOOKUP(D75,Calcs!B:M,11,FALSE),"") | H75: =IFERROR(VLOOKUP(D75,Calcs!B:N,12,FALSE),"")
B76: =IF(F75>0.99,"Passthrough Freight Charge (Required)","") -> Passthrough Freight Charge (Required) | D76: 3RD-FREIGHT-SLIDE | E76: *Passthrough Cost | F76: =F75 | H76: =IF(F76=1,"TBD","")
B77: =IFERROR(VLOOKUP(D77,Calcs!B:G,3,FALSE),"") | D77: 150045 | F77: =IFERROR(VLOOKUP(D77,Calcs!B:F,5,FALSE),"") | G77: =IFERROR(VLOOKUP(D77,Calcs!B:M,11,FALSE),"") | H77: =IFERROR(VLOOKUP(D77,Calcs!B:N,12,FALSE),"")
B78: =IF(F74>0.99,"Passthrough Freight Charge (Required)","") -> Passthrough Freight Charge (Required) | D78: 3RD-FREIGHT | E78: *Passthrough Cost | F78: =F77 | H78: =IF(F78=1,"TBD","")
B79: =IFERROR(VLOOKUP(D79,Calcs!B:G,3,FALSE),"") | D79: A-2349 | F79: =IFERROR(VLOOKUP(D79,Calcs!B:F,5,FALSE),"") | G79: =IFERROR(VLOOKUP(D79,Calcs!B:M,11,FALSE),"") | H79: =IFERROR(VLOOKUP(D79,Calcs!B:N,12,FALSE),"")
B80: Climbing Wall & Safety Accessories | F80: =IF(SUM(F81:F83)>=1,1,"") -> 1
B81: =IFERROR(VLOOKUP(D81,Calcs!B:G,3,FALSE),"") | C81: * | D81: SSG-SA-CFM | E81: *Popular Addition | F81: =IFERROR(VLOOKUP(D81,Calcs!B:F,5,FALSE),"") | G81: =IFERROR(VLOOKUP(D81,Calcs!B:M,11,FALSE),"") | H81: =IFERROR(VLOOKUP(D81,Calcs!B:N,12,FALSE),"")
B82: =IFERROR(VLOOKUP(D82,Calcs!B:G,3,FALSE),"") | D82: P-2500 | F82: =IFERROR(VLOOKUP(D82,Calcs!B:F,5,FALSE),"") | G82: =IFERROR(VLOOKUP(D82,Calcs!B:M,11,FALSE),"") | H82: =IFERROR(VLOOKUP(D82,Calcs!B:N,12,FALSE),"")
B83: =IFERROR(VLOOKUP(D83,Calcs!B:G,3,FALSE),"") -> Adventure Climbing Wall - Wall Mounted-Metal Studs (Includes Climbing Holds) | D83: SSG-SA-CWM | E83: *Popular Addition | F83: =IFERROR(VLOOKUP(D83,Calcs!B:F,5,FALSE),"") -> 1 | G83: =IFERROR(VLOOKUP(D83,Calcs!B:M,11,FALSE),"") -> 2442.6 | H83: =IFERROR(VLOOKUP(D83,Calcs!B:N,12,FALSE),"") -> 2442.6
B84: Ladder - Safety Accessories | F84: =IF(SUM(F85)>=1,1,"")
B85: =IFERROR(VLOOKUP(D85,Calcs!B:G,3,FALSE),"") | D85: P-2502 | F85: =IFERROR(VLOOKUP(D85,Calcs!B:F,5,FALSE),"") | G85: =IFERROR(VLOOKUP(D85,Calcs!B:M,11,FALSE),"") | H85: =IFERROR(VLOOKUP(D85,Calcs!B:N,12,FALSE),"")
B86: =IFERROR(VLOOKUP(D86,Calcs!B:G,3,FALSE),"") | D86: K-5000 | F86: =IFERROR(VLOOKUP(D86,Calcs!B:F,5,FALSE),"") | G86: =IFERROR(VLOOKUP(D86,Calcs!B:M,11,FALSE),"") | H86: =IFERROR(VLOOKUP(D86,Calcs!B:N,12,FALSE),"")
B87: =IFERROR(VLOOKUP(D87,Calcs!B:G,3,FALSE),"") | D87: T11412 | F87: =IFERROR(VLOOKUP(D87,Calcs!B:F,5,FALSE),"") | G87: =IFERROR(VLOOKUP(D87,Calcs!B:M,11,FALSE),"") | H87: =IFERROR(VLOOKUP(D87,Calcs!B:N,12,FALSE),"")
B88: =IF(B87="adjustable Indoor Climbing Wall","Adjustable Indoor Climbing Wall - Freight Charge","") | D88: T11412-FREIGHT | F88: =IF(F87=1,1,"") | G88: =IFERROR(VLOOKUP(D88,Calcs!B:M,11,FALSE),"") | H88: =IFERROR(VLOOKUP(D88,Calcs!B:N,12,FALSE),"")
B89: =IFERROR(VLOOKUP(D89,Calcs!B:G,3,FALSE),"") | C89: * | D89: B07V3J9S2R | E89: *Popular Addition | F89: =IFERROR(VLOOKUP(D89,Calcs!B:F,5,FALSE),"") | G89: =IFERROR(VLOOKUP(D89,Calcs!B:M,11,FALSE),"") | H89: =IFERROR(VLOOKUP(D89,Calcs!B:N,12,FALSE),"")
B90: =IFERROR(VLOOKUP(D90,Calcs!B:G,3,FALSE),"") | D90: B07TSDMPNQ | E90: *Popular Addition | F90: =IFERROR(VLOOKUP(D90,Calcs!B:F,5,FALSE),"") | G90: =IFERROR(VLOOKUP(D90,Calcs!B:M,11,FALSE),"") | H90: =IFERROR(VLOOKUP(D90,Calcs!B:N,12,FALSE),"")
B91: =IFERROR(VLOOKUP(D91,Calcs!B:G,3,FALSE),"") | C91: * | D91: B0BGDQF46S | F91: =IFERROR(VLOOKUP(D91,Calcs!B:F,5,FALSE),"") | G91: =IFERROR(VLOOKUP(D91,Calcs!B:M,11,FALSE),"") | H91: =IFERROR(VLOOKUP(D91,Calcs!B:N,12,FALSE),"")
B92: =IFERROR(VLOOKUP(D92,Calcs!B:G,3,FALSE),"") | C92: * | D92: B0193YG8GI | F92: =IFERROR(VLOOKUP(D92,Calcs!B:F,5,FALSE),"") | G92: =IFERROR(VLOOKUP(D92,Calcs!B:M,11,FALSE),"") | H92: =IFERROR(VLOOKUP(D92,Calcs!B:N,12,FALSE),"")
B93: =IFERROR(VLOOKUP(D93,Calcs!B:G,3,FALSE),"") | C93: * | D93: B07MC3144W | F93: =IFERROR(VLOOKUP(D93,Calcs!B:F,5,FALSE),"") | G93: =IFERROR(VLOOKUP(D93,Calcs!B:M,11,FALSE),"") | H93: =IFERROR(VLOOKUP(D93,Calcs!B:N,12,FALSE),"")
B94: =IFERROR(VLOOKUP(D94,Calcs!B:G,3,FALSE),"") | C94: * | D94: B07PQHSZPR | F94: =IFERROR(VLOOKUP(D94,Calcs!B:F,5,FALSE),"") | G94: =IFERROR(VLOOKUP(D94,Calcs!B:M,11,FALSE),"") | H94: =IFERROR(VLOOKUP(D94,Calcs!B:N,12,FALSE),"")
B95: =IFERROR(VLOOKUP(D95,Calcs!B:G,3,FALSE),"") | C95: * | D95: B07ZQZD6WX | F95: =IFERROR(VLOOKUP(D95,Calcs!B:F,5,FALSE),"") | G95: =IFERROR(VLOOKUP(D95,Calcs!B:M,11,FALSE),"") | H95: =IFERROR(VLOOKUP(D95,Calcs!B:N,12,FALSE),"")
B96: =IFERROR(VLOOKUP(D96,Calcs!B:G,3,FALSE),"") | C96: * | D96: B08DTP539F | F96: =IFERROR(VLOOKUP(D96,Calcs!B:F,5,FALSE),"") | G96: =IFERROR(VLOOKUP(D96,Calcs!B:M,11,FALSE),"") | H96: =IFERROR(VLOOKUP(D96,Calcs!B:N,12,FALSE),"")
B97: =IFERROR(VLOOKUP(D97,Calcs!B:G,3,FALSE),"") | C97: * | D97: B01C3I4SL8 | E97: *Popular Addition | F97: =IFERROR(VLOOKUP(D97,Calcs!B:F,5,FALSE),"") | G97: =IFERROR(VLOOKUP(D97,Calcs!B:M,11,FALSE),"") | H97: =IFERROR(VLOOKUP(D97,Calcs!B:N,12,FALSE),"")
B98: =IFERROR(VLOOKUP(D98,Calcs!B:G,3,FALSE),"") | D98: SFCS48 | E98: *Climbing Safety | F98: =IFERROR(VLOOKUP(D98,Calcs!B:F,5,FALSE),"") | G98: =IFERROR(VLOOKUP(D98,Calcs!B:M,11,FALSE),"") | H98: =IFERROR(VLOOKUP(D98,Calcs!B:N,12,FALSE),"")
D99: SP150 | E99: *Popular Addition | F99: =IFERROR(VLOOKUP(D99,Calcs!B:F,5,FALSE),"") | G99: =IFERROR(VLOOKUP(D99,Calcs!B:M,11,FALSE),"") | H99: =IFERROR(VLOOKUP(D99,Calcs!B:N,12,FALSE),"")
D100: SP5000 | E100: *Popular Addition | F100: =IFERROR(VLOOKUP(D100,Calcs!B:F,5,FALSE),"") | G100: =IFERROR(VLOOKUP(D100,Calcs!B:M,11,FALSE),"") | H100: =IFERROR(VLOOKUP(D100,Calcs!B:N,12,FALSE),"")
D101: B07918TH4Q | E101: *Popular Addition | F101: =IFERROR(VLOOKUP(D101,Calcs!B:F,5,FALSE),"") | G101: =IFERROR(VLOOKUP(D101,Calcs!B:M,11,FALSE),"") | H101: =IFERROR(VLOOKUP(D101,Calcs!B:N,12,FALSE),"")
B102: =IFERROR(VLOOKUP(D102,Calcs!B:G,3,FALSE),"") | C102: * | D102: 120040 | F102: =IFERROR(VLOOKUP(D102,Calcs!B:F,5,FALSE),"") | G102: =IFERROR(VLOOKUP(D102,Calcs!B:M,11,FALSE),"") | H102: =IFERROR(VLOOKUP(D102,Calcs!B:N,12,FALSE),"")
B103: =IFERROR(VLOOKUP(D103,Calcs!B:G,3,FALSE),"") | C103: * | D103: 120050 | E103: *Popular Addition | F103: =IFERROR(VLOOKUP(D103,Calcs!B:F,5,FALSE),"") | G103: =IFERROR(VLOOKUP(D103,Calcs!B:M,11,FALSE),"") | H103: =IFERROR(VLOOKUP(D103,Calcs!B:N,12,FALSE),"")
B104: =IFERROR(VLOOKUP(D104,Calcs!B:G,3,FALSE),"") | D104: 120077 | F104: =IFERROR(VLOOKUP(D104,Calcs!B:F,5,FALSE),"") | G104: =IFERROR(VLOOKUP(D104,Calcs!B:M,11,FALSE),"") | H104: =IFERROR(VLOOKUP(D104,Calcs!B:N,12,FALSE),"")
B105: =IFERROR(VLOOKUP(D105,Calcs!B:G,3,FALSE),"") | D105: B0894XNGJP | F105: =IFERROR(VLOOKUP(D105,Calcs!B:F,5,FALSE),"") | G105: =IFERROR(VLOOKUP(D105,Calcs!B:M,11,FALSE),"") | H105: =IFERROR(VLOOKUP(D105,Calcs!B:N,12,FALSE),"")
B106: =IFERROR(VLOOKUP(D106,Calcs!B:G,3,FALSE),"") | D106: B092QYLLL2 | E106: *Popular Addition | F106: =IFERROR(VLOOKUP(D106,Calcs!B:F,5,FALSE),"") | G106: =IFERROR(VLOOKUP(D106,Calcs!B:M,11,FALSE),"") | H106: =IFERROR(VLOOKUP(D106,Calcs!B:N,12,FALSE),"")
B107: =IFERROR(VLOOKUP(D107,Calcs!B:G,3,FALSE),"") | D107: 815DBLESTK | E107: *Extremely Strong | F107: =IFERROR(VLOOKUP(D107,Calcs!B:F,5,FALSE),"") | G107: =IFERROR(VLOOKUP(D107,Calcs!B:M,11,FALSE),"") | H107: =IFERROR(VLOOKUP(D107,Calcs!B:N,12,FALSE),"")
B108: =IFERROR(VLOOKUP(D108,Calcs!B:G,3,FALSE),"") | D108: 382-408_x000D_ | F108: =IFERROR(VLOOKUP(D108,Calcs!B:F,5,FALSE),"") | G108: =IFERROR(VLOOKUP(D108,Calcs!B:M,11,FALSE),"") | H108: =IFERROR(VLOOKUP(D108,Calcs!B:N,12,FALSE),"")
B109: =IFERROR(VLOOKUP(D109,Calcs!B:G,3,FALSE),"") | D109: XL-PLAT | F109: =IFERROR(VLOOKUP(D109,Calcs!B:F,5,FALSE),"") | G109: =IFERROR(VLOOKUP(D109,Calcs!B:M,11,FALSE),"") | H109: =IFERROR(VLOOKUP(D109,Calcs!B:N,12,FALSE),"")
B110: =IFERROR(VLOOKUP(D110,Calcs!B:G,3,FALSE),"") | D110: B07Z79ZCZX | E110: *Popular Addition | F110: =IFERROR(VLOOKUP(D110,Calcs!B:F,5,FALSE),"") | G110: =IFERROR(VLOOKUP(D110,Calcs!B:M,11,FALSE),"") | H110: =IFERROR(VLOOKUP(D110,Calcs!B:N,12,FALSE),"")
B111: =IFERROR(VLOOKUP(D111,Calcs!B:G,3,FALSE),"") | D111: 48RACK | E111: *Popular Addition | F111: =IFERROR(VLOOKUP(D111,Calcs!B:F,5,FALSE),"") | G111: =IFERROR(VLOOKUP(D111,Calcs!B:M,11,FALSE),"") | H111: =IFERROR(VLOOKUP(D111,Calcs!B:N,12,FALSE),"")
B112: =IFERROR(VLOOKUP(D112,Calcs!B:G,3,FALSE),"") | D112: 382-411 | F112: =IFERROR(VLOOKUP(D112,Calcs!B:F,5,FALSE),"") | G112: =IFERROR(VLOOKUP(D112,Calcs!B:M,11,FALSE),"") | H112: =IFERROR(VLOOKUP(D112,Calcs!B:N,12,FALSE),"")
D113: B0C4YB8D64
B114: Essential Carabiners & Connectors | F114: =IF(SUM(F115:F118)>1,1,"") -> 1
B115: =IFERROR(VLOOKUP(D115,Calcs!B:G,3,FALSE),"") -> Auto Locking Carabiner Clips - 28KN (6172lbs) Heavy Duty Carabiner (4 Pack) | D115: B0CDVDZSB1 | E115: *Popular Addition | F115: =IFERROR(VLOOKUP(D115,Calcs!B:F,5,FALSE),0) -> 2 | G115: =IFERROR(VLOOKUP(D115,Calcs!B:M,11,FALSE),"") -> 52.88 | H115: =IFERROR(VLOOKUP(D115,Calcs!B:N,12,FALSE),"") -> 105.76
...

Sheet Summit Flex Proposal
B1: Summit Sensory Gym | J1: PSF File Name | K1: =B10&" - Summit Flex- PSFv73 - "&TEXT(H9,"MMDDYYYY") -> Soar Autism Center - South Fort Collins - Summit Flex- PSFv73 - 07222026
B2: 6150 S Geneva Court | J2: Proposal File Name | K2: =B10&" - Summit Flex - Proposal "&F9&" - "&TEXT(H9,"MMDDYYYY") -> Soar Autism Center - South Fort Collins - Summit Flex - Proposal FLEX-SS-260722-001 - 07222026
B3: Englewood, CO 80111
B4: Phone: 720-457-5500
B5: Fax: 720-242-8085
B6: Support@SummitSensory.com
B8: CUSTOMER INFO | F8: PROPOSAL # | H8: DATE
B9: =Discovery!B2 -> Tyler Galiotto | F9: ="FLEX-" & UPPER(LEFT(B10,1) & RIGHT(B10,1)) & "-" & TEXT(H9,"yymmdd") & "-" & TEXT( IF(AND(ISNUMBER(K11),K11>0), K11, COUNTIFS($B$10:B10,B10,$H$9:H9,H9) ), "000") -> FLEX-SS-260722-001 | H9: =TODAY() -> 46225
B10: =Discovery!B3 -> Soar Autism Center - South Fort Collins | F10: PROJECT ID # | H10: VALID UNTIL
B11: =Discovery!B4 -> 3801 Automation Way | F11: ="SSG-"&Discovery!B13 -> SSG-12552093278 | H11: =H9+7 -> 46232 | J11: Proposal # Override | K11: 0
B12: =Discovery!B5&" "&Discovery!B6&" "&ZAPIER!J2 -> Fort Collins, CO 80525 5203895979
B14: Based on your business needs, we put the following proposal together to help with your purchase decision.
B16: PROPOSAL DETAILS
B17: ="Summit Flex: Universal Exercise Unit (Spider Cage)"&IF(SUM(Calcs!F268:F295)>0.1," & Accessories","") -> Summit Flex: Universal Exercise Unit (Spider Cage) & Accessories
B20: DESCRIPTION | D20: SKU | F20: QTY | G20: UNIT PRICE (USD) | H20: AMOUNT
B21: PRODUCT DESCRIPTION | F21: TITL
B22: SUMMIT FLEX: UNIVERSAL EXERCISE UNIT (SPIDER CAGE) | D22: A-2200 | F22: 1 | G22: =IFERROR(VLOOKUP(D22,Calcs!B:N,12,FALSE),"") -> 5414.4 | H22: =F22*G22 -> 5414.4
B23: The Summit Flex Universal Exercise Unit (Spider Cage) features a pulley system that allows for resistive muscle-strengthening exercises, customized to each patient's needs. By eliminating the influence of gravity, therapists can isolate and train the target joint, promoting range of motion and improved muscle strength. Additionally, the Spider Cage suspension system provides just the right amount of support needed for securing and balancing patients while practicing or performing needed movements, making it a valuable tool for improving balance, coordination, and postural control. | F23: HOLD
B24: SUBTOTAL | F24: HOLD | H24: =H22 -> 5414.4
F25: HOLD
B26: UNIVERSAL EXERCISE UNIT (SPIDER CAGE) TRACKING RAIL SYSTEM (Optional) | F26: HOLD
B27: Unquoted | F27: UQ-RAIL
B28: =IFERROR(VLOOKUP(D28,Calcs!B:G,3,FALSE),"") -> Integrated Suspension Tracking Rail System | D28: UEU-ISTRS | F28: =IFERROR(VLOOKUP('Summit Flex Proposal'!D28,Calcs!$B$260:$F$295,5,FALSE),"") -> 1 | G28: =IFERROR(VLOOKUP(D28,Calcs!B:N,12,FALSE),"") -> 1415.04 | H28: =IFERROR(VLOOKUP(D28,Calcs!B:AB,11,FALSE),"") -> 1415.04
B29: Our upgraded Summit Flex Universal Exercise Unit (Spider Cage) now features a premium center-mounted tracking rail that allows a suspended patient in a therapy suit to glide smoothly from the back to the front of the cage. This addition is perfect for gait training, walking therapy, and core strengthening, making the Summit Flex ideal for advanced therapy applications. The tracking rail enhances mobility and safety, creating more engaging and functional movement experiences for patients. | F29: =F28 -> 1
B30: =IFERROR(VLOOKUP(D30,Calcs!B:G,3,FALSE),"") | D30: UEU-ISTRS-UNIKIT | F30: =IFERROR(VLOOKUP('Summit Flex Proposal'!D30,Calcs!$B$260:$F$295,5,FALSE),"") | G30: =IFERROR(VLOOKUP(D30,Calcs!B:N,12,FALSE),"") | H30: =IFERROR(VLOOKUP(D30,Calcs!B:AB,11,FALSE),"")
B31: =IFERROR(VLOOKUP(D31,Calcs!B:G,3,FALSE),"") -> Suspension Harness Kit | D31: UEU-HARKIT | F31: =IFERROR(VLOOKUP('Summit Flex Proposal'!D31,Calcs!$B$260:$F$295,5,FALSE),"") -> 1 | G31: =IFERROR(VLOOKUP(D31,Calcs!B:N,12,FALSE),"") -> 204.435 | H31: =IFERROR(VLOOKUP(D31,Calcs!B:AB,11,FALSE),"") -> 204.435
B32: SUBTOTAL | F32: HOLD | H32: =SUM(H28:H31) -> 1619.475
F33: HOLD
B34: UNIVERSAL EXCERISE UNIT (SPIDER CAGE) SAFETY PADDING (Optional) | F34: HOLD
B35: Unquoted | F35: UQ-PAD
B36: =IFERROR(VLOOKUP(D36,Calcs!B:G,3,FALSE),"") | D36: FLEX69482 | F36: =IFERROR(VLOOKUP('Summit Flex Proposal'!D36,Calcs!$B$260:$F$295,5,FALSE),"") | G36: =IFERROR(VLOOKUP(D36,Calcs!B:N,12,FALSE),"") | H36: =IFERROR(VLOOKUP(D36,Calcs!B:AB,11,FALSE),"")
B37: =IFERROR(VLOOKUP(D37,Calcs!B:G,3,FALSE),"") | D37: FLEX72482 | F37: =IFERROR(VLOOKUP('Summit Flex Proposal'!D37,Calcs!$B$260:$F$295,5,FALSE),"") | G37: =IFERROR(VLOOKUP(D37,Calcs!B:N,12,FALSE),"") | H37: =IFERROR(VLOOKUP(D37,Calcs!B:AB,11,FALSE),"")
B38: =IFERROR(VLOOKUP(D38,Calcs!B:G,3,FALSE),"") | D38: FLEX-VERT-BUNDLE | F38: =IFERROR(VLOOKUP('Summit Flex Proposal'!D38,Calcs!$B$260:$F$295,5,FALSE),"") | G38: =IFERROR(VLOOKUP(D38,Calcs!B:N,12,FALSE),"") | H38: =IFERROR(VLOOKUP(D38,Calcs!B:AB,11,FALSE),"")
B39: =IFERROR(VLOOKUP(D39,Calcs!B:G,3,FALSE),"") -> Floor Padding - 69" x 72" x 2" V1 Folding Mat - 2 Sections | D39: FLEX69722 | F39: =IFERROR(VLOOKUP('Summit Flex Proposal'!D39,Calcs!$B$260:$F$295,5,FALSE),"") -> 1 | G39: =IFERROR(VLOOKUP(D39,Calcs!B:N,12,FALSE),"") -> 574.09 | H39: =IFERROR(VLOOKUP(D39,Calcs!B:AB,11,FALSE),"") -> 574.09
B40: =IFERROR(VLOOKUP(D40,Calcs!B:G,3,FALSE),"") | D40: FLEX-PAD-BUNDLE | F40: =IFERROR(VLOOKUP('Summit Flex Proposal'!D40,Calcs!$B$260:$F$295,5,FALSE),"") | G40: =IFERROR(VLOOKUP(D40,Calcs!B:N,12,FALSE),"") | H40: =IFERROR(VLOOKUP(D40,Calcs!B:AB,11,FALSE),"")
H41: =IFERROR(VLOOKUP(D41,Calcs!B:AB,11,FALSE),"")
B42: SUBTOTAL | F42: SUB | H42: =SUM(H36:H41) -> 574.09
F43: HOLD
B44: UNIVERSAL EXCERCISE UNIT (SPIDER CAGE) ACCESSORIES (Optional) | F44: HOLD
B45: Unquoted | F45: UQ-ACC
B46: =IFERROR(VLOOKUP(D46,Calcs!B:G,3,FALSE),"") -> Petzel - Full Body Youth Harness (Supports Up to 65 lbs) | D46: OUISTITI | F46: =IFERROR(VLOOKUP('Summit Flex Proposal'!D46,Calcs!$B$260:$F$295,5,FALSE),"") -> 1 | G46: =IFERROR(VLOOKUP(D46,Calcs!B:N,12,FALSE),"") -> 163.35 | H46: =IFERROR(VLOOKUP(D46,Calcs!B:AB,11,FALSE),"") -> 163.35
B47: =IFERROR(VLOOKUP(D47,Calcs!B:G,3,FALSE),"") | D47: B092QYLLL2 | F47: =IFERROR(VLOOKUP('Summit Flex Proposal'!D47,Calcs!$B$260:$F$295,5,FALSE),"") | G47: =IFERROR(VLOOKUP(D47,Calcs!B:N,12,FALSE),"") | H47: =IFERROR(VLOOKUP(D47,Calcs!B:AB,11,FALSE),"")
B48: =IFERROR(VLOOKUP(D48,Calcs!B:G,3,FALSE),"") | D48: L54 | F48: =IFERROR(VLOOKUP('Summit Flex Proposal'!D48,Calcs!$B$260:$F$295,5,FALSE),"") | G48: =IFERROR(VLOOKUP(D48,Calcs!B:N,12,FALSE),"") | H48: =IFERROR(VLOOKUP(D48,Calcs!B:AB,11,FALSE),"")
B49: =IFERROR(VLOOKUP(D49,Calcs!B:G,3,FALSE),"") -> Equipment Rack (Frame Mounted) | D49: FLEX-RACK | F49: =IFERROR(VLOOKUP('Summit Flex Proposal'!D49,Calcs!$B$260:$F$295,5,FALSE),"") -> 1 | G49: =IFERROR(VLOOKUP(D49,Calcs!B:N,12,FALSE),"") -> 107.25 | H49: =IFERROR(VLOOKUP(D49,Calcs!B:AB,11,FALSE),"") -> 107.25
B50: =IFERROR(VLOOKUP(D50,Calcs!B:G,3,FALSE),"") | D50: FLEX-BOOT | F50: =IFERROR(VLOOKUP('Summit Flex Proposal'!D50,Calcs!$B$260:$F$295,5,FALSE),"") | G50: =IFERROR(VLOOKUP(D50,Calcs!B:N,12,FALSE),"") | H50: =IFERROR(VLOOKUP(D50,Calcs!B:AB,11,FALSE),"")
B51: =IFERROR(VLOOKUP(D51,Calcs!B:G,3,FALSE),"") -> Flex Leather Belt Bundle (7 Belts - All Sizes) (1) XX Small Leather Belt (1) X Small Leather Belt (1) Small Leather Belt (1) Medium Leather Belt (1) Large Leather Belt (1) X Large Leather Belt (1) XX Large Leather Belt | D51: FLEX-BELT-BUNDLE | F51: =IFERROR(VLOOKUP('Summit Flex Proposal'!D51,Calcs!$B$260:$F$295,5,FALSE),"") -> 1 | G51: =IFERROR(VLOOKUP(D51,Calcs!B:N,12,FALSE),"") -> 1470 | H51: =IFERROR(VLOOKUP(D51,Calcs!B:AB,11,FALSE),"") -> 1470
B52: =IFERROR(VLOOKUP(D52,Calcs!B:G,3,FALSE),"") -> Leather Belt (Size - TBD) | D52: FLEX-BELT-TBD | F52: =IFERROR(VLOOKUP('Summit Flex Proposal'!D52,Calcs!$B$260:$F$295,5,FALSE),"") -> 2 | G52: =IFERROR(VLOOKUP(D52,Calcs!B:N,12,FALSE),"") -> 453.76 | H52: =IFERROR(VLOOKUP(D52,Calcs!B:AB,11,FALSE),"") -> 226.88
B53: =IFERROR(VLOOKUP(D53,Calcs!B:G,3,FALSE),"") | D53: FLEX-BELT-XXS | F53: =IFERROR(VLOOKUP('Summit Flex Proposal'!D53,Calcs!$B$260:$F$295,5,FALSE),"") | G53: =IFERROR(VLOOKUP(D53,Calcs!B:N,12,FALSE),"") | H53: =IFERROR(VLOOKUP(D53,Calcs!B:AB,11,FALSE),"")
B54: =IFERROR(VLOOKUP(D54,Calcs!B:G,3,FALSE),"") | D54: FLEX-BELT-XS | F54: =IFERROR(VLOOKUP('Summit Flex Proposal'!D54,Calcs!$B$260:$F$295,5,FALSE),"") | G54: =IFERROR(VLOOKUP(D54,Calcs!B:N,12,FALSE),"") | H54: =IFERROR(VLOOKUP(D54,Calcs!B:AB,11,FALSE),"")
B55: =IFERROR(VLOOKUP(D55,Calcs!B:G,3,FALSE),"") | D55: FLEX-BELT-S | F55: =IFERROR(VLOOKUP('Summit Flex Proposal'!D55,Calcs!$B$260:$F$295,5,FALSE),"") | G55: =IFERROR(VLOOKUP(D55,Calcs!B:N,12,FALSE),"") | H55: =IFERROR(VLOOKUP(D55,Calcs!B:AB,11,FALSE),"")
B56: =IFERROR(VLOOKUP(D56,Calcs!B:G,3,FALSE),"") | D56: FLEX-BELT-M | F56: =IFERROR(VLOOKUP('Summit Flex Proposal'!D56,Calcs!$B$260:$F$295,5,FALSE),"") | G56: =IFERROR(VLOOKUP(D56,Calcs!B:N,12,FALSE),"") | H56: =IFERROR(VLOOKUP(D56,Calcs!B:AB,11,FALSE),"")
B57: =IFERROR(VLOOKUP(D57,Calcs!B:G,3,FALSE),"") | D57: FLEX-BELT-L | F57: =IFERROR(VLOOKUP('Summit Flex Proposal'!D57,Calcs!$B$260:$F$295,5,FALSE),"") | G57: =IFERROR(VLOOKUP(D57,Calcs!B:N,12,FALSE),"") | H57: =IFERROR(VLOOKUP(D57,Calcs!B:AB,11,FALSE),"")
... B59: =IFERROR(VLOOKUP(D59,Calcs!B:G,3,FALSE),"") | D59: FLEX-BELT-XXL | F59: =IFERROR(VLOOKUP('Summit Flex Proposal'!D59,Calcs!$B$260:$F$295,5,FALSE),"") | G59: =IFERROR(VLOOKUP(D59,Calcs!B:N,12,FALSE),"") | H59: =IFERROR(VLOOKUP(D59,Calcs!B:AB,11,FALSE),"")
B60: =IF(F60>0.99,"Passthrough Freight Charge for Belt(s) / Boot(s)","") -> Passthrough Freight Charge for Belt(s) / Boot(s) | D60: 3RD-FREIGHT | F60: =IF(SUM(F50:F59)>0.99,1,0) -> 1 | G60: =IF(F60>0.9,95,"") -> 95 | H60: =IFERROR(VLOOKUP(D60,Calcs!B:AB,11,FALSE),"") -> 0
B61: =IFERROR(VLOOKUP(D61,Calcs!B:G,3,FALSE),"") -> TheraBungee - 10 Piece Bungee Set | D61: UEU-THERABUNGEE-23 | E61: *Highly Recommended | F61: =IFERROR(VLOOKUP('Summit Flex Proposal'!D61,Calcs!$B$260:$F$295,5,FALSE),"") -> 1 | G61: =IFERROR(VLOOKUP(D61,Calcs!B:N,12,FALSE),"") -> 297.07 | H61: =IFERROR(VLOOKUP(D61,Calcs!B:AB,11,FALSE),"") -> 297.07
B62: =IFERROR(VLOOKUP(D62,Calcs!B:G,3,FALSE),"") | D62: BASIC | F62: =IFERROR(VLOOKUP('Summit Flex Proposal'!D62,Calcs!$B$260:$F$295,5,FALSE),"") | G62: =IFERROR(VLOOKUP(D62,Calcs!B:N,12,FALSE),"") | H62: =IFERROR(VLOOKUP(D62,Calcs!B:AB,11,FALSE),"")
B63: =IFERROR(VLOOKUP(D63,Calcs!B:G,3,FALSE),"") -> Standard Equipment Set - 82 Elements | D63: STANDARD | F63: =IFERROR(VLOOKUP('Summit Flex Proposal'!D63,Calcs!$B$260:$F$295,5,FALSE),"") -> 1 | G63: =IFERROR(VLOOKUP(D63,Calcs!B:N,12,FALSE),"") -> 1649.99 | H63: =IFERROR(VLOOKUP(D63,Calcs!B:AB,11,FALSE),"") -> 1649.99
B64: =IFERROR(VLOOKUP(D64,Calcs!B:G,3,FALSE),"") | D64: FULL | E64: *Highly Recommended | F64: =IFERROR(VLOOKUP('Summit Flex Proposal'!D64,Calcs!$B$260:$F$295,5,FALSE),"") | G64: =IFERROR(VLOOKUP(D64,Calcs!B:N,12,FALSE),"") | H64: =IFERROR(VLOOKUP(D64,Calcs!B:AB,11,FALSE),"")
B65: SUBTOTAL | F65: SUB | H65: =SUM(H46:H64) -> 4141.42
F66: HOLD
B67: CUSTOM COLOR UPCHARGE | F67: HOLD
B68: Premium Powder Color | D68: POW-1000 | F68: 1 | H68: {=_xlfn.IFS(Discovery!B44="Cardinal",0,Discovery!B44="Prismatic",350,Discovery!B44="Prismatic-Other",Discovery!B45)} -> 0
F69: HOLD
F70: SUBTOTAL: | H70: =H24+H32+H42+H65+H68 -> 11749.385
F71: DISCOUNT: | H71: =Calcs!Q269 -> 0
F72: =IFERROR(IF(Calcs!Q269>0.01,"DISCOUNT EXPIRATION:",""),"") | H72: =IFERROR(IF(Calcs!Q269>0.01,(H9+6),""),"")
B74: IMPORTANT PROPOSAL DETAILS: This proposal serves as a detailed estimate of the total cost for the products and services outlined and does not constitute an invoice. Once signed and returned, it becomes a binding agreement, confirming acceptance of the order and associated payment terms. A 50% deposit is required to initiate production, with the remaining balance due prior to shipment. The signed proposal may be returned by mail or fax using the contact information provided above. For payments made by credit card, a 3.5% processing fee will be added to the total amount. | F74: CRATING & FREIGHT: | H74: =IF(Discovery!C19="TBD","TBD",Discovery!C19) -> TBD
F75: FREIGHT-MATS: | H75: =IF(Discovery!C24="TBD","TBD",Discovery!C24) -> 859.14
F76: ESTIMATED TAX: | H76: =IF(Discovery!C25="TBD","TBD",Discovery!C25) -> 294.07
F77: TOTAL PROPOSAL: | H77: =H70-H71+(IF(H74="TBD",0,H74))+(IF(H75="TBD",0,H75))+(IF(H76="TBD",0,H76)) -> 12902.595
F78: 50% DEPOSIT: | H78: =H77/2 -> 6451.2975
F79: 1
B80: CRATING & FREIGHT FEES: Final crating and freight charges will be calculated and invoiced at the time of shipment based on the actual costs incurred and the rates in effect at that time. Summit makes no representations or warranties, express or implied, regarding the availability or stability of crating costs or freight rates prior to shipment, and Buyer acknowledges and agrees that such charges may increase or decrease between the date of proposal and the shipment date.
B83: Customer Acceptance
B87: Signature | D87: Printed Name | G87: Date
B89: If you have any questions, please contact Bryan Shepherd, 720-457-5500, Bryan@SummitSensory.com

Sheet Flex Pro-Pack
B1: Summit Sensory Gym | J1: PSF File Name | K1: =B10&" - Summit Flex- PSFv73 - "&TEXT(H9,"MMDDYYYY") -> Soar Autism Center - South Fort Collins - Summit Flex- PSFv73 - 07222026
B2: 6150 S Geneva Court | J2: Proposal File Name | K2: =B10&" - Summit Flex - Proposal "&F9&" - "&TEXT(H9,"MMDDYYYY") -> Soar Autism Center - South Fort Collins - Summit Flex - Proposal FLEXPRO-SS-260722-001 - 07222026
B3: Englewood, CO 80111
B4: Phone: 720-457-5500
B5: Fax: 720-242-8085
B6: Support@SummitSensory.com
B8: CUSTOMER INFO | F8: PROPOSAL # | H8: DATE
B9: =Discovery!B2 -> Tyler Galiotto | F9: ="FLEXPRO-" & UPPER(LEFT(B10,1) & RIGHT(B10,1)) & "-" & TEXT(H9,"yymmdd") & "-" & TEXT( IF(AND(ISNUMBER(K11),K11>0), K11, COUNTIFS($B$10:B10,B10,$H$9:H9,H9) ), "000") -> FLEXPRO-SS-260722-001 | H9: =TODAY() -> 46225
B10: =Discovery!B3 -> Soar Autism Center - South Fort Collins | F10: PROJECT ID # | H10: VALID UNTIL
B11: =Discovery!B4 -> 3801 Automation Way | F11: ="SSG-"&Discovery!B13 -> SSG-12552093278 | H11: =H9+7 -> 46232 | J11: Proposal # Override | K11: 0
B12: =Discovery!B5&" "&Discovery!B6 -> Fort Collins, CO 80525
B15: Based on your business needs, we put the following proposal together to help with your purchase decision.
B17: PROPOSAL DETAILS
B18: Summit Flex: Pro Pack – Complete Universal Exercise Unit System
B21: DESCRIPTION | D21: SKU | F21: QTY | G21: UNIT PRICE (USD) | H21: AMOUNT
B22: PRODUCT DESCRIPTION | F22: TITL
B23: SUMMIT FLEX: PRO PACK - COMPLETE UNIVERSAL EXCERISE UNIT SYSTEM | F23: HOLD
B24: Summit Flex: Universal Excerise Unit (Spider Cage) | D24: A-2200 | F24: 1 | G24: =IFERROR(VLOOKUP(D24,Calcs!B:N,12,FALSE),"") -> 5414.4 | H24: =F24*G24 -> 5414.4
B25: The Summit Flex Universal Exercise Unit (Spider Cage) features a pulley system that allows for resistive muscle-strengthening exercises, customized to each patient's needs. By eliminating the influence of gravity, therapists can isolate and train the target joint, promoting range of motion and improved muscle strength. Additionally, the Spider Cage suspension system provides just the right amount of support needed for securing and balancing patients while practicing or performing needed movements, making it a valuable tool for improving balance, coordination, and postural control. | F25: HOLD
B26: Integrated Suspension Tracking Rail System | D26: UEU-ISTRS | F26: =IFERROR(VLOOKUP('Flex Pro-Pack'!D26,Calcs!$B$260:$F$295,5,FALSE),"") -> 1 | G26: =IFERROR(VLOOKUP(D26,Calcs!B:N,12,FALSE),"") -> 1415.04 | H26: =IFERROR(VLOOKUP(D26,Calcs!B:AB,11,FALSE),"") -> 1415.04
B27: Our upgraded Summit Flex Universal Exercise Unit (Spider Cage) now features a premium center-mounted tracking rail that allows a suspended patient in a therapy suit to glide smoothly from the back to the front of the cage. This addition is perfect for gait training, walking therapy, and core strengthening, making the Summit Flex ideal for advanced therapy applications. The tracking rail enhances mobility and safety, creating more engaging and functional movement experiences for patients. | F27: =F26 -> 1
B28: =IFERROR(VLOOKUP(D28,Calcs!B:G,3,FALSE),"") -> Suspension Harness Kit | D28: UEU-HARKIT | F28: 1 | G28: =IFERROR(VLOOKUP(D28,Calcs!B:N,12,FALSE),"") -> 204.435 | H28: =IFERROR(VLOOKUP(D28,Calcs!B:AB,11,FALSE),"") -> 204.435
B29: =IFERROR(VLOOKUP(D29,Calcs!B:G,3,FALSE),"") -> Floor Padding - 69" x 72" x 2" V1 Folding Mat - 2 Sections | D29: FLEX69722 | F29: 1 | G29: =IFERROR(VLOOKUP(D29,Calcs!B:N,12,FALSE),"") -> 574.09 | H29: =IFERROR(VLOOKUP(D29,Calcs!B:AB,11,FALSE),"") -> 574.09
B30: =IFERROR(VLOOKUP(D30,Calcs!B:G,3,FALSE),"") -> Equipment Rack (Frame Mounted) | D30: FLEX-RACK | F30: 1 | G30: =IFERROR(VLOOKUP(D30,Calcs!B:N,12,FALSE),"") -> 107.25 | H30: =IFERROR(VLOOKUP(D30,Calcs!B:AB,11,FALSE),"") -> 107.25 | J30: Summit Flex: Pro-Pack
B31: =IF(K31>0.99,J31,"") -> Leather Belt (Size - TBD) | D31: FLEX-BELT-TBD | F31: =K31 -> 1 | G31: =L31 -> 226.88 | H31: =M31 -> 226.88 | J31: =Calcs!D275 -> Leather Belt (Size - TBD) | K31: 1 | L31: =IF(K31<0.99,K31,Calcs!L275) -> 226.88 | M31: =K31*L31 -> 226.88 | N31: ONLY 1 BELT IS INCLUDED IN PRO-PACK
B32: =IF(K32>0.99,J32,"") | D32: FLEX-BELT-XXS | F32: =K32 -> 0 | G32: =L32 -> 0 | H32: =M32 -> 0 | J32: =Calcs!D276 -> Leather Belt (Size - XX Small) | K32: 0 | L32: =IF(K32<0.99,K32,Calcs!L276) -> 0 | M32: =K32*L32 -> 0
B33: =IF(K33>0.99,J33,"") | D33: FLEX-BELT-XS | F33: =K33 -> 0 | G33: =L33 -> 0 | H33: =M33 -> 0 | J33: =Calcs!D277 -> Leather Belt (Size - X Small) | K33: 0 | L33: =IF(K33<0.99,K33,Calcs!L277) -> 0 | M33: =K33*L33 -> 0
B34: =IF(K34>0.99,J34,"") | D34: FLEX-BELT-S | F34: =K34 -> 0 | G34: =L34 -> 0 | H34: =M34 -> 0 | J34: =Calcs!D278 -> Leather Belt (Size - Small) | K34: 0 | L34: =IF(K34<0.99,K34,Calcs!L278) -> 0 | M34: =K34*L34 -> 0
B35: =IF(K35>0.99,J35,"") | D35: FLEX-BELT-M | F35: =K35 -> 0 | G35: =L35 -> 0 | H35: =M35 -> 0 | J35: =Calcs!D279 -> Leather Belt (Size - Medium) | K35: 0 | L35: =IF(K35<0.99,K35,Calcs!L279) -> 0 | M35: =K35*L35 -> 0
B36: =IF(K36>0.99,J36,"") | D36: FLEX-BELT-L | F36: =K36 -> 0 | G36: =L36 -> 0 | H36: =M36 -> 0 | J36: =Calcs!D280 -> Leather Belt (Size - Large) | K36: 0 | L36: =IF(K36<0.99,K36,Calcs!L280) -> 0 | M36: =K36*L36 -> 0
B37: =IF(K37>0.99,J37,"") | D37: FLEX-BELT-XL | F37: =K37 -> 0 | G37: =L37 -> 0 | H37: =M37 -> 0 | J37: =Calcs!D281 -> Leather Belt (Size - X Large) | K37: 0 | L37: =IF(K37<0.99,K37,Calcs!L281) -> 0 | M37: =K37*L37 -> 0
B38: =IF(K38>0.99,J38,"") | D38: FLEX-BELT-XXL | F38: =K38 -> 0 | G38: =L38 -> 0 | H38: =M38 -> 0 | J38: =Calcs!D282 -> Leather Belt (Size - XX Large) | K38: 0 | L38: =IF(K38<0.99,K38,Calcs!L282) -> 0 | M38: =K38*L38 -> 0
B39: =IF(F39>0.99,"Passthrough Freight Charge for Belt(s) / Boot(s)","") -> Passthrough Freight Charge for Belt(s) / Boot(s) | D39: 3RD-FREIGHT | F39: =IF(SUM(F31:F38)>0.99,1,0) -> 1 | G39: =IF(F39>0.9,95,"") -> 95 | H39: =G39 -> 95
B40: =IFERROR(VLOOKUP(D40,Calcs!B:G,3,FALSE),"") -> TheraBungee - 10 Piece Bungee Set | D40: UEU-THERABUNGEE-23 | F40: =IFERROR(VLOOKUP('Flex Pro-Pack'!D40,Calcs!$B$260:$F$295,5,FALSE),"") -> 1 | G40: =IFERROR(VLOOKUP(D40,Calcs!B:N,12,FALSE),"") -> 297.07 | H40: =IFERROR(VLOOKUP(D40,Calcs!B:AB,11,FALSE),"") -> 297.07
B41: =IF(K41>0.99,J41,"") -> Standard Equipment Set - 82 Elements | D41: STANDARD | F41: =K41 -> 1 | G41: =L41 -> 1649.99 | H41: =M41 -> 1649.99 | J41: Standard Equipment Set - 82 Elements | K41: 1 | L41: =IF(K41<0.99,K41,Calcs!L294) -> 1649.99 | M41: =K41*L41 -> 1649.99 | N41: DEFAULT
B42: =IF(K42>0.99,J42,"") | D42: FULL | F42: =K42 -> 0 | G42: =L42 -> 0 | H42: =M42 -> 0 | J42: Full Equipment Set - 132 Elements | K42: 0 | L42: =IF(K42<0.99,K42,Calcs!L295) -> 0 | M42: =K42*L42 -> 0
F43: =IFERROR(VLOOKUP('Flex Pro-Pack'!D43,Calcs!$B$260:$F$295,5,FALSE),"") | G43: =IFERROR(VLOOKUP(D43,Calcs!B:N,12,FALSE),"") | H43: =IFERROR(VLOOKUP(D43,Calcs!B:AB,11,FALSE),"")
B44: PRO-PACK SUBTOTAL | F44: HOLD | H44: =SUM(H24:H42) -> 9984.155
F45: HOLD
B46: ADDITIONAL ITEMS (Optional) | F46: HOLD
B47: Unquoted | F47: UQ-AD | J47: Additional Belts
B48: =IF(K48>0.99,J48,"") | D48: FLEX-BELT-TBD | F48: =K48 -> 0 | G48: =L48 -> 0 | H48: =M48 -> 0 | J48: Leather Belt (Size - TBD) | K48: 0 | L48: =IF(K48<0.99,K48,Calcs!L275) -> 0 | M48: =K48*L48 -> 0
B49: =IF(K49>0.99,J49,"") | D49: FLEX-BELT-XXS | F49: =K49 -> 0 | G49: =L49 -> 0 | H49: =M49 -> 0 | J49: Leather Belt (Size - XX Small) | K49: 0 | L49: =IF(K49<0.99,K49,Calcs!L276) -> 0 | M49: =K49*L49 -> 0
B50: =IF(K50>0.99,J50,"") | D50: FLEX-BELT-XS | F50: =K50 -> 0 | G50: =L50 -> 0 | H50: =M50 -> 0 | J50: Leather Belt (Size - X Small) | K50: 0 | L50: =IF(K50<0.99,K50,Calcs!L277) -> 0 | M50: =K50*L50 -> 0 | S50: =Calcs!O275 -> 0 | T50: =Calcs!P275 -> 0 | U50: =Calcs!Q275 -> 0 | V50: =Calcs!R275 -> 0 | W50: =Calcs!S275 -> 0 | X50: =Calcs!T275 -> 0 | Y50: =Calcs!U275 -> 0
B51: =IF(K51>0.99,J51,"") | D51: FLEX-BELT-S | F51: =K51 -> 0 | G51: =L51 -> 0 | H51: =M51 -> 0 | J51: Leather Belt (Size - Small) | K51: 0 | L51: =IF(K51<0.99,K51,Calcs!L278) -> 0 | M51: =K51*L51 -> 0
B52: =IF(K52>0.99,J52,"") | D52: FLEX-BELT-M | F52: =K52 -> 0 | G52: =L52 -> 0 | H52: =M52 -> 0 | J52: Leather Belt (Size - Medium) | K52: 0 | L52: =IF(K52<0.99,K52,Calcs!L279) -> 0 | M52: =K52*L52 -> 0
B53: =IF(K53>0.99,J53,"") | D53: FLEX-BELT-L | F53: =K53 -> 0 | G53: =L53 -> 0 | H53: =M53 -> 0 | J53: Leather Belt (Size - Large) | K53: 0 | L53: =IF(K53<0.99,K53,Calcs!L280) -> 0 | M53: =K53*L53 -> 0
B54: =IF(K54>0.99,J54,"") | D54: FLEX-BELT-XL | F54: =K54 -> 0 | G54: =L54 -> 0 | H54: =M54 -> 0 | J54: Leather Belt (Size - X Large) | K54: 0 | L54: =IF(K54<0.99,K54,Calcs!L281) -> 0 | M54: =K54*L54 -> 0
B55: =IF(K55>0.99,J55,"") | D55: FLEX-BELT-XXL | F55: =K55 -> 0 | G55: =L55 -> 0 | H55: =M55 -> 0 | J55: Leather Belt (Size - XX Large) | K55: 0 | L55: =IF(K55<0.99,K55,Calcs!L282) -> 0 | M55: =K55*L55 -> 0
B56: SUBTOTAL | F56: HOLD | H56: =SUM(H48:H55) -> 0
F57: HOLD
B58: UNIVERSAL EXERCISE UNIT TRAINING COURSE (Optional) | F58: HOLD
B59: Unquoted | F59: UQ-TC | J59: UEU Training
B60: Summit/PediaSuit UEU Training Course | D60: TRAINING | F60: =K60 -> 0 | G60: =L60 -> 800 | H60: =M60 -> 0 | J60: Training | K60: 0 | L60: 800 | M60: =K60*L60 -> 0
B61: Location: TBD | F61: =F60 -> 0
B62: SUBTOTAL | F62: HOLD | H62: =SUM(H60) -> 0
F63: HOLD
F64: SUBTOTAL: | H64: =H44+H56+H62 -> 9984.155
F65: PRO BUNDLE DISCOUNT: | H65: 758.95
B66: IMPORTANT PROPOSAL DETAILS: This proposal serves as a detailed estimate of the total cost for the products and services outlined and does not constitute an invoice. Once signed and returned, it becomes a binding agreement, confirming acceptance of the order and associated payment terms. A 50% deposit is required to initiate production, with the remaining balance due prior to shipment. The signed proposal may be returned by mail or fax using the contact information provided above. For payments made by credit card, a 3.5% processing fee will be added to the total amount. | F66: CRATING & FREIGHT: | H66: =IF(Discovery!C19="TBD","TBD",Discovery!C19+100) -> TBD
F67: FREIGHT-MATS: | H67: =IF(Discovery!C24="TBD","TBD",Discovery!C24) -> 859.14
F68: ESTIMATED TAX: | H68: =IF(Discovery!C25="TBD","TBD",Discovery!C25) -> 294.07
F69: TOTAL PROPOSAL: | H69: =H64-H65+(IF(H66="TBD",0,H66))+(IF(H67="TBD",0,H67))+(IF(H68="TBD",0,H68)) -> 10378.415
F70: 50% DEPOSIT: | H70: =H69/2 -> 5189.2075
F71: 1
B72: CRATING & FREIGHT FEES: Final crating and freight charges will be calculated and invoiced at the time of shipment based on the actual costs incurred and the rates in effect at that time. Summit makes no representations or warranties, express or implied, regarding the availability or stability of crating costs or freight rates prior to shipment, and Buyer acknowledges and agrees that such charges may increase or decrease between the date of proposal and the shipment date.
B75: Customer Acceptance
B79: Signature | D79: Printed Name | G79: Date
B81: If you have any questions, please contact Bryan Shepherd, 720-457-5500, Bryan@SummitSensory.com

Sheet VLOOKUP - Soar
A1: Summit Soar Frame Type | B1: Units
A2: S1 | B2: 1 | D2: Summit Soar S1 - Mobile Free-Standing Swing Frame w/ Single Cross Beam
A3: S2 | B3: 0 | D3: Summit Soar S2 - Mobile Free-Standing Swing Frame w/ Two Cross Beams
A4: S3 | B4: 0 | D4: Summit Soar S3 - Mobile Free-Standing Swing Frame w/ Three Cross Beams
A5: S1-XL | B5: 0 | D5: Summit Soar S1-XL - Mobile Free-Standing Swing Frame w/ Single Cross Beam (Width: 12')
A6: S2-XL | B6: 0 | D6: Summit Soar S2-XL - Mobile Free-Standing Swing Frame w/ Two Cross Beams (Width: 12')
A7: S3-XL | B7: 0 | D7: Summit Soar S3-XL - Mobile Free-Standing Swing Frame w/ Three Cross Beams (Width: 12')
A9: Summit Soar - Swing Mount Extensions | B9: No
A11: Padding/Column Wrap | B11: Yes
A12: Soar-XL Floor Mat System (138" x 80" x 3.25") - Single Fold | B12: =IF(AND(B11="yes", B5+B6+B7>=1),1,0) -> 0
A13: Soar Floor Mat System (100" x 80" x 3.25") - Single Fold | B13: =IF(AND(B11="yes", B2+B3+B4>=1),1,0) -> 1
A14: Soar Base Beam U Column Wrap (30" x 4.5" x 3.5" x 3.5" x 1.375") | B14: =IF(B11="yes",4,0) -> 4
A15: Gusset Plate Padding | B15: =IF(B11="yes",2,0) -> 2
A16: Soar Column Wrap (60" x 4.5" x 4.5" x 1.375") | B16: =B15 -> 2
A18: Accessories | B18: Units
A19: 3/8 Double Swivel Eye Bolt | B19: 1
A20: Wheelchair Swing Platform - Adult | B20: 1
A21: 2 Hole Heavy Duty Aluminum Swing Hangers | B21: =IF(B20=1,2,0) -> 2
A22: Platform Swing XL (48" x 60") - Holds Up to 500lbs | B22: 0
A23: Bolster Swing | B23: 0
A25: Discount

Sheet Summit Soar Proposal
B1: Summit Sensory Gym
B2: 6150 S Geneva Court | J2: PSF File Name | K2: =B10&" - Summit Soar - PSFv73 - "&TEXT(H9,"MMDDYYYY") -> Soar Autism Center - South Fort Collins - Summit Soar - PSFv73 - 07222026
B3: Englewood, CO 80111 | J3: Proposal File Name | K3: =B10&" - Summit Soar - Proposal "&F9&" - "&TEXT(H9,"MMDDYYYY") -> Soar Autism Center - South Fort Collins - Summit Soar - Proposal SOAR-SS-260722-001 - 07222026
B4: Phone: 720-457-5500
B5: Fax: 720-242-8085
B6: Support@SummitSensory.com
B8: CUSTOMER INFO | F8: =IF(L11="Yes","INVOICE #","PROPOSAL #") -> PROPOSAL # | H8: DATE
B9: =Discovery!B2 -> Tyler Galiotto | F9: ="SOAR-" & UPPER(LEFT(B10,1) & RIGHT(B10,1)) & "-" & TEXT(H9,"yymmdd") & "-" & TEXT( IF(AND(ISNUMBER(K11),K11>0), K11, COUNTIFS($B$10:B10,B10,$H$9:H9,H9) ), "000") -> SOAR-SS-260722-001 | H9: =TODAY() -> 46225
B10: =Discovery!B3 -> Soar Autism Center - South Fort Collins | F10: PROJECT ID # | H10: VALID UNTIL
B11: =Discovery!B4 -> 3801 Automation Way | F11: ="SSG-"&Discovery!B13 -> SSG-12552093278 | H11: =H9+7 -> 46232 | J11: Proposal # Override | K11: 0
B12: =Discovery!B5&" "&Discovery!B6 -> Fort Collins, CO 80525
B15: SENSORY GYM PROPOSAL - PROJECT SCOPE
B16: {=_xlfn.IFS(F21=1,B21,F22=1,B22,F23=1,B23,F24=1,B24,F25=1,B25,F26=1,B26,F27=1,B27)} -> SUMMIT SOAR S1 - MOBILE FREE-STANDING SWING FRAME W/ SINGLE CROSS BEAM
B19: DESCRIPTION | D19: SKU | F19: QTY | G19: UNIT PRICE (USD) | H19: AMOUNT
B20: PRODUCT DESCRIPTION | F20: TITL
B21: =UPPER(IFERROR(VLOOKUP(D21,Calcs!B:F,3,FALSE),"")) -> SUMMIT SOAR S1 - MOBILE FREE-STANDING SWING FRAME W/ SINGLE CROSS BEAM | D21: K-4000 | F21: =IFERROR(VLOOKUP(D21,Calcs!$B$231:$F$247,5,FALSE),"") -> 1 | G21: =IFERROR(VLOOKUP(D21,Calcs!B:Z,11,FALSE),"") -> 3900 | H21: =IF(F21=1,F21*G21,0) -> 3900
B22: =UPPER(IFERROR(VLOOKUP(D22,Calcs!B:F,3,FALSE),"")) | D22: K-4002 | F22: =IFERROR(VLOOKUP(D22,Calcs!$B$231:$F$247,5,FALSE),"") | G22: =IFERROR(VLOOKUP(D22,Calcs!B:Z,11,FALSE),"") | H22: =IF(F22=1,F22*G22,0) -> 0
B23: =UPPER(IFERROR(VLOOKUP(D23,Calcs!B:F,3,FALSE),"")) | D23: SOAR-S2 | F23: =IFERROR(VLOOKUP(D23,Calcs!$B$231:$F$247,5,FALSE),"") | G23: =IFERROR(VLOOKUP(D23,Calcs!B:Z,11,FALSE),"") | H23: =IF(F23=1,F23*G23,0) -> 0
B24: =UPPER(IFERROR(VLOOKUP(D24,Calcs!B:F,3,FALSE),"")) | D24: SOAR-S3 | F24: =IFERROR(VLOOKUP(D24,Calcs!$B$231:$F$247,5,FALSE),"") | G24: =IFERROR(VLOOKUP(D24,Calcs!B:Z,11,FALSE),"") | H24: =IF(F24=1,F24*G24,0) -> 0
B25: =UPPER(IFERROR(VLOOKUP(D25,Calcs!B:F,3,FALSE),"")) | D25: SOAR-S1-XL | F25: =IFERROR(VLOOKUP(D25,Calcs!$B$231:$F$247,5,FALSE),"") | G25: =IFERROR(VLOOKUP(D25,Calcs!B:Z,11,FALSE),"") | H25: =IF(F25=1,F25*G25,0) -> 0
B26: =UPPER(IFERROR(VLOOKUP(D26,Calcs!B:F,3,FALSE),"")) | D26: SOAR-S2-XL | F26: =IFERROR(VLOOKUP(D26,Calcs!$B$231:$F$247,5,FALSE),"") | G26: =IFERROR(VLOOKUP(D26,Calcs!B:Z,11,FALSE),"") | H26: =IF(F26=1,F26*G26,0) -> 0
B27: =UPPER(IFERROR(VLOOKUP(D27,Calcs!B:F,3,FALSE),"")) | D27: SOAR-S3-XL | F27: =IFERROR(VLOOKUP(D27,Calcs!$B$231:$F$247,5,FALSE),"") | G27: =IFERROR(VLOOKUP(D27,Calcs!B:Z,11,FALSE),"") | H27: =IF(F27=1,F27*G27,0) -> 0
B28: DESCRIPTION | F28: 1
B29: The Summit Soar Sensory Swing Frame is a freestanding therapeutic swing frame that is perfect for indoor use. It is designed specifically for multisensory gyms that have low ceilings or are smaller in size. The compact swing frame is constructed of durable and non-corrosive powder-coated steel with safety padding on the uprights and bases. It can support up to 1,000 lbs. and accommodates a variety of therapy swings, including linear and rotational as well as single and double point swings. Note that the mat and swings are not included. Ideal for smaller rooms and rooms with lower ceilings, the Summit Soar provides more than 35 various connection points for a wide variety of therapy swings to be used within the structure. The eyebolts are included for attaching therapy swings, including high back, platform, strap, wheel, and cuddle swings. The Summit Soar can be used in sensory gyms, special ed classrooms, and homes. Occupational therapists use the Summit Soar to administer vestibular, neuro-developmental, and sensory integration swing therapy to clients with ADHD, Autism, and other Sensory Processing Disorders. The Summit Soar Sensory Swing Frame is a responsive, reliable, and transparent partner that stands out from the competition. | F29: 1
F30: 1
F31: 1
F32: 1
F33: 1
F34: 1
F35: 1
F36: 1
F37: 1
F38: 1
B39: SUBTOTAL | F39: 1 | H39: =SUM(H21:H27) -> 3900
F40: 1
B41: SUMMIT SOAR MATS & ACCESSORIES (Optional) | F41: 1
B42: Unquoted | F42: Unquoted
B43: =IFERROR(VLOOKUP(D43,Calcs!$B$231:$F$247,3,FALSE),"") -> Wheelchair Swing Platform - Adult | D43: 382-408 | F43: =IFERROR(VLOOKUP(D43,Calcs!$B$231:$F$247,5,FALSE),"") -> 1 | G43: =IFERROR(VLOOKUP(D43,Calcs!B233:Z247,12,FALSE),"") -> 2110.5 | H43: =IFERROR(VLOOKUP(D43,Calcs!$B$231:$M$247,11,FALSE),"") -> 2110.5
B44: =IF(F43>0.99,"Passthrough Freight Charge (Required)","") -> Passthrough Freight Charge (Required) | D44: 3RD-FREIGHT | E44: *Passthrough Cost | F44: =IF(F43>0.99,1,"") -> 1 | H44: =IF(F44=1,"TBD","") -> TBD
B45: =IFERROR(VLOOKUP(D45,Calcs!$B$231:$F$247,3,FALSE),"") | D45: XL-PLAT | F45: =IFERROR(VLOOKUP(D45,Calcs!$B$231:$F$247,5,FALSE),"") | G45: =IFERROR(VLOOKUP(D45,Calcs!B234:Z248,12,FALSE),"") | H45: =IFERROR(VLOOKUP(D45,Calcs!$B$231:$M$247,11,FALSE),"")
B46: =IFERROR(VLOOKUP(D46,Calcs!$B$231:$F$247,3,FALSE),"") -> 2 Hole Heavy Duty Aluminum Swing Hangers | D46: BSP-041-BLKALUHNGW-SO2 | F46: =IFERROR(VLOOKUP(D46,Calcs!$B$231:$F$247,5,FALSE),"") -> 2 | G46: =IFERROR(VLOOKUP(D46,Calcs!B234:Z248,11,FALSE),"") -> 64.86 | H46: =IFERROR(VLOOKUP(D46,Calcs!$B$231:$M$247,12,FALSE),"") -> 129.72
B47: =IFERROR(VLOOKUP(D47,Calcs!$B$231:$F$247,3,FALSE),"") -> 3/8 Double Swivel Eye Bolt | D47: 6820H-LDD | F47: =IFERROR(VLOOKUP(D47,Calcs!$B$231:$F$247,5,FALSE),"") -> 1 | G47: =IFERROR(VLOOKUP(D47,Calcs!B234:Z248,11,FALSE),"") -> 158.73 | H47: =IFERROR(VLOOKUP(D47,Calcs!$B$231:$M$247,12,FALSE),"") -> 158.73
B48: =IFERROR(VLOOKUP(D48,Calcs!$B$231:$F$247,3,FALSE),"") | D48: CLM325 | F48: =IFERROR(VLOOKUP(D48,Calcs!$B$231:$F$247,5,FALSE),"") | G48: =IFERROR(VLOOKUP(D48,Calcs!B234:Z248,11,FALSE),"") | H48: =IFERROR(VLOOKUP(D48,Calcs!$B$231:$M$247,12,FALSE),"")
B49: =IFERROR(VLOOKUP(D49,Calcs!$B$231:$F$247,3,FALSE),"") -> Soar Floor Mat System (100" x 80" x 3.25") - Single Fold | D49: SSM80100 | F49: =IFERROR(VLOOKUP(D49,Calcs!$B$231:$F$247,5,FALSE),"") -> 1 | G49: =IFERROR(VLOOKUP(D49,Calcs!B234:Z248,11,FALSE),"") -> 1042.5 | H49: =IFERROR(VLOOKUP(D49,Calcs!$B$231:$M$247,12,FALSE),"") -> 1042.5
B50: =IFERROR(VLOOKUP(D50,Calcs!$B$231:$F$247,3,FALSE),"") -> Soar Base Beam U Column Wrap (30" x 4.5" x 3.5" x 3.5" x 1.375") | D50: COLU2812 | F50: =IFERROR(VLOOKUP(D50,Calcs!$B$231:$F$247,5,FALSE),"") -> 4 | G50: =IFERROR(VLOOKUP(D50,Calcs!B235:Z249,11,FALSE),"") -> 178.5 | H50: =IFERROR(VLOOKUP(D50,Calcs!$B$231:$M$247,12,FALSE),"") -> 714
B51: =IFERROR(VLOOKUP(D51,Calcs!$B$231:$F$247,3,FALSE),"") -> Gusset Plate Padding | D51: SFGPC | F51: =IFERROR(VLOOKUP(D51,Calcs!$B$231:$F$247,5,FALSE),"") -> 2 | G51: =IFERROR(VLOOKUP(D51,Calcs!B236:Z250,11,FALSE),"") -> 175.5 | H51: =IFERROR(VLOOKUP(D51,Calcs!$B$231:$M$247,12,FALSE),"") -> 351
B52: =IFERROR(VLOOKUP(D52,Calcs!$B$231:$F$247,3,FALSE),"") -> Soar Column Wrap (60" x 4.5" x 4.5" x 1.375") | D52: COLW2812 | F52: =IFERROR(VLOOKUP(D52,Calcs!$B$231:$F$247,5,FALSE),"") -> 2 | G52: =IFERROR(VLOOKUP(D52,Calcs!B237:Z251,11,FALSE),"") -> 221.13 | H52: =IFERROR(VLOOKUP(D52,Calcs!$B$231:$M$247,12,FALSE),"") -> 442.26
B53: SUBTOTAL | F53: SUB | H53: =SUM(H43:H52) -> 4948.71
F54: HOLD
B55: CUSTOM COLOR UPCHARGE | F55: 1
B56: Premium Powder Color | D56: POW-1000 | F56: 1 | H56: {=_xlfn.IFS(Discovery!B44="Cardinal",0,Discovery!B44="Prismatic",350,Discovery!B44="Prismatic-Other",Discovery!B45)} -> 0
F57: HOLD
F58: SUBTOTAL: | H58: =H39+H53+H56 -> 8848.71
F59: DISCOUNT: | H59: =Calcs!Q243 -> 0
F60: =IFERROR(IF(Calcs!Q243>0.01,"DISCOUNT EXPIRATION:",""),"") | H60: =IFERROR(IF(Calcs!Q243>0.01,(H9+6),""),"")
B61: IMPORTANT PROPOSAL DETAILS: This proposal serves as a detailed estimate of the total cost for the products and services outlined and does not constitute an invoice. Once signed and returned, it becomes a binding agreement, confirming acceptance of the order and associated payment terms. A 50% deposit is required to initiate production, with the remaining balance due prior to shipment. The signed proposal may be returned by mail or fax using the contact information provided above. For payments made by credit card, a 3.5% processing fee will be added to the total amount. | F61: CRATING & FREIGHT: | H61: =IF(Discovery!B19="TBD","TBD",Discovery!B19) -> TBD
F62: FREIGHT-MATS: | H62: =IF(Discovery!B24="TBD","TBD",Discovery!B24) -> 859.14
F63: ESTIMATED TAX: | H63: =IF(Discovery!B25="TBD","TBD",Discovery!B25) -> 294.07
F64: TOTAL PROPOSAL: | H64: =H58-H59+(IF(H63="TBD",0,H63))+(IF(H61="TBD",0,H61))+(IF(H62="TBD",0,H62)) -> 10001.92
B66: CRATING & FREIGHT FEES: Final crating and freight charges will be calculated and invoiced at the time of shipment based on the actual costs incurred and the rates in effect at that time. Summit makes no representations or warranties, express or implied, regarding the availability or stability of crating costs or freight rates prior to shipment, and Buyer acknowledges and agrees that such charges may increase or decrease between the date of proposal and the shipment date.
B69: Customer Acceptance
B71: Signature | C71: Printed Name | G71: Date
B73: If you have any questions, please contact Bryan Shepherd, 720-457-5500, Bryan@SummitSensory.com

Sheet Summit Scape Proposal
B1: Summit Sensory Gym
B2: 6150 S Geneva Court | J2: PSF File Name | K2: =B10&" - Summit Soar - PSFv73 - "&TEXT(H9,"MMDDYYYY") -> Soar Autism Center - South Fort Collins - Summit Soar - PSFv73 - 07222026
B3: Englewood, CO 80111 | J3: Proposal File Name | K3: =B10&" - Summit Soar - Proposal "&F9&" - "&TEXT(H9,"MMDDYYYY") -> Soar Autism Center - South Fort Collins - Summit Soar - Proposal SOAR-SS-260722-001 - 07222026
B4: Phone: 720-457-5500
B5: Fax: 720-242-8085
B6: Support@SummitSensory.com
B8: CUSTOMER INFO | F8: =IF(L11="Yes","INVOICE #","PROPOSAL #") -> PROPOSAL # | H8: DATE
B9: =Discovery!B2 -> Tyler Galiotto | F9: ="SOAR-" & UPPER(LEFT(B10,1) & RIGHT(B10,1)) & "-" & TEXT(H9,"yymmdd") & "-" & TEXT( IF(AND(ISNUMBER(K11),K11>0), K11, COUNTIFS($B$10:B10,B10,$H$9:H9,H9) ), "000") -> SOAR-SS-260722-001 | H9: =TODAY() -> 46225
B10: =Discovery!B3 -> Soar Autism Center - South Fort Collins | F10: PROJECT ID # | H10: VALID UNTIL
B11: =Discovery!B4 -> 3801 Automation Way | F11: ="SSG-"&Discovery!B13 -> SSG-12552093278 | H11: =H9+7 -> 46232 | J11: Proposal # Override | K11: 0
B12: =Discovery!B5&" "&Discovery!B6 -> Fort Collins, CO 80525
B13: =ZAPIER!J2 -> 5203895979
B15: PROJECT SCOPE
B16: Summit Scape: Complete Sensory & Calming Room
B19: DESCRIPTION | D19: SKU | F19: QTY | G19: UNIT PRICE (USD) | H19: AMOUNT
B20: PRODUCT DESCRIPTION | F20: TITL
B21: =IFERROR(VLOOKUP(D21,Calcs!B:D,3,FALSE),"") | D21: SP9012 | F21: =IFERROR(VLOOKUP(D21,Calcs!$B$312:$E$328,4,FALSE),"")
B22: =IFERROR(VLOOKUP(D22,Calcs!B:D,3,FALSE),"") | D22: 5805-PB | F22: =IFERROR(VLOOKUP(D22,Calcs!$B$312:$E$328,4,FALSE),"")
B23: =IFERROR(VLOOKUP(D23,Calcs!B:D,3,FALSE),"") | D23: 303805 | F23: =IFERROR(VLOOKUP(D23,Calcs!$B$312:$E$328,4,FALSE),"")
B24: =IFERROR(VLOOKUP(D24,Calcs!B:D,3,FALSE),"") | D24: RPAL6868 | F24: =IFERROR(VLOOKUP(D24,Calcs!$B$312:$E$328,4,FALSE),"")
B25: =IFERROR(VLOOKUP(D25,Calcs!B:D,3,FALSE),"") | F25: =IFERROR(VLOOKUP(D25,Calcs!$B$312:$E$328,4,FALSE),"") | G25: =IFERROR(VLOOKUP(D25,Calcs!B:Z,11,FALSE),"")
B26: =IFERROR(VLOOKUP(D26,Calcs!B:D,3,FALSE),"") | F26: =IFERROR(VLOOKUP(D26,Calcs!$B$312:$E$328,4,FALSE),"") | G26: =IFERROR(VLOOKUP(D26,Calcs!B:Z,11,FALSE),"")
B27: =IFERROR(VLOOKUP(D27,Calcs!B:D,3,FALSE),"") | F27: =IFERROR(VLOOKUP(D27,Calcs!$B$312:$E$328,4,FALSE),"") | G27: =IFERROR(VLOOKUP(D27,Calcs!B:Z,11,FALSE),"")
B28: =IFERROR(VLOOKUP(D28,Calcs!B:D,3,FALSE),"") | F28: =IFERROR(VLOOKUP(D28,Calcs!$B$312:$E$328,4,FALSE),"")
B29: =IFERROR(VLOOKUP(D29,Calcs!B:D,3,FALSE),"") | F29: =IFERROR(VLOOKUP(D29,Calcs!$B$312:$E$328,4,FALSE),"")
B30: =IFERROR(VLOOKUP(D30,Calcs!B:D,3,FALSE),"") | F30: =IFERROR(VLOOKUP(D30,Calcs!$B$312:$E$328,4,FALSE),"")
B31: =IFERROR(VLOOKUP(D31,Calcs!B:D,3,FALSE),"") | F31: =IFERROR(VLOOKUP(D31,Calcs!$B$312:$E$328,4,FALSE),"")
B32: =IFERROR(VLOOKUP(D32,Calcs!B:D,3,FALSE),"") | F32: =IFERROR(VLOOKUP(D32,Calcs!$B$312:$E$328,4,FALSE),"")
B33: =IFERROR(VLOOKUP(D33,Calcs!B:D,3,FALSE),"") | F33: =IFERROR(VLOOKUP(D33,Calcs!$B$312:$E$328,4,FALSE),"")
B34: =IFERROR(VLOOKUP(D34,Calcs!B:D,3,FALSE),"") | F34: =IFERROR(VLOOKUP(D34,Calcs!$B$312:$E$328,4,FALSE),"")
B35: =IFERROR(VLOOKUP(D35,Calcs!B:D,3,FALSE),"") | F35: =IFERROR(VLOOKUP(D35,Calcs!$B$312:$E$328,4,FALSE),"")
B36: =IFERROR(VLOOKUP(D36,Calcs!B:D,3,FALSE),"") | D36: INTERIOR | F36: =IFERROR(VLOOKUP(D36,Calcs!$B$312:$E$328,4,FALSE),"")
B37: =IFERROR(VLOOKUP(D37,Calcs!B:D,3,FALSE),"") | F37: =IFERROR(VLOOKUP(D37,Calcs!$B$312:$E$328,4,FALSE),"")
B38: =IFERROR(VLOOKUP(D38,Calcs!B:D,3,FALSE),"") | F38: =IFERROR(VLOOKUP(D38,Calcs!$B$312:$E$328,4,FALSE),"")
B39: SUBTOTAL | F39: 1 | H39: =Calcs!J331 -> 0
F40: 1
B41: SUMMIT FOUNDATION SYSTEM (Highly Recommended - Optional) - Enhanced Flooring Protection | F41: 1
B42: Unquoted | F42: Unquoted
B43: Summit Foundation System | F43: =IFERROR(VLOOKUP(D43,Calcs!$B$231:$F$247,5,FALSE),"") | G43: =IFERROR(VLOOKUP(D43,Calcs!B233:Z247,12,FALSE),"") | H43: =IFERROR(VLOOKUP(D43,Calcs!$B$231:$M$247,11,FALSE),"")
B44: =IFERROR(VLOOKUP(D44,Calcs!B:D,3,FALSE),"") | D44: GRPMAT158 | F44: =IFERROR(VLOOKUP(D44,Calcs!$B$312:$E$328,4,FALSE),"") | G44: =IFERROR(VLOOKUP(D44,Calcs!$B$312:$I$328,8,FALSE),"") | H44: =IFERROR(VLOOKUP(D44,Calcs!$B$312:$M$347,9,FALSE),"")
B45: *ASTM Impact Standards for Falls Up to 4 Feet | F45: =IFERROR(VLOOKUP(D45,Calcs!$B$312:$E$328,4,FALSE),"") | G45: =IFERROR(VLOOKUP(D45,Calcs!$B$312:$I$328,8,FALSE),"") | H45: =IFERROR(VLOOKUP(D45,Calcs!$B$312:$M$347,9,FALSE),"")
B46: =IFERROR(VLOOKUP(D46,Calcs!B:D,3,FALSE),"") | D46: BR158 | F46: =IFERROR(VLOOKUP(D46,Calcs!$B$312:$E$328,4,FALSE),"") | G46: =IFERROR(VLOOKUP(D46,Calcs!$B$312:$I$328,8,FALSE),"") | H46: =IFERROR(VLOOKUP(D46,Calcs!$B$312:$M$347,9,FALSE),"")
B47: SUBTOTAL | F47: SUB | H47: =SUM(H43:H46) -> 0
F48: HOLD
F49: SUBTOTAL: | H49: =H39+H47 -> 0
F50: DISCOUNT: | H50: =Calcs!Q243 -> 0
B51: IMPORTANT PROPOSAL DETAILS: This proposal serves as a detailed estimate of the total cost for the products and services outlined and does not constitute an invoice. Once signed and returned, it becomes a binding agreement, confirming acceptance of the order and associated payment terms. A 50% deposit is required to initiate production, with the remaining balance due prior to shipment. The signed proposal may be returned by mail or fax using the contact information provided above. For payments made by credit card, a 3.5% processing fee will be added to the total amount. | F51: =IFERROR(IF(Calcs!Q243>0.01,"DISCOUNT EXPIRATION:",""),"") | H51: =IFERROR(IF(Calcs!Q243>0.01,(H9+6),""),"")
F52: CRATING & FREIGHT: | H52: =IF(Discovery!B19="TBD","TBD",Discovery!B19+100) -> TBD
F53: FREIGHT-MATS: | H53: =IF(Discovery!B24="TBD","TBD",Discovery!B24+50) -> 909.14
F54: ESTIMATED TAX: | H54: =IF(Discovery!B25="TBD","TBD",Discovery!B25) -> 294.07
F55: TOTAL PROPOSAL: | H55: =H49-H50+(IF(H54="TBD",0,H54))+(IF(H52="TBD",0,H52))+(IF(H53="TBD",0,H53)) -> 1203.21
B59: Customer Acceptance
B61: Signature | C61: Printed Name | G61: Date
B63: If you have any questions, please contact Bryan Shepherd, 720-457-5500, Bryan@SummitSensory.com

Sheet TrolleyPO
D1: PURCHASE ORDER
A2: Summit Sensory Gym | E2: DATE | H2: Filename: | I2: =A10&" PO "&E5 -> Productive Tool Products PO 07222026-SSG80525
A3: 6150 S Geneva Court | E3: =TODAY() -> 46225
A4: Englewood, Co 80111 | E4: PURCHASE ORDER NO.
A5: Phone: 720-457-5500 | E5: =CONCATENATE(TEXT(TODAY(),"mmddyyyy")&"-SSG"&Discovery!B6) -> 07222026-SSG80525
A6: Fax: 720-242-8085 | E6: CUSTOMER NO.
A7: Support@SummitSensory.com | E7: ="SSG"&Discovery!B6 -> SSG80525
A9: VENDOR | D9: SHIP TO
A10: Productive Tool Products | D10: Goldberg Brothers, Inc.
A11: 1075 Headquarters Park Drive | D11: Attention: Grant Golesh
A12: Fenton, MO 63026 | D12: ="Order: "&"Inventory 6/16" -> Order: Inventory 6/16
A13: Phone: 636-305-1200 | D13: 10488 W Centennial Rd Suite 100
A14: Fax: 636-305-1202 | D14: Littleton, CO 80127
D15: Phone: (303) 321-1099
A17: SHIPPING METHOD | B17: SHIPPING TERMS | C17: SHIP VIA | D17: PAYMENT | E17: DELIVERY DATE
A18: Contact Grant Golesh (grantg@goldbergbrothers.com) for FedEx shipping Label
A20: ITEM NO. | B20: DESCRIPTION | C20: QTY | D20: UNIT PRICE | E20: TOTAL
A21: TR2000-A09 | B21: 9' of Aluminum enclosed rail 550lbs. max weight with end cap holes | C21: 14 | D21: =lists!M39 -> 193.16 | E21: =C21*D21 -> 2704.24
A23: TR2000-A07 | B23: 7' of Aluminum enclosed rail 550lbs. max weight with end cap holes | C23: 0 | D23: =lists!M41 -> 151.2 | E23: =C23*D23 -> 0
C24: SPACE
A25: TRT2001 | B25: Trolley for TR2000 rail | C25: 14 | D25: =lists!M42 -> 93.49 | E25: =C25*D25 -> 1308.86
C26: SPACE
A27: TRN2016 | B27: End Cap for TR2000 rail | C27: 28 | D27: =lists!M43 -> 46.75 | E27: =C27*D27 -> 1309
C28: SPACE
A29: TRH2005 | B29: Universal Threaded Rod Hanger | C29: 42 | D29: =lists!M44 -> 99.66 | E29: =C29*D29 -> 4185.72
C30: SPACE
C31: SPACE
A32: Remarks / Instructions: | C32: SPACE | D32: SUBTOTAL | E32: =SUM(E21:E31) -> 9507.82
C33: SPACE | D33: DISCOUNT | E33: 0
C34: SUBTOTAL LESS DISCOUNT | E34: =E32-E33 -> 9507.82
C35: SPACE | D35: TOTAL | E35: =E34 -> 9507.82
C36: SPACE
C37: SPACE
A38: AUTHORIZED SIGNATURE | D38: DATE: | E38: =TODAY() -> 46225

Sheet lists
A1: Gym Type | B1: Gym Shape | C1: Gym Package | D1: Base Plate Shields | E1: Crating | F1: Powder Brand | I1: FABRICATOR PRICING | K1: PRICING | P1: Product Line
A2: Commercial | B2: Square | C2: Everest | D2: Yes | F2: Cardinal | J2: Fabricators--> | K2: Dakotaland | L2: Goldberg | M2: Productive Tool Products | N2: Selling Price | O2: Mark Up | P2: Summit Adventure
A3: Clinic | B3: Rectangle | C3: K2 | D3: No | F3: Prismatic | I3: A-2245 | J3: Vertical Tall <80 w/Gusset | K3: 427 | L3: 242.5 | P3: Summit Flex
A4: Home | B4: Custom | C4: Lien | F4: Prismatic-Other | I4: A-2241 | J4: Corner Post <80 1-Way Weld Assembly | L4: 73 | P4: Summit Soar
C5: Custom | I5: A-2242 | J5: Corner Post <80 2-Way Weld Assembly | K5: 181 | L5: 76.5
I6: A-2243 | J6: Corner Post <80 3-Way Weld Assembly | K6: 237 | L6: 97
I7: A-2244 | J7: Corner Post <80 4-Way Weld Assembly | K7: 309 | L7: 101
I8: A-2225 | J8: Mid Span 1-Way Saddle Alt Weld Assembly | K8: 110 | L8: 46
I9: A-2253 | J9: Single Leg Inner Ladder Sleeve Footless Weld Assembly | K9: 94 | L9: 65.5
I10: A-2248 | J10: Double Leg Ladder Sleeve Weld Assembly | K10: 116.7 | L10: 79
I11: A-2246 | J11: Vertical Tall <80 w/Gussets, Rungs & Handles | K11: 447 | L11: 242.5
I12: P-2545 | J12: 5' Full Bay HSS Member Alt w/ Logo | L12: 150
I13: P-2206 | J13: 6' Full Bay HSS Member Alt w/Logo | L13: 150
I14: P-2207 | J14: 7' Full Bay HSS Member Alt w/Logo | L14: 150
I15: A-2408 | J15: 8' HALF BAY <80 HSS MEMBER ALT W/LOGO | K15: 221 | L15: 190
I16: A-2409 | J16: 9' HALF BAY <80 HSS MEMBER W/SPLICES & HDWE | K16: 224 | L16: 200
I17: A-2410 | J17: 10' HALF BAY <90 HSS MEMBER W/SPLICES & HDWE | K17: 327 | L17: 200
I18: P-2124 | J18: Accessory Saddle w/Logo | K18: 48 | L18: 51
I19: P-2018 | J19: Trolley Bar | K19: 150 | L19: 14
I20: P-2330 | J20: Monkey Bar w/ 4 Threaded Holes | K20: 24 | L20: 20.5
I21: P-2531 | J21: Ladder Leg Footless | K21: 203 | L21: 97.5
I22: P-2024 | J22: Zip Line Hss Tube | K22: 58 | L22: 20
I23: P-2025 | J23: Trolley Bar Plate | K23: 71 | L23: 12
I24: P-2027 | J24: Base Plate Shield | K24: 36 | L24: 25
I25: P-2028 | J25: BASE PLATE SHIELD | L25: 25
I26: P-2102 | J26: MONKEY BAR W/THREADS | L26: 20
I27: P-2216 | J27: 6' FULL BAY MONKEY BAR HSS MEMBER ALT W/LOGO | L27: 150
I28: P-2217 | J28: 7' FULL BAY MONKEY BAR HSS MEMBER ALT W/LOGO | L28: 150
I29: A-2418 | J29: 8' HALF BAY <80 MONKEY BAR HSS MEMBER ALT W/LOGO | L29: 190
I30: A-2419 | J30: 9' HALF BAY <80 MONKEY BAR HSS W/SPLICES & HDWE | L30: 200
I31: A-2420 | J31: 10' HALF BAY <90 MONKEY BAR HSS W/SPLICES & HDWE | L31: 200
I32: P-2500 | J32: CLIMBING WALL SHIELD | L32: 52
I33: P-2501 | J33: LADDER TOP SHIELD 90 DEGREE | L33: 52
I34: P-2502 | J34: LADDER TOP SHIELD 50 DEGREE | L34: 52
I35: A-2349 | J35: WELD ASSY; EXTENDED LADDER RUNG FOR STEAMROLLER | L35: 81
I36: P-2513 | J36: SUMMIT FLEX TROLLEY RAIL REAR BRACKET | L36: 30
I37: P-2526 | J37: HARNESS SPREADER BAR - SUMMIT FLEX -TRS | L37: 10.5
I38: TR2000-A10 | J38: 10' Aluminum enclosed rail 550lbs. max weight | M38: 215.1
I39: TR2000-A09 | J39: 9' Aluminum enclosed rail 550lbs. max weight | M39: 193.16
I40: TR2000-A08 | J40: 8' Aluminum enclosed rail 550lbs. max weight | M40: 170.72
I41: TR2000-A07 | J41: 7' Aluminum enclosed rail 550lbs. max weight | M41: 151.2
I42: TRT2001 | J42: Trolley for TR2000 rail | M42: 93.49
I43: TRN2016 | J43: End Cap for TR2000 rail | M43: 46.75
I44: TRH2005 | J44: Universal Threaded Rod Hanger | M44: 99.66
I45: SSG-SA-CFM | J45: Adventure Climbing Wall - Frame Mounted (Includes Climbing Holds) | L45: 825
I46: SSG-SA-CWM | J46: Adventure Climbing Wall - Wall Mounted-Metal Studs (Includes Climbing Holds) | L46: 1062
I47: K-5000 | J47: Ball Rack Kit with Hardware | L47: 192
I48: A-2530 | J48: ADVENTURE ZIPLINE COLLAR STIFFENER WELD ASSY | L48: 53
H51: Bagged Letters
H52: AD | I52: 6820H-LAD | J52: PLAYGROUND HANDLES, GATE HANDLES 1 EACH | L52: 15
H53: Z | I53: 6820H-LZ-1 | J53: RED HEAD TRUBOLT 1/2 X 4.25 WEDGE ANCHOR EACH | L53: 1.5
H54: DD | I54: 6820H-LDD | J54: 3/8 SWIVEL EYE BOLT (AAC BRKT SWIVEL OPTION) | L54: 81.06 | N54: 158.73 | O54: =(N54/L54)-1 -> 0.95817913
H55: AC | I55: 6820H-LAC-G | J55: EYE BOLT; 3/8-16 X .75 LENGTH | L55: 6
H56: P | I56: 6820H-LP | J56: EYE BOLT; 1/2-13 X 4 LENGTH | L56: 8.95
H57: Y | I57: 6820H-LY | J57: EYE BOLT; 1/4-20 X 2 LENGTH | L57: 6.5
H58: E | I58: 6820H-LE-G | J58: HITCH PIN SWIVEL LOCK 1/2 X 3-1/2 | L58: 28.91
H59: C | I59: 6820H-LC | J59: HEX NYLON INSERT LOCK NUT, ZINC PLATED GRADE 5 STEEL, 1/2-13 | L59: 0.34
H60: X | I60: 6820H-LX | J60: FLAT SHOULDER ROD END BOLT 5/16-18 X 1 SHANK THREAD | L60: 15.5
H61: F | I61: 6820H-LF | J61: HEX NYLON INSERT LOCK NUT, ZINC PLATED GRADE 5 STEEL, 3/8-16 | L61: 0.25
H62: B | I62: 6820H-LB | J62: WASHER 1/2 FLAT Zinc plated grade 5 steel | L62: 0.18
H63: A | I63: 6820H-LA | J63: HEX BOLT, ZINC PLATED GRADE 5 STEEL, 1/2-13 X 4-1/2" | L63: 1
H64: AG | I64: 6820H-LAG | J64: HEX BOLT, ZINC PLATED GRADE 5 STEEL, 1/2-13 X 4" | L64: 0.95
H65: H | I65: 6820H-LH | J65: TAP BOLT, ZINC PLATED GRADE 5 STEEL, 3/8-16 X 2-1/4" | L65: 0.55
H66: G | I66: 6820H-LG | J66: TAP BOLT, ZINC PLATED GRADE 5 STEEL, 3/8-16 X 1-3/4" | L66: 0.4
... H91: AN | I91: 6820H-LAN | J91: 60" Multi-Pocket Black Sling | L91: 22.4925
I92: SSG-SA-SWIVEL-EYE | J92: SUMMIT ADVENTURE STAND ALONE SWING & SWIVEL EYEBOLT | L92: 100.06 | N92: =L92*1.96 -> 196.1176 | O92: =(N92/L92)-1 -> 0.96
H97: RESILITE PADDING | L97: RESILITE | U97: Width (Inches) | V97: Length (Inches) | W97: Total SQ (Inches) | X97: Total Sq Ft | Y97: Price Per SQ Ft
I98: SSM80100 | J98: 100" x 80" x 3.25" Single-Fold CLM Style Mat | L98: 750
I99: COLW2812 | J99: 60" x 3-1/2" x 3-1/2" x 1.375" Column Wrap | L99: 95
I100: COLU2812 | J100: 30" x 3-1/2" x 3-1/2" x 3-1/2" x 1.375" Column Wrap | L100: 76
I101: SFGPC | J101: Custom Gusset Plate Pads - See Drawing | L101: 100
I102: SSFLEX69722 | L102: 284
I103: CLM325 | J103: Soar-XL Floor Mat System (138" x 80" x 3.25") - Single Fold | L103: 1032
I104: SSUSP72 | J104: Adventure U Shaped Column Wrap Ladder Leg (72" x 2" x 3.875" x 2" x 1.375" ) | L104: 120

Sheet ZAPIER
A1: Sequence | B1: Project ID | C1: Point of Contact | D1: Customer Organization | E1: Address | F1: City | G1: State | H1: Zip | I1: Country | J1: Phone | K1: Email
A2: 12552093278 | B2: 12552093278 | C2: Tyler Galiotto | D2: Soar Autism Center - South Fort Collins | E2: 3801 Automation Way | F2: Fort Collins | G2: CO | H2: 80525 | I2: United States | J2: 5203895979 | O2: 524.81 | P2: 173.74
A4: Proper
A5: =PROPER(A2) -> 12552093278 | B5: =PROPER(B2) -> 12552093278 | C5: =PROPER(C2) -> Tyler Galiotto | D5: =D2 -> Soar Autism Center - South Fort Collins | E5: =E2 -> 3801 Automation Way | F5: =PROPER(F2) -> Fort Collins | G5: =G2 -> CO | H5: =H2 -> 80525 | I5: =PROPER(I2) -> United States | J5: =PROPER(J2) -> 5203895979 | K5: =IF(K2=0,"",K2)

Sheet Estimated Dates
A1: Color Type | B1: Cardinal | C1: {=_xlfn.IFS(B1="cardinal",0,B1="Prismatic",7,B1="","")} -> 0
A2: Proposal Signature Date | B2: =TODAY() -> 46225
A3: Estimated Deposit Date | B3: =TODAY() -> 46225
B5: Adventure - Standard | C5: Adventure - Custom | D5: Soar - Standard | E5: Flex - Standard | G5: Summit Sensory Gym - Anticipated Delivery Windows
A6: Proposal Signature | B6: =$B$2 -> 46225 | C6: =$B$2 -> 46225 | D6: =$B$2 -> 46225 | E6: =$B$2 -> 46225
A7: Deposit Date | B7: =$B$3 -> 46225 | C7: =$B$3 -> 46225 | D7: =$B$3 -> 46225 | E7: =$B$3 -> 46225 | H7: Scenario 1
G8: Proposal Signature Date | H8: =B2 -> 46225
A9: Sent to Manufacturing | B9: =$B$7 -> 46225 | C9: =C7+3 -> 46228 | D9: =$B$7 -> 46225 | E9: =$B$7 -> 46225 | G9: Deposit Date | H9: =B3 -> 46225
A10: Color Selection - Extra Days | B10: =B9+$C$1 -> 46225 | C10: =C9+$C$1 -> 46228 | D10: =D9+$C$1 -> 46225 | E10: =E9+$C$1 -> 46225
G11: Delivery Estimates | H11: Date Range
A12: Production | G12: Structure (5-6 weeks) + shipping | H12: =H9+35 -> 46260 | I12: =H12+7 -> 46267
A13: Structure (Estimate - 35 Days) | B13: =B10+35 -> 46260 | C13: =C10+35 -> 46263 | D13: =D10+35 -> 46260 | E13: =E10+35 -> 46260 | G13: Mats & Column Wraps (8-10 weeks) + shipping | H13: =H9+56 -> 46281 | I13: =H13+14 -> 46295
A14: Shipping (Estimate - 3 Days) | B14: =B13+3 -> 46263 | C14: =C13+3 -> 46266 | D14: =D13+3 -> 46263 | E14: =E13+3 -> 46263
G15: * It should be noted that we base our delivery dates on when we receive the initial order deposit. Once the deposit and frame/mat colors are received, we will then push the order into manufacturing.
A16: Mats & Padding (Estimate - 63 Days) | B16: =B9+63 -> 46288 | C16: =C9+63 -> 46291 | D16: =D9+63 -> 46288 | E16: =E9+63 -> 46288
A17: Shipping (Estimate - 4 Days) | B17: =B16+4 -> 46292 | C17: =C16+4 -> 46295 | D17: =D16+4 -> 46292 | E17: =E16+4 -> 46292
A19: Estimated Delivery Date
A20: Structure | B20: =B14 -> 46263 | C20: =C14 -> 46266 | D20: =D14 -> 46263 | E20: =E14 -> 46263
A21: Mats & Padding | B21: =B17 -> 46292 | C21: =C17 -> 46295 | D21: =D17 -> 46292 | E21: =E17 -> 46292
A23: Estimated Order to Delivery Days
A24: Structure | B24: =B20-B6 -> 38 | C24: =C20-C6 -> 41 | D24: =D20-D6 -> 38 | E24: =E20-E6 -> 38
A25: Mats | B25: =B21-B7 -> 67 | C25: =C21-C7 -> 70 | D25: =D21-D7 -> 67 | E25: =E21-E7 -> 67

Sheet Payment Schedule

Sheet Resilite Mat Cost List
A1: Resilite Custom Mat Pricing
A2: Resilite Price Per Sq Ft | C2: =B18+2 -> 13.78
A3: SSG Price Per Sq Ft | C3: =C2*H3 -> 20.67 | F3: Mark Up | H3: 1.5
A5: Resilite Custom Mat Segments & Pricing
A6: Segment | C6: Width | D6: Length | F6: Total St Ft | H6: Resilite Price | I6: SSG Price | J6: Gross Margin
A7: 1 | C7: 6 | D7: 16 | F7: =C7*D7 -> 96 | H7: =F7*$C$2 -> 1322.88 | I7: =F7*$C$3 -> 1984.32 | J7: =I7-H7 -> 661.44
A8: 2 | C8: 3 | D8: 12 | F8: =C8*D8 -> 36 | H8: =F8*$C$2 -> 496.08 | I8: =F8*$C$3 -> 744.12 | J8: =I8-H8 -> 248.04
A9: =A8+1 -> 3 | C9: 3 | D9: 12 | F9: =C9*D9 -> 36 | H9: =F9*$C$2 -> 496.08 | I9: =F9*$C$3 -> 744.12 | J9: =I9-H9 -> 248.04
A10: =A9+1 -> 4 | F10: =C10*D10 -> 0 | H10: =F10*$C$2 -> 0 | I10: =F10*$C$3 -> 0 | J10: =I10-H10 -> 0
A11: =A10+1 -> 5 | F11: =C11*D11 -> 0 | H11: =F11*$C$2 -> 0 | I11: =F11*$C$3 -> 0 | J11: =I11-H11 -> 0
A12: =A11+1 -> 6 | F12: =C12*D12 -> 0 | H12: =F12*$C$2 -> 0 | I12: =F12*$C$3 -> 0 | J12: =I12-H12 -> 0
A13: =A12+1 -> 7 | F13: =C13*D13 -> 0 | H13: =F13*$C$2 -> 0 | I13: =F13*$C$3 -> 0 | J13: =I13-H13 -> 0
A14: =A13+1 -> 8 | F14: =C14*D14 -> 0 | H14: =F14*$C$2 -> 0 | I14: =F14*$C$3 -> 0 | J14: =I14-H14 -> 0
A15: Total | F15: =SUM(F7:F14) -> 168 | H15: =SUM(H7:H14) -> 2315.04 | I15: =SUM(I7:I14) -> 3472.56 | J15: =SUM(J7:J14) -> 1157.52
A17: Floor Pad Height (Inches) | B17: Resilite Cost | C17: Weight Per Sq Ft
A18: 3.25 | B18: 11.78 | C18: 1.3
A19: 2 | B19: 7.65 | C19: 0.75
A21: SKU | B21: Yes / No | C21: Width | D21: Length | E21: Height | F21: Total Sq Ft | G21: Cost Per Sq Ft | H21: Resilite Price | I21: SSG Price | J21: Total Ship Weight | L21: Width (Inches) | M21: Length (Inches) | N21: SQ Inches | O21: Total Sq Ft
A22: R-SSA-0808CLM | C22: 8 | D22: 8 | E22: 3.25 | F22: =O22 -> 84.027778 | G22: =VLOOKUP(E22,$A$18:$B$19,2,FALSE) -> 11.78 | H22: =ROUND(F22*G22,2) -> 989.85 | I22: =ROUND(H22*1.4,2) -> 1385.79 | J22: =IF(E22=3.25,ROUND(F22*$C$18,0),ROUND(F22*$C$19,0)) -> 109 | L22: =(C22*12)+14 -> 110 | M22: =(D22*12)+14 -> 110 | N22: =L22*M22 -> 12100 | O22: =N22/144 -> 84.027778
A23: R-SSA-0806CLM | C23: 8 | D23: 6 | E23: 3.25 | F23: =O23 -> 65.694444 | G23: =VLOOKUP(E23,$A$18:$B$19,2,FALSE) -> 11.78 | H23: =ROUND(F23*G23,2) -> 773.88 | I23: =ROUND(H23*1.4,2) -> 1083.43 | J23: =IF(E23=3.25,ROUND(F23*$C$18,0),ROUND(F23*$C$19,0)) -> 85 | L23: =(C23*12)+14 -> 110 | M23: =(D23*12)+14 -> 86 | N23: =L23*M23 -> 9460 | O23: =N23/144 -> 65.694444
A24: R-SSA-0909CLM | B24: Yes | C24: 9 | D24: 9 | E24: 3.25 | F24: =O24 -> 103.36111 | G24: =VLOOKUP(E24,$A$18:$B$19,2,FALSE) -> 11.78 | H24: =ROUND(F24*G24,2) -> 1217.59 | I24: =ROUND(H24*1.4,2) -> 1704.63 | J24: =IF(E24=3.25,ROUND(F24*$C$18,0),ROUND(F24*$C$19,0)) -> 134 | L24: =(C24*12)+14 -> 122 | M24: =(D24*12)+14 -> 122 | N24: =L24*M24 -> 14884 | O24: =N24/144 -> 103.36111
A25: R-SSA-0908CLM | C25: 9 | D25: 8 | E25: 3.25 | F25: =O25 -> 93.194444 | G25: =VLOOKUP(E25,$A$18:$B$19,2,FALSE) -> 11.78 | H25: =ROUND(F25*G25,2) -> 1097.83 | I25: =ROUND(H25*1.4,2) -> 1536.96 | J25: =IF(E25=3.25,ROUND(F25*$C$18,0),ROUND(F25*$C$19,0)) -> 121 | L25: =(C25*12)+14 -> 122 | M25: =(D25*12)+14 -> 110 | N25: =L25*M25 -> 13420 | O25: =N25/144 -> 93.194444
A26: R-SSA-0907CLM | C26: 9 | D26: 7 | E26: 3.25 | F26: =O26 -> 83.027778 | G26: =VLOOKUP(E26,$A$18:$B$19,2,FALSE) -> 11.78 | H26: =ROUND(F26*G26,2) -> 978.07 | I26: =ROUND(H26*1.4,2) -> 1369.3 | J26: =IF(E26=3.25,ROUND(F26*$C$18,0),ROUND(F26*$C$19,0)) -> 108 | L26: =(C26*12)+14 -> 122 | M26: =(D26*12)+14 -> 98 | N26: =L26*M26 -> 11956 | O26: =N26/144 -> 83.027778
A27: R-SSA-1010CLM | C27: 10 | D27: 10 | E27: 3.25 | F27: =O27 -> 124.69444 | G27: =VLOOKUP(E27,$A$18:$B$19,2,FALSE) -> 11.78 | H27: =ROUND(F27*G27,2) -> 1468.9 | I27: =ROUND(H27*1.4,2) -> 2056.46 | J27: =IF(E27=3.25,ROUND(F27*$C$18,0),ROUND(F27*$C$19,0)) -> 162 | L27: =(C27*12)+14 -> 134 | M27: =(D27*12)+14 -> 134 | N27: =L27*M27 -> 17956 | O27: =N27/144 -> 124.69444 | T27: =O27 -> 124.69444 | U27: 1740 | V27: =U27/T27 -> 13.95411
A28: R-SSA-1009CLM | C28: 10 | D28: 9 | E28: 3.25 | F28: =O28 -> 113.52778 | G28: =VLOOKUP(E28,$A$18:$B$19,2,FALSE) -> 11.78 | H28: =ROUND(F28*G28,2) -> 1337.36 | I28: =ROUND(H28*1.4,2) -> 1872.3 | J28: =IF(E28=3.25,ROUND(F28*$C$18,0),ROUND(F28*$C$19,0)) -> 148 | L28: =(C28*12)+14 -> 134 | M28: =(D28*12)+14 -> 122 | N28: =L28*M28 -> 16348 | O28: =N28/144 -> 113.52778
A29: R-SSA-1008CLM | C29: 10 | D29: 8 | E29: 3.25 | F29: =O29 -> 102.36111 | G29: =VLOOKUP(E29,$A$18:$B$19,2,FALSE) -> 11.78 | H29: =ROUND(F29*G29,2) -> 1205.81 | I29: =ROUND(H29*1.4,2) -> 1688.13 | J29: =IF(E29=3.25,ROUND(F29*$C$18,0),ROUND(F29*$C$19,0)) -> 133 | L29: =(C29*12)+14 -> 134 | M29: =(D29*12)+14 -> 110 | N29: =L29*M29 -> 14740 | O29: =N29/144 -> 102.36111
A30: R-SSA-1007CLM | C30: 10 | D30: 7 | E30: 3.25 | F30: =O30 -> 91.194444 | G30: =VLOOKUP(E30,$A$18:$B$19,2,FALSE) -> 11.78 | H30: =ROUND(F30*G30,2) -> 1074.27 | I30: =ROUND(H30*1.4,2) -> 1503.98 | J30: =IF(E30=3.25,ROUND(F30*$C$18,0),ROUND(F30*$C$19,0)) -> 119 | L30: =(C30*12)+14 -> 134 | M30: =(D30*12)+14 -> 98 | N30: =L30*M30 -> 13132 | O30: =N30/144 -> 91.194444
A31: R-SSA-1006CLM | C31: 10 | D31: 6 | E31: 3.25 | F31: =O31 -> 80.027778 | G31: =VLOOKUP(E31,$A$18:$B$19,2,FALSE) -> 11.78 | H31: =ROUND(F31*G31,2) -> 942.73 | I31: =ROUND(H31*1.4,2) -> 1319.82 | J31: =IF(E31=3.25,ROUND(F31*$C$18,0),ROUND(F31*$C$19,0)) -> 104 | L31: =(C31*12)+14 -> 134 | M31: =(D31*12)+14 -> 86 | N31: =L31*M31 -> 11524 | O31: =N31/144 -> 80.027778
A32: R-SSA-2010CLM | C32: 20 | D32: 10 | E32: 3.25 | F32: =O32 -> 236.36111 | G32: =VLOOKUP(E32,$A$18:$B$19,2,FALSE) -> 11.78 | H32: =ROUND(F32*G32,2) -> 2784.33 | I32: =ROUND(H32*1.4,2) -> 3898.06 | J32: =IF(E32=3.25,ROUND(F32*$C$18,0),ROUND(F32*$C$19,0)) -> 307 | L32: =(C32*12)+14 -> 254 | M32: =(D32*12)+14 -> 134 | N32: =L32*M32 -> 34036 | O32: =N32/144 -> 236.36111 | T32: =O32 -> 236.36111 | U32: 3390 | V32: =U32/T32 -> 14.342461
A33: R-SSA-2008CLM | C33: 20 | D33: 8 | E33: 3.25 | F33: =O33 -> 194.02778 | G33: =VLOOKUP(E33,$A$18:$B$19,2,FALSE) -> 11.78 | H33: =ROUND(F33*G33,2) -> 2285.65 | I33: =ROUND(H33*1.4,2) -> 3199.91 | J33: =IF(E33=3.25,ROUND(F33*$C$18,0),ROUND(F33*$C$19,0)) -> 252 | L33: =(C33*12)+14 -> 254 | M33: =(D33*12)+14 -> 110 | N33: =L33*M33 -> 27940 | O33: =N33/144 -> 194.02778
A34: R-SSA-1610CLM | C34: 16 | D34: 10 | E34: 3.25 | F34: =O34 -> 191.69444 | G34: =VLOOKUP(E34,$A$18:$B$19,2,FALSE) -> 11.78 | H34: =ROUND(F34*G34,2) -> 2258.16 | I34: =ROUND(H34*1.4,2) -> 3161.42 | J34: =IF(E34=3.25,ROUND(F34*$C$18,0),ROUND(F34*$C$19,0)) -> 249 | L34: =(C34*12)+14 -> 206 | M34: =(D34*12)+14 -> 134 | N34: =L34*M34 -> 27604 | O34: =N34/144 -> 191.69444
A35: R-SSA-2007CLM | C35: 20 | D35: 7 | E35: 3.25 | F35: =O35 -> 172.86111 | G35: =VLOOKUP(E35,$A$18:$B$19,2,FALSE) -> 11.78 | H35: =ROUND(F35*G35,2) -> 2036.3 | I35: =ROUND(H35*1.4,2) -> 2850.82 | J35: =IF(E35=3.25,ROUND(F35*$C$18,0),ROUND(F35*$C$19,0)) -> 225 | L35: =(C35*12)+14 -> 254 | M35: =(D35*12)+14 -> 98 | N35: =L35*M35 -> 24892 | O35: =N35/144 -> 172.86111
A36: R-SSA-88CLM-2 | C36: 8 | D36: 8 | E36: 2 | F36: =O36 -> 84.027778 | G36: =VLOOKUP(E36,$A$18:$B$19,2,FALSE) -> 7.65 | H36: =ROUND(F36*G36,2) -> 642.81 | I36: =ROUND(H36*1.4,2) -> 899.93 | J36: =IF(E36=3.25,ROUND(F36*$C$18,0),ROUND(F36*$C$19,0)) -> 63 | L36: =(C36*12)+14 -> 110 | M36: =(D36*12)+14 -> 110 | N36: =L36*M36 -> 12100 | O36: =N36/144 -> 84.027778
A37: R-SSA-86CLM-2 | C37: 8 | D37: 6 | E37: 2 | F37: =O37 -> 65.694444 | G37: =VLOOKUP(E37,$A$18:$B$19,2,FALSE) -> 7.65 | H37: =ROUND(F37*G37,2) -> 502.56 | I37: =ROUND(H37*1.4,2) -> 703.58 | J37: =IF(E37=3.25,ROUND(F37*$C$18,0),ROUND(F37*$C$19,0)) -> 49 | L37: =(C37*12)+14 -> 110 | M37: =(D37*12)+14 -> 86 | N37: =L37*M37 -> 9460 | O37: =N37/144 -> 65.694444
A38: R-SSA-99CLM-2 | C38: 9 | D38: 9 | E38: 2 | F38: =O38 -> 103.36111 | G38: =VLOOKUP(E38,$A$18:$B$19,2,FALSE) -> 7.65 | H38: =ROUND(F38*G38,2) -> 790.71 | I38: =ROUND(H38*1.4,2) -> 1106.99 | J38: =IF(E38=3.25,ROUND(F38*$C$18,0),ROUND(F38*$C$19,0)) -> 78 | L38: =(C38*12)+14 -> 122 | M38: =(D38*12)+14 -> 122 | N38: =L38*M38 -> 14884 | O38: =N38/144 -> 103.36111
A39: R-SSA-98CLM-2 | C39: 9 | D39: 8 | E39: 2 | F39: =O39 -> 93.194444 | G39: =VLOOKUP(E39,$A$18:$B$19,2,FALSE) -> 7.65 | H39: =ROUND(F39*G39,2) -> 712.94 | I39: =ROUND(H39*1.4,2) -> 998.12 | J39: =IF(E39=3.25,ROUND(F39*$C$18,0),ROUND(F39*$C$19,0)) -> 70 | L39: =(C39*12)+14 -> 122 | M39: =(D39*12)+14 -> 110 | N39: =L39*M39 -> 13420 | O39: =N39/144 -> 93.194444
A40: R-SSA-97CLM-2 | C40: 9 | D40: 7 | E40: 2 | F40: =O40 -> 83.027778 | G40: =VLOOKUP(E40,$A$18:$B$19,2,FALSE) -> 7.65 | H40: =ROUND(F40*G40,2) -> 635.16 | I40: =ROUND(H40*1.4,2) -> 889.22 | J40: =IF(E40=3.25,ROUND(F40*$C$18,0),ROUND(F40*$C$19,0)) -> 62 | L40: =(C40*12)+14 -> 122 | M40: =(D40*12)+14 -> 98 | N40: =L40*M40 -> 11956 | O40: =N40/144 -> 83.027778
A41: R-SSA-1010CLM-2 | C41: 10 | D41: 10 | E41: 2 | F41: =O41 -> 124.69444 | G41: =VLOOKUP(E41,$A$18:$B$19,2,FALSE) -> 7.65 | H41: =ROUND(F41*G41,2) -> 953.91 | I41: =ROUND(H41*1.4,2) -> 1335.47 | J41: =IF(E41=3.25,ROUND(F41*$C$18,0),ROUND(F41*$C$19,0)) -> 94 | L41: =(C41*12)+14 -> 134 | M41: =(D41*12)+14 -> 134 | N41: =L41*M41 -> 17956 | O41: =N41/144 -> 124.69444
A42: R-SSA-1009CLM-2 | C42: 10 | D42: 9 | E42: 2 | F42: =O42 -> 113.52778 | G42: =VLOOKUP(E42,$A$18:$B$19,2,FALSE) -> 7.65 | H42: =ROUND(F42*G42,2) -> 868.49 | I42: =ROUND(H42*1.4,2) -> 1215.89 | J42: =IF(E42=3.25,ROUND(F42*$C$18,0),ROUND(F42*$C$19,0)) -> 85 | L42: =(C42*12)+14 -> 134 | M42: =(D42*12)+14 -> 122 | N42: =L42*M42 -> 16348 | O42: =N42/144 -> 113.52778
A43: R-SSA-1008CLM-2 | C43: 10 | D43: 8 | E43: 2 | F43: =O43 -> 102.36111 | G43: =VLOOKUP(E43,$A$18:$B$19,2,FALSE) -> 7.65 | H43: =ROUND(F43*G43,2) -> 783.06 | I43: =ROUND(H43*1.4,2) -> 1096.28 | J43: =IF(E43=3.25,ROUND(F43*$C$18,0),ROUND(F43*$C$19,0)) -> 77 | L43: =(C43*12)+14 -> 134 | M43: =(D43*12)+14 -> 110 | N43: =L43*M43 -> 14740 | O43: =N43/144 -> 102.36111
A44: R-SSA-1007CLM-2 | C44: 10 | D44: 7 | E44: 2 | F44: =O44 -> 91.194444 | G44: =VLOOKUP(E44,$A$18:$B$19,2,FALSE) -> 7.65 | H44: =ROUND(F44*G44,2) -> 697.64 | I44: =ROUND(H44*1.4,2) -> 976.7 | J44: =IF(E44=3.25,ROUND(F44*$C$18,0),ROUND(F44*$C$19,0)) -> 68 | L44: =(C44*12)+14 -> 134 | M44: =(D44*12)+14 -> 98 | N44: =L44*M44 -> 13132 | O44: =N44/144 -> 91.194444
... A49: R-SSA-1610CLM-2 | C49: 20 | D49: 7 | E49: 2 | F49: =O49 -> 172.86111 | G49: =VLOOKUP(E49,$A$18:$B$19,2,FALSE) -> 7.65 | H49: =ROUND(F49*G49,2) -> 1322.39 | I49: =ROUND(H49*1.4,2) -> 1851.35 | J49: =IF(E49=3.25,ROUND(F49*$C$18,0),ROUND(F49*$C$19,0)) -> 130 | L49: =(C49*12)+14 -> 254 | M49: =(D49*12)+14 -> 98 | N49: =L49*M49 -> 24892 | O49: =N49/144 -> 172.86111
A50: COLW2812 | H50: 102 | I50: =ROUND(H50*1.4,2) -> 142.8
A51: COLU2812 | H51: 81 | I51: =ROUND(H51*1.4,2) -> 113.4
A52: SFGPC | H52: 107 | I52: =ROUND(H52*1.4,2) -> 149.8
A53: SSM80100 | C53: =L53/12 -> 8.3333333 | D53: =M53/12 -> 6.6666667 | E53: 3.25 | F53: =O53 -> 55.555556 | G53: =VLOOKUP(E53,$A$18:$B$19,2,FALSE) -> 11.78 | H53: =ROUND(F53*G53,2) -> 654.44 | I53: =ROUND(H53*1.4,2) -> 916.22 | L53: 100 | M53: 80 | N53: =L53*M53 -> 8000 | O53: =N53/144 -> 55.555556 | Q53: 802 | R53: =Q53/F53 -> 14.436
A54: SSCW67 | H54: 142.31 | I54: =ROUND(H54*1.4,2) -> 199.23
A55: SSUSP72 | H55: 128.4 | I55: =ROUND(H55*1.4,2) -> 179.76
A56: SSUSP67 | H56: 149.8 | I56: =ROUND(H56*1.4,2) -> 209.72

Sheet Travel Proposal
A1: ve | B1: Summit Sensory Gym | J1: PSF File Name | K1: =B10&" - "&VLOOKUP!F1&" - PSFv73 - "&TEXT(H9,"MMDDYYYY") -> Soar Autism Center - South Fort Collins - SQ-2MBL2T-10x10 - PSFv73 - 07222026
B2: 6150 S Geneva Court | J2: Proposal File Name | K2: =B10&" - "&VLOOKUP!F1&" - Proposal "&F9&" - "&TEXT(H9,"MMDDYYYY") -> Soar Autism Center - South Fort Collins - SQ-2MBL2T-10x10 - Proposal ADV-SS-260722-001 - 07222026
B3: Englewood, CO 80111
B4: Phone: 720-457-5500
B5: Fax: 720-242-8085
B6: Support@SummitSensory.com
B8: CUSTOMER INFO | F8: PROPOSAL | H8: DATE
B9: =Discovery!B2 -> Tyler Galiotto | F9: ="ADV-" & UPPER(LEFT(B10,1) & RIGHT(B10,1)) & "-" & TEXT(H9,"yymmdd") & "-" & TEXT( IF(AND(ISNUMBER(K11),K11>0), K11, COUNTIFS($B$10:B10,B10,$H$9:H9,H9) ), "000") -> ADV-SS-260722-001 | H9: =TODAY() -> 46225
B10: =Discovery!B3 -> Soar Autism Center - South Fort Collins | F10: PROJECT ID # | H10: VALID UNTIL
B11: =Discovery!B4 -> 3801 Automation Way | F11: ="SSG-"&Discovery!B13 -> SSG-12552093278 | H11: =H9+6 -> 46231 | J11: Proposal # Override | K11: 0
B12: =Discovery!B5&" "&Discovery!B6 -> Fort Collins, CO 80525 | F12: FREIGHT WEIGHT (lbs) | H12: =Calcs!I176+100 -> 1376.862
B13: =Discovery!B10 -> United States | J13: Freight Weight Conversion
J14: lbs | K14: =H12 -> 1376.862
B15: TRAVEL PROPOSAL DETAILS | J15: kgs | K15: =K14/2.205 -> 624.42721
B16: PROFESSIONAL ONSITE INSTALLATION & SETUP OF SUMMIT SENSORY GYM PRODUCTS
B19: DESCRIPTION
B20: INSTALLATION TEAM SIZE | H20: 2
B22: ON-SITE INSTALLATION - ESTIMATED TRAVEL COST SUMMARY | F22: QTY | G22: ESTIMATED COST | H22: AMOUNT
B23: Airfare - Estimate | F23: 1 | G23: 600 | H23: =F23*G23 -> 600 | J23: Sioux Falls - Airline Estimated Cost | K23: 600
B24: All flight costs are estimated and subject to adjustment based on actual airfare at the time of purchase.
B25: ="Flight Details:Sioux Falls, SD to "&ZAPIER!G5&", "&ZAPIER!H5 -> Flight Details:Sioux Falls, SD to CO, 80525
B26: Airfare - Estimate | J26: Denver - Airline Estimated Cost | K26: 600
B27: All flight costs are estimated and subject to adjustment based on actual airfare at the time of purchase.
B28: ="Flight Details:Denver, CO to "&ZAPIER!G5&", "&ZAPIER!H5 -> Flight Details:Denver, CO to CO, 80525
B51: SUBTOTAL | F51: SUB | H51: =SUM(H23:H50) -> 600
F52: HOLD
B53: DUAL TROLLEY SYSTEM (Optional) | F53: TITL
B54: Unquoted | F54: UQ-TR
B55: =IFERROR(VLOOKUP(D55,Calcs!B:G,3,FALSE),"") -> Trolley Bar | D55: P-2018 | F55: =IFERROR(VLOOKUP(D55,Calcs!B:F,5,FALSE),"") -> 1 | G55: =IFERROR(VLOOKUP(D55,Calcs!B:M,11,FALSE),"") -> 32.2 | H55: =IFERROR(VLOOKUP(D55,Calcs!B:Z,12,FALSE),"") -> 32.2
B56: =IFERROR(VLOOKUP(D56,Calcs!B:G,3,FALSE),"") -> Trolley Bar Plate | D56: P-2025 | F56: =IFERROR(VLOOKUP(D56,Calcs!B:F,5,FALSE),"") -> 2 | G56: =IFERROR(VLOOKUP(D56,Calcs!B:M,11,FALSE),"") -> 27.6 | H56: =IFERROR(VLOOKUP(D56,Calcs!B:Z,12,FALSE),"") -> 55.2
B57: =IFERROR(VLOOKUP(D57,Calcs!B:G,3,FALSE),"") | D57: SSG-TR-A10 | F57: =IFERROR(VLOOKUP(D57,Calcs!B:F,5,FALSE),"") | G57: =IFERROR(VLOOKUP(D57,Calcs!B:M,11,FALSE),"") | H57: =IFERROR(VLOOKUP(D57,Calcs!B:Z,12,FALSE),"")
B58: =IFERROR(VLOOKUP(D58,Calcs!B:G,3,FALSE),"") -> 9' Aluminum Enclosed Rail 550lbs. Max Weight | D58: SSG-TR-A09 | F58: =IFERROR(VLOOKUP(D58,Calcs!B:F,5,FALSE),"") -> 2 | G58: =IFERROR(VLOOKUP(D58,Calcs!B:M,11,FALSE),"") -> 445.05 | H58: =IFERROR(VLOOKUP(D58,Calcs!B:Z,12,FALSE),"") -> 890.1
B59: =IFERROR(VLOOKUP(D59,Calcs!B:G,3,FALSE),"") | D59: SSG-TR-A08 | F59: =IFERROR(VLOOKUP(D59,Calcs!B:F,5,FALSE),"") | G59: =IFERROR(VLOOKUP(D59,Calcs!B:M,11,FALSE),"") | H59: =IFERROR(VLOOKUP(D59,Calcs!B:Z,12,FALSE),"")
B60: =IFERROR(VLOOKUP(D60,Calcs!B:G,3,FALSE),"") | D60: SSG-TR-A07 | F60: =IFERROR(VLOOKUP(D60,Calcs!B:F,5,FALSE),"") | G60: =IFERROR(VLOOKUP(D60,Calcs!B:M,11,FALSE),"") | H60: =IFERROR(VLOOKUP(D60,Calcs!B:Z,12,FALSE),"")
B61: =IFERROR(VLOOKUP(D61,Calcs!B:G,3,FALSE),"") -> Universal Threaded Rod Hanger | D61: SSG-TRH | F61: =IFERROR(VLOOKUP(D61,Calcs!B:F,5,FALSE),"") -> 6 | G61: =IFERROR(VLOOKUP(D61,Calcs!B:M,11,FALSE),"") -> 259.9 | H61: =IFERROR(VLOOKUP(D61,Calcs!B:Z,12,FALSE),"") -> 1559.4
B62: =IFERROR(VLOOKUP(D62,Calcs!B:G,3,FALSE),"") -> End Cap for Rail | D62: SSG-TRN | F62: =IFERROR(VLOOKUP(D62,Calcs!B:F,5,FALSE),"") -> 4 | G62: =IFERROR(VLOOKUP(D62,Calcs!B:M,11,FALSE),"") -> 131.1 | H62: =IFERROR(VLOOKUP(D62,Calcs!B:Z,12,FALSE),"") -> 524.4
B63: =IFERROR(VLOOKUP(D63,Calcs!B:G,3,FALSE),"") -> Trolley for Rail | D63: SSG-TRT | F63: =IFERROR(VLOOKUP(D63,Calcs!B:F,5,FALSE),"") -> 2 | G63: =IFERROR(VLOOKUP(D63,Calcs!B:M,11,FALSE),"") -> 243.8 | H63: =IFERROR(VLOOKUP(D63,Calcs!B:Z,12,FALSE),"") -> 487.6
B64: SUBTOTAL | F64: SUB | H64: =SUM(H55:H63) -> 3548.9
F65: HOLD
B66: SENSORY GYM ACCESSORIES (Optional) | F66: TITL
B67: Unquoted | F67: UQ-OP
B68: Summit Adventure Slide System | F68: =IF(SUM(F69:F72)>=1,1,"")
B69: =IFERROR(VLOOKUP(D69,Calcs!B:G,3,FALSE),"") | C69: * | D69: A-2216 | E69: *Popular Addition | F69: =IFERROR(VLOOKUP(D69,Calcs!B:F,5,FALSE),"") | G69: =IFERROR(VLOOKUP(D69,Calcs!B:M,11,FALSE),"") | H69: =IFERROR(VLOOKUP(D69,Calcs!B:N,12,FALSE),"")
B70: =IFERROR(VLOOKUP(D70,Calcs!B:G,3,FALSE),"") | D70: WS8203 | E70: *Passthrough Cost | F70: =IFERROR(VLOOKUP(D70,Calcs!B:F,5,FALSE),"") | G70: =IFERROR(VLOOKUP(D70,Calcs!B:M,11,FALSE),"") | H70: =IFERROR(VLOOKUP(D70,Calcs!B:N,12,FALSE),"")
B71: =IF(F70>0.99,"Passthrough Freight Charge (Required)","") -> Passthrough Freight Charge (Required) | D71: 3RD-FREIGHT-SLIDE | E71: *Passthrough Cost | F71: =F70 | H71: =IF(F71=1,"TBD","")
B72: =IFERROR(VLOOKUP(D72,Calcs!B:G,3,FALSE),"") | D72: 150045 | F72: =IFERROR(VLOOKUP(D72,Calcs!B:F,5,FALSE),"") | G72: =IFERROR(VLOOKUP(D72,Calcs!B:M,11,FALSE),"") | H72: =IFERROR(VLOOKUP(D72,Calcs!B:N,12,FALSE),"")
B73: =IF(F69>0.99,"Passthrough Freight Charge (Required)","") -> Passthrough Freight Charge (Required) | D73: 3RD-FREIGHT | E73: *Passthrough Cost | F73: =F72 | H73: =IF(Discovery!B20="TBD","TBD",Discovery!B20*1.15) -> 0
B74: =IFERROR(VLOOKUP(D74,Calcs!B:G,3,FALSE),"") | D74: A-2349 | F74: =IFERROR(VLOOKUP(D74,Calcs!B:F,5,FALSE),"") | G74: =IFERROR(VLOOKUP(D74,Calcs!B:M,11,FALSE),"") | H74: =IFERROR(VLOOKUP(D74,Calcs!B:N,12,FALSE),"")
B75: Climbing Wall & Safety Accessories | F75: =IF(SUM(F76:F78)>=1,1,"") -> 1
B76: =IFERROR(VLOOKUP(D76,Calcs!B:G,3,FALSE),"") | C76: * | D76: SSG-SA-CFM | E76: *Popular Addition | F76: =IFERROR(VLOOKUP(D76,Calcs!B:F,5,FALSE),"") | G76: =IFERROR(VLOOKUP(D76,Calcs!B:M,11,FALSE),"") | H76: =IFERROR(VLOOKUP(D76,Calcs!B:N,12,FALSE),"")
B77: =IFERROR(VLOOKUP(D77,Calcs!B:G,3,FALSE),"") | D77: P-2500 | F77: =IFERROR(VLOOKUP(D77,Calcs!B:F,5,FALSE),"") | G77: =IFERROR(VLOOKUP(D77,Calcs!B:M,11,FALSE),"") | H77: =IFERROR(VLOOKUP(D77,Calcs!B:N,12,FALSE),"")
B78: =IFERROR(VLOOKUP(D78,Calcs!B:G,3,FALSE),"") -> Adventure Climbing Wall - Wall Mounted-Metal Studs (Includes Climbing Holds) | D78: SSG-SA-CWM | E78: *Popular Addition | F78: =IFERROR(VLOOKUP(D78,Calcs!B:F,5,FALSE),"") -> 1 | G78: =IFERROR(VLOOKUP(D78,Calcs!B:M,11,FALSE),"") -> 2442.6 | H78: =IFERROR(VLOOKUP(D78,Calcs!B:N,12,FALSE),"") -> 2442.6
B79: Ladder - Safety Accessories | F79: =IF(SUM(F80)>=1,1,"")
B80: =IFERROR(VLOOKUP(D80,Calcs!B:G,3,FALSE),"") | D80: P-2502 | F80: =IFERROR(VLOOKUP(D80,Calcs!B:F,5,FALSE),"") | G80: =IFERROR(VLOOKUP(D80,Calcs!B:M,11,FALSE),"") | H80: =IFERROR(VLOOKUP(D80,Calcs!B:N,12,FALSE),"")
B81: =IFERROR(VLOOKUP(D81,Calcs!B:G,3,FALSE),"") | D81: K-5000 | F81: =IFERROR(VLOOKUP(D81,Calcs!B:F,5,FALSE),"") | G81: =IFERROR(VLOOKUP(D81,Calcs!B:M,11,FALSE),"") | H81: =IFERROR(VLOOKUP(D81,Calcs!B:N,12,FALSE),"")
B82: =IFERROR(VLOOKUP(D82,Calcs!B:G,3,FALSE),"") | D82: T11412 | F82: =IFERROR(VLOOKUP(D82,Calcs!B:F,5,FALSE),"") | G82: =IFERROR(VLOOKUP(D82,Calcs!B:M,11,FALSE),"") | H82: =IFERROR(VLOOKUP(D82,Calcs!B:N,12,FALSE),"")
B83: =IF(B82="adjustable Indoor Climbing Wall","Adjustable Indoor Climbing Wall - Freight Charge","") | D83: T11412-FREIGHT | F83: =IF(F82=1,1,"") | G83: =IFERROR(VLOOKUP(D83,Calcs!B:M,11,FALSE),"") | H83: =IFERROR(VLOOKUP(D83,Calcs!B:N,12,FALSE),"")
B84: =IFERROR(VLOOKUP(D84,Calcs!B:G,3,FALSE),"") | C84: * | D84: B07V3J9S2R | E84: *Popular Addition | F84: =IFERROR(VLOOKUP(D84,Calcs!B:F,5,FALSE),"") | G84: =IFERROR(VLOOKUP(D84,Calcs!B:M,11,FALSE),"") | H84: =IFERROR(VLOOKUP(D84,Calcs!B:N,12,FALSE),"")
B85: =IFERROR(VLOOKUP(D85,Calcs!B:G,3,FALSE),"") | D85: B07TSDMPNQ | E85: *Popular Addition | F85: =IFERROR(VLOOKUP(D85,Calcs!B:F,5,FALSE),"") | G85: =IFERROR(VLOOKUP(D85,Calcs!B:M,11,FALSE),"") | H85: =IFERROR(VLOOKUP(D85,Calcs!B:N,12,FALSE),"")
B86: =IFERROR(VLOOKUP(D86,Calcs!B:G,3,FALSE),"") | C86: * | D86: B0BGDQF46S | F86: =IFERROR(VLOOKUP(D86,Calcs!B:F,5,FALSE),"") | G86: =IFERROR(VLOOKUP(D86,Calcs!B:M,11,FALSE),"") | H86: =IFERROR(VLOOKUP(D86,Calcs!B:N,12,FALSE),"")
B87: =IFERROR(VLOOKUP(D87,Calcs!B:G,3,FALSE),"") | C87: * | D87: B0193YG8GI | F87: =IFERROR(VLOOKUP(D87,Calcs!B:F,5,FALSE),"") | G87: =IFERROR(VLOOKUP(D87,Calcs!B:M,11,FALSE),"") | H87: =IFERROR(VLOOKUP(D87,Calcs!B:N,12,FALSE),"")
B88: =IFERROR(VLOOKUP(D88,Calcs!B:G,3,FALSE),"") | C88: * | D88: B07MC3144W | F88: =IFERROR(VLOOKUP(D88,Calcs!B:F,5,FALSE),"") | G88: =IFERROR(VLOOKUP(D88,Calcs!B:M,11,FALSE),"") | H88: =IFERROR(VLOOKUP(D88,Calcs!B:N,12,FALSE),"")
B89: =IFERROR(VLOOKUP(D89,Calcs!B:G,3,FALSE),"") | C89: * | D89: B07PQHSZPR | F89: =IFERROR(VLOOKUP(D89,Calcs!B:F,5,FALSE),"") | G89: =IFERROR(VLOOKUP(D89,Calcs!B:M,11,FALSE),"") | H89: =IFERROR(VLOOKUP(D89,Calcs!B:N,12,FALSE),"")
B90: =IFERROR(VLOOKUP(D90,Calcs!B:G,3,FALSE),"") | C90: * | D90: B07ZQZD6WX | F90: =IFERROR(VLOOKUP(D90,Calcs!B:F,5,FALSE),"") | G90: =IFERROR(VLOOKUP(D90,Calcs!B:M,11,FALSE),"") | H90: =IFERROR(VLOOKUP(D90,Calcs!B:N,12,FALSE),"")
B91: =IFERROR(VLOOKUP(D91,Calcs!B:G,3,FALSE),"") | C91: * | D91: B08DTP539F | F91: =IFERROR(VLOOKUP(D91,Calcs!B:F,5,FALSE),"") | G91: =IFERROR(VLOOKUP(D91,Calcs!B:M,11,FALSE),"") | H91: =IFERROR(VLOOKUP(D91,Calcs!B:N,12,FALSE),"")
